Workbook

Sheet README
A1: OI critical review: paper selection and scoring workbook
A3: Purpose | B3: Select papers by a written protocol, score each on a rigor rubric (two raters), log every claim, and analyze the results without rebuilding anything.
A4: Workflow | B4: 1) Check Protocol and Screening_Log. 2) Full-text check the Include and Maybe records; add new records to the log. 3) Rater 1 and Rater 2 score on Scoring without seeing each other's columns. 4) Discuss every DISCUSS cell and overwrite it with the agreed value. 5) Log claims on Claims while reading. 6) Read the tiers on Tiers (set cut-offs first), compare papers within each tier, write the findings per tier, then check the candidate determining factor. 7) Read Analysis.
A5: Sheets | B5: Protocol: criteria and search record. Screening_Log: every record with decision and reason. Flow: PRISMA-style counts. Scoring: one row per empirical paper (9 items, including Replication), with an automatic tier. Scoring_Reviews: reviews, roadmaps and company pages on a 4-item review rubric. Tiers: cut-offs, tier comparison, findings per tier, determining factor. Claims: claims audit. Rubric_Anchors: what 0, 1, 2 mean (empirical and review rubrics). Analysis: item means, Cohen's kappa, COI and peer-review comparisons, claim tags. Codes and Lists: reference values for dropdowns.
A6: Color key | B6: Blue text on yellow fill = team input (edit these). Black text = formula or fixed content (do not overwrite, except DISCUSS cells in the Final block, which you replace with the agreed score).
A7: Pre-filled vs checked | B7: Pre-filled and unverified: screening decisions (abstracts only), claim categories, peer-review status. Taken from the team's OI Notes and not re-checked against PDFs: COI for the five seed papers and claims C01-C11.
A8: Capacity | B8: Scoring holds up to 100 empirical papers (rows 6-105), Scoring_Reviews up to 50, Claims up to 200 rows, Screening_Log up to 400 records. Extend the formula ranges if you go past that.
A9: Stats step | B9: Kappa and group comparisons are computed as soon as Rater 2 scores exist. Weighted kappa and exact tests (Mann-Whitney) need to be run outside the sheet.
A10: What this workbook does not do | B10: It does not score papers. Scores need a person reading the full text; an AI second pass can help flag misreads but should never replace a human rater.
A12: Example row (fictional, for format only; not in any formula range)
A13: Field | B13: Example value
A14: Paper ID / title | B14: example:Doe-2024 / Doe et al. 2024 (EXAMPLE ONLY, not a real paper)
A15: R1 scores SM, UA, CT, CF, EA, RB, TR, CC, RP | B15: 2, 1, 2, 0, NA, 1, 2, 1, 0
A16: R2 scores | B16: 2, 1, 1, 0, NA, 1, 2, 2, 0 (Final block would show DISCUSS for CT and CC)
A17: COI / affiliation | B17: Academic, none declared
A18: Claim row | B18: Learning/adaptation | 'Cultures improve over 5 days' | Demonstrated under constraints | Measured | Comparator: none | n = 8 cultures

Sheet Protocol
A1: Search and selection protocol (v1, written before the searches were run)
A3: Review question | B3: How well supported are published computational, learning, and efficiency claims about brain organoids and neural cultures used as biological computing substrates (organoid intelligence, biocomputing, wetware)?
A4: Why include weak papers | B4: Selection is by 'makes a claim in scope', not by quality. Quality is scored afterwards, so low-rigor and hyped papers stay in the corpus. Screening only for rigor would hide the thing being studied.
A5: Inclusion (all required) | B5: I1: living neural tissue (organoid, 2D culture, assembloid) on an electrode or similar interface used as a computational or learning substrate, OR a review/roadmap/grey source making explicit claims about such systems. I2: at least one explicit claim about (a) computational performance, (b) learning or adaptation, or (c) efficiency (energy, sample, or cost) relative to AI/silicon. I3: enough text accessible to code the rubric items. I4: English; published or posted 2020 onward.
A6: Exclusion codes | B6: See the Codes sheet (E1-E8). Duplicates and preprints of an included paper are logged as E3 and the version of record is kept.
A7: Context sources (not scored) | B7: Codes C1-C4: critiques and skeptical sources, commentary and press (for tracing how claims propagate), OI-specific ethics papers (ethics arm), and comparator literature on AI/neuromorphic energy and sample efficiency.
A8: Paper-index searches (from 2020-01-01 unless noted) | B8: Q1 organoid intelligence biocomputing brain organoids as computational substrate (top 40) Q2 brain organoid reservoir computing learning on multielectrode array (top 40) Q3 in vitro neuronal cultures closed-loop learning game-playing Pong sample efficiency versus reinforcement learning (top 40) Q4 energy efficiency biological neural networks versus silicon computing organoid (top 30) Q5 ethics of organoid intelligence sentience consciousness brain organoid computing (top 30) Q6 FinalSpark Neuroplatform electrophysiological remote access human brain organoids (from 2022, top 15) Q7 Smirnova Hartung organoid intelligence OI roadmap biocomputing (from 2022, top 15) Q8 critique skeptical hype claims synthetic biological intelligence organoid intelligence limitations (from 2022, top 25)
A9: Web search (grey literature) | B9: W1 Cortical Labs CL1 biological computer FinalSpark Unconventional AI whitepaper energy claims (top 10). Company pages and the InsightAce market report are included as grey literature and scored mainly on EA, CC and TR.
A10: Index coverage | B10: The paper index covers PubMed, bioRxiv, medRxiv, arXiv and other scientific sources. Google Scholar, Web of Science and Scopus were not searched; adding at least one of them is the main way to reduce coverage bias.
A11: Citation chaining (not completed) | B11: Attempted citers of Kagan 2022 and Cai 2023 through the index's citation graph; the seed IDs did not resolve and no results came back. Do this by hand with 'Cited by' in Google Scholar or Scopus, then add new records to Screening_Log.
A12: Known gaps | B12: 1) Unconventional AI materials were not found by the search; look at their site and any preprints by hand. 2) The Smirnova 2023 seed was not returned by the index and was added manually. 3) Screening used titles and abstracts only, by one screener, so every Include/Maybe needs a full-text check and a second screener on a ~20% random sample (Screening_Log columns K-L). 4) The search is not exhaustive, so describe the corpus as a systematic-style sample, not a complete census of the field.
A13: Rubric changes | B13: Do not change the rubric midstream without noting the version and date here. Re-score earlier papers if an anchor changes.

Sheet Screening_Log
A1: Screening log (every record, with decision and reason)
A2: Screened on title/abstract only, by a single screener (Claude). Blue-on-yellow cells are for the team: second-screener decision on a random ~20% sample, and any overrides. Counts on the Flow sheet update automatically.
A3: Years left blank where the identifier does not show one; fill in when you open the record.
A5: # | B5: Record ID | C5: Title | D5: Year | E5: Record type | F5: Found via | G5: Decision | H5: Code | I5: Reason (auto from Codes) | J5: Notes | K5: 2nd screener decision | L5: Agree?
A6: 1 | B6: doi:10.1016/j.neuron.2022.09.001 | C6: Kagan et al. In vitro neurons learn and exhibit sentience when embodied in a simulated game-world (DishBrain), Neuron | D6: 2022 | E6: Empirical | F6: Seed; Q3 | G6: Include | H6: I | I6: =IF(H6="","",IFERROR(INDEX(Codes!$B$2:$B$30,MATCH(H6,Codes!$A$2:$A$30,0)),"")) -> Include: empirical paper with a computational, learning, or efficiency claim about living neural tissue as a substrate | J6: Team seed. Index ID pmcid:PMC9747182 | L6: =IF(K6="","",IF(K6=G6,"Y","N"))
A7: 2 | B7: doi:10.1038/s41928-023-01069-w | C7: Cai et al. Brain organoid reservoir computing for artificial intelligence (Brainoware), Nat Electron | D7: 2023 | E7: Empirical | F7: Seed; Q1 | G7: Include | H7: I | I7: =IF(H7="","",IFERROR(INDEX(Codes!$B$2:$B$30,MATCH(H7,Codes!$A$2:$A$30,0)),"")) -> Include: empirical paper with a computational, learning, or efficiency claim about living neural tissue as a substrate | J7: Team seed. Preprint version logged separately as duplicate | L7: =IF(K7="","",IF(K7=G7,"Y","N"))
A8: 3 | B8: doi:10.34133/cbsystems.0336 | C8: Khajehnejad et al. Dynamic network plasticity and sample efficiency in biological neural cultures: comparison with deep RL, Cyborg Bionic Syst | D8: 2025 | E8: Empirical | F8: Seed; Q3 | G8: Include | H8: I | I8: =IF(H8="","",IFERROR(INDEX(Codes!$B$2:$B$30,MATCH(H8,Codes!$A$2:$A$30,0)),"")) -> Include: empirical paper with a computational, learning, or efficiency claim about living neural tissue as a substrate | J8: Team seed; cite 2025 published version. Index ID pmcid:PMC12320521 | L8: =IF(K8="","",IF(K8=G8,"Y","N"))
A9: 4 | B9: doi:10.3389/frai.2024.1376042 | C9: Jordan et al. Open and remotely accessible Neuroplatform for research in wetware computing (FinalSpark), Front AI | D9: 2024 | E9: Empirical | F9: Seed; Q6 | G9: Include | H9: I | I9: =IF(H9="","",IFERROR(INDEX(Codes!$B$2:$B$30,MATCH(H9,Codes!$A$2:$A$30,0)),"")) -> Include: empirical paper with a computational, learning, or efficiency claim about living neural tissue as a substrate | J9: Team seed. Index ID pmcid:PMC11097343 | L9: =IF(K9="","",IF(K9=G9,"Y","N"))
A10: 5 | B10: doi:10.3389/fsci.2023.1017235 | C10: Smirnova et al. Organoid intelligence (OI): the new frontier in biocomputing and intelligence-in-a-dish, Front Sci | D10: 2023 | E10: Review/roadmap | F10: Seed (manual add) | G10: Include | H10: R | I10: =IF(H10="","",IFERROR(INDEX(Codes!$B$2:$B$30,MATCH(H10,Codes!$A$2:$A$30,0)),"")) -> Include: review or roadmap that makes explicit claims about such systems | J10: Team seed. Not returned by index search; added from team notes | L10: =IF(K10="","",IF(K10=G10,"Y","N"))
A11: 6 | B11: pmid:42399712 | C11: Computing inspired by the brain: a journey from algorithms to organoids (Nat Comput Sci) | D11: 2026 | E11: Review/roadmap | F11: Q1 | G11: Include | H11: R | I11: =IF(H11="","",IFERROR(INDEX(Codes!$B$2:$B$30,MATCH(H11,Codes!$A$2:$A$30,0)),"")) -> Include: review or roadmap that makes explicit claims about such systems | L11: =IF(K11="","",IF(K11=G11,"Y","N"))
A12: 7 | B12: arxiv:2503.19770 | C12: Brain Organoid Computing: an Overview | D12: 2025 | E12: Review/roadmap | F12: Q1 | G12: Include | H12: R | I12: =IF(H12="","",IFERROR(INDEX(Codes!$B$2:$B$30,MATCH(H12,Codes!$A$2:$A$30,0)),"")) -> Include: review or roadmap that makes explicit claims about such systems | L12: =IF(K12="","",IF(K12=G12,"Y","N"))
A13: 8 | B13: pmcid:PMC10013972 | C13: First Organoid Intelligence (OI) workshop to form an OI community | D13: 2023 | E13: Review/roadmap | F13: Q1 | G13: Include | H13: R | I13: =IF(H13="","",IFERROR(INDEX(Codes!$B$2:$B$30,MATCH(H13,Codes!$A$2:$A$30,0)),"")) -> Include: review or roadmap that makes explicit claims about such systems | L13: =IF(K13="","",IF(K13=G13,"Y","N"))
A14: 9 | B14: pmcid:PMC10002682 | C14: Brain Organoid Computing for Artificial Intelligence (bioRxiv preprint of Brainoware) | D14: 2023 | E14: Empirical | F14: Q1; Q2 | G14: Exclude | H14: E3 | I14: =IF(H14="","",IFERROR(INDEX(Codes!$B$2:$B$30,MATCH(H14,Codes!$A$2:$A$30,0)),"")) -> Exclude: duplicate or earlier version of an included record (version of record kept) | J14: Preprint of Cai 2023; version of record is the seed record | L14: =IF(K14="","",IF(K14=G14,"Y","N"))
A15: 10 | B15: pmid:37009773 | C15: Organoid intelligence (OI): the ultimate functionality of a brain microphysiological system (ALTEX) | D15: 2023 | E15: Review/roadmap | F15: Q1 | G15: Include | H15: R | I15: =IF(H15="","",IFERROR(INDEX(Codes!$B$2:$B$30,MATCH(H15,Codes!$A$2:$A$30,0)),"")) -> Include: review or roadmap that makes explicit claims about such systems | L15: =IF(K15="","",IF(K15=G15,"Y","N"))
A16: 11 | B16: pmid:38252094 | C16: The Promise and Potential of Brain Organoids | D16: 2024 | E16: Review/roadmap | F16: Q1 | G16: Maybe | H16: M | I16: =IF(H16="","",IFERROR(INDEX(Codes!$B$2:$B$30,MATCH(H16,Codes!$A$2:$A$30,0)),"")) -> Maybe: borderline, needs second screener or full-text check | J16: OI appears to be one section; check for explicit OI performance claims | L16: =IF(K16="","",IF(K16=G16,"Y","N"))
A17: 12 | B17: pmid:40540969 | C17: Scalable 3D packaging technique for brain organoid arrays toward high-capacity bioprocessors | D17: 2025 | E17: Engineering/tools | F17: Q1; Q2 | G17: Maybe | H17: M | I17: =IF(H17="","",IFERROR(INDEX(Codes!$B$2:$B$30,MATCH(H17,Codes!$A$2:$A$30,0)),"")) -> Maybe: borderline, needs second screener or full-text check | J17: Abstract asserts energy-efficient signal processing; check whether measured or motivational | L17: =IF(K17="","",IF(K17=G17,"Y","N"))
A18: 13 | B18: doi:10.64898/2026.10.11.758231 | C18: PULSE: foundation model for brain organoid network dynamics reporting intrinsic computation | D18: 2026 | E18: Empirical | F18: Q1 | G18: Include | H18: I | I18: =IF(H18="","",IFERROR(INDEX(Codes!$B$2:$B$30,MATCH(H18,Codes!$A$2:$A$30,0)),"")) -> Include: empirical paper with a computational, learning, or efficiency claim about living neural tissue as a substrate | J18: Preprint | L18: =IF(K18="","",IF(K18=G18,"Y","N"))
A19: 14 | B19: pmcid:PMC10796793 | C19: Brain organoids and organoid intelligence from ethical, legal, and social points of view | D19: 2023 | E19: Ethics | F19: Q1; Q5 | G19: Context | H19: C3 | I19: =IF(H19="","",IFERROR(INDEX(Codes!$B$2:$B$30,MATCH(H19,Codes!$A$2:$A$30,0)),"")) -> Context: ethics or governance paper specific to organoid computing / OI (ethics arm, not scored on the main rubric) | J19: Ethics arm, OI-specific | L19: =IF(K19="","",IF(K19=G19,"Y","N"))
A20: 15 | B20: pmcid:PMC13039412 | C20: Ethical concerns about embodied brain organoids (biocomputers): public attitudes experiment | D20: 2026 | E20: Ethics | F20: Q1; Q5 | G20: Context | H20: C3 | I20: =IF(H20="","",IFERROR(INDEX(Codes!$B$2:$B$30,MATCH(H20,Codes!$A$2:$A$30,0)),"")) -> Context: ethics or governance paper specific to organoid computing / OI (ethics arm, not scored on the main rubric) | J20: Ethics arm, OI-specific | L20: =IF(K20="","",IF(K20=G20,"Y","N"))
A21: 16 | B21: pmcid:PMC11869974 | C21: Emerging brain organoids: 3D models to decipher, identify and revolutionize brain | D21: 2025 | E21: Review/roadmap | F21: Q1 | G21: Exclude | H21: E2 | I21: =IF(H21="","",IFERROR(INDEX(Codes!$B$2:$B$30,MATCH(H21,Codes!$A$2:$A$30,0)),"")) -> Exclude: mentions OI only in passing | J21: OI mentioned in passing | L21: =IF(K21="","",IF(K21=G21,"Y","N"))
A22: 17 | B22: pmid:36480938 | C22: Neuronal cultures playing Pong: first steps toward advanced screening and biological computing (Neuron preview) | D22: 2022 | E22: Commentary/news | F22: Q1; Q3 | G22: Context | H22: C2 | I22: =IF(H22="","",IFERROR(INDEX(Codes!$B$2:$B$30,MATCH(H22,Codes!$A$2:$A$30,0)),"")) -> Context: commentary, editorial, or press coverage (not scored; used to trace how claims propagate) | J22: Commentary on Kagan; use for claim-propagation tracing | L22: =IF(K22="","",IF(K22=G22,"Y","N"))
A23: 18 | B23: pmcid:PMC12796111 | C23: Artificial Intelligence Virtual Organoids (AIVOs) | D23: 2025 | E23: AI/hardware-only | F23: Q1 | G23: Exclude | H23: E5 | I23: =IF(H23="","",IFERROR(INDEX(Codes!$B$2:$B$30,MATCH(H23,Codes!$A$2:$A$30,0)),"")) -> Exclude: AI, simulation, or hardware only; no living neural substrate | J23: Digital twins, no living substrate | L23: =IF(K23="","",IF(K23=G23,"Y","N"))
A24: 19 | B24: pmcid:PMC11870477 | C24: Neuromodulation in neural organoids with shell MEAs (preprint) | D24: 2025 | E24: Engineering/tools | F24: Q1; Q2 | G24: Exclude | H24: E1 | I24: =IF(H24="","",IFERROR(INDEX(Codes!$B$2:$B$30,MATCH(H24,Codes!$A$2:$A$30,0)),"")) -> Exclude: no computational, learning, or efficiency claim (disease modeling, tools, engineering, theory) | J24: Interface characterization | L24: =IF(K24="","",IF(K24=G24,"Y","N"))
A25: 20 | B25: doi:10.64898/2026.09.09.750433 | C25: Information processing-like phenotype of human brain organoids | D25: 2026 | E25: Empirical | F25: Q1; Q2 | G25: Include | H25: I | I25: =IF(H25="","",IFERROR(INDEX(Codes!$B$2:$B$30,MATCH(H25,Codes!$A$2:$A$30,0)),"")) -> Include: empirical paper with a computational, learning, or efficiency claim about living neural tissue as a substrate | J25: Preprint | L25: =IF(K25="","",IF(K25=G25,"Y","N"))
A26: 21 | B26: pmcid:PMC11661084 | C26: Goal-directed learning in cortical organoids (Cell Rep) | D26: 2026 | E26: Empirical | F26: Q1; Q2; Q3 | G26: Include | H26: I | I26: =IF(H26="","",IFERROR(INDEX(Codes!$B$2:$B$30,MATCH(H26,Codes!$A$2:$A$30,0)),"")) -> Include: empirical paper with a computational, learning, or efficiency claim about living neural tissue as a substrate | J26: bioRxiv preprint doi:10.1101/2024.12.07.627350 is the same work | L26: =IF(K26="","",IF(K26=G26,"Y","N"))
A27: 22 | B27: pmcid:PMC10995847 | C27: Moral considerability of brain organoids from the perspective of computational architecture | D27: 2024 | E27: Ethics | F27: Q1 | G27: Context | H27: C3 | I27: =IF(H27="","",IFERROR(INDEX(Codes!$B$2:$B$30,MATCH(H27,Codes!$A$2:$A$30,0)),"")) -> Context: ethics or governance paper specific to organoid computing / OI (ethics arm, not scored on the main rubric) | J27: Ethics arm, OI-specific | L27: =IF(K27="","",IF(K27=G27,"Y","N"))
A28: 23 | B28: pmcid:PMC11429697 | C28: Human neural organoid microphysiological systems show building blocks for basic learning and memory (bioRxiv) | D28: 2024 | E28: Empirical | F28: Q1 | G28: Exclude | H28: E3 | I28: =IF(H28="","",IFERROR(INDEX(Codes!$B$2:$B$30,MATCH(H28,Codes!$A$2:$A$30,0)),"")) -> Exclude: duplicate or earlier version of an included record (version of record kept) | J28: Preprint of PMC12357958 | L28: =IF(K28="","",IF(K28=G28,"Y","N"))
A29: 24 | B29: pmcid:PMC11027187 | C29: Organoid intelligence: integration of organoid technology and AI in the new era of in vitro models | D29: 2024 | E29: Review/roadmap | F29: Q1 | G29: Include | H29: R | I29: =IF(H29="","",IFERROR(INDEX(Codes!$B$2:$B$30,MATCH(H29,Codes!$A$2:$A$30,0)),"")) -> Include: review or roadmap that makes explicit claims about such systems | L29: =IF(K29="","",IF(K29=G29,"Y","N"))
A30: 25 | B30: pmid:32833194 | C30: Review of AI applications and algorithms for brain organoid research | D30: 2020 | E30: Review/roadmap | F30: Q1 | G30: Exclude | H30: E5 | I30: =IF(H30="","",IFERROR(INDEX(Codes!$B$2:$B$30,MATCH(H30,Codes!$A$2:$A$30,0)),"")) -> Exclude: AI, simulation, or hardware only; no living neural substrate | J30: AI used to analyze organoids, not organoids as computers | L30: =IF(K30="","",IF(K30=G30,"Y","N"))
A31: 26 | B31: doi:10.1101/2025.03.02.641081 | C31: Modeling Organoid Population Electrophysiology Dynamics | D31: 2025 | E31: Empirical | F31: Q1 | G31: Exclude | H31: E1 | I31: =IF(H31="","",IFERROR(INDEX(Codes!$B$2:$B$30,MATCH(H31,Codes!$A$2:$A$30,0)),"")) -> Exclude: no computational, learning, or efficiency claim (disease modeling, tools, engineering, theory) | J31: Disease/toxicology modeling framing | L31: =IF(K31="","",IF(K31=G31,"Y","N"))
A32: 27 | B32: pmid:42675178 | C32: Organoid intelligence: a promising paradigm for autism spectrum disorder research | D32: 2026 | E32: Review/roadmap | F32: Q1 | G32: Maybe | H32: M | I32: =IF(H32="","",IFERROR(INDEX(Codes!$B$2:$B$30,MATCH(H32,Codes!$A$2:$A$30,0)),"")) -> Maybe: borderline, needs second screener or full-text check | J32: OI framed for disease research; check for explicit OI performance claims | L32: =IF(K32="","",IF(K32=G32,"Y","N"))
A33: 28 | B33: pmid:42285251 | C33: Convergence and innovative applications of cutting-edge biomedical technologies in brain organoid research | D33: 2026 | E33: Review/roadmap | F33: Q1 | G33: Exclude | H33: E1 | I33: =IF(H33="","",IFERROR(INDEX(Codes!$B$2:$B$30,MATCH(H33,Codes!$A$2:$A$30,0)),"")) -> Exclude: no computational, learning, or efficiency claim (disease modeling, tools, engineering, theory) | L33: =IF(K33="","",IF(K33=G33,"Y","N"))
A34: 29 | B34: pmid:37288491 | C34: Human brain organoids: moral concerns if they grow up in the lab and are transplanted or destroyed | D34: 2023 | E34: Ethics | F34: Q1; Q5 | G34: Exclude | H34: E8 | I34: =IF(H34="","",IFERROR(INDEX(Codes!$B$2:$B$30,MATCH(H34,Codes!$A$2:$A$30,0)),"")) -> Exclude: brain-organoid ethics not specific to computing / OI | L34: =IF(K34="","",IF(K34=G34,"Y","N"))
A35: 30 | B35: pmcid:PMC11493634 | C35: Organoid intelligence for developmental neurotoxicity testing | D35: 2024 | E35: Review/roadmap | F35: Q1; Q2 | G35: Maybe | H35: M | I35: =IF(H35="","",IFERROR(INDEX(Codes!$B$2:$B$30,MATCH(H35,Codes!$A$2:$A$30,0)),"")) -> Maybe: borderline, needs second screener or full-text check | J35: Proposal paper; check for explicit OI capability claims | L35: =IF(K35="","",IF(K35=G35,"Y","N"))
A36: 31 | B36: pmid:41832075 | C36: Next-generation discovery: empowering organoid research with ML, AI and mathematical modeling | D36: 2026 | E36: Review/roadmap | F36: Q1 | G36: Exclude | H36: E5 | I36: =IF(H36="","",IFERROR(INDEX(Codes!$B$2:$B$30,MATCH(H36,Codes!$A$2:$A$30,0)),"")) -> Exclude: AI, simulation, or hardware only; no living neural substrate | L36: =IF(K36="","",IF(K36=G36,"Y","N"))
A37: 32 | B37: pmid:37496118 | C37: Brain Model Technology and Its Implications | D37: 2023 | E37: Ethics | F37: Q1 | G37: Exclude | H37: E8 | I37: =IF(H37="","",IFERROR(INDEX(Codes!$B$2:$B$30,MATCH(H37,Codes!$A$2:$A$30,0)),"")) -> Exclude: brain-organoid ethics not specific to computing / OI | L37: =IF(K37="","",IF(K37=G37,"Y","N"))
A38: 33 | B38: pmcid:PMC9338020 | C38: Human brain organoid networks (Nat Commun) | D38: 2022 | E38: Empirical | F38: Q1; Q2 | G38: Exclude | H38: E1 | I38: =IF(H38="","",IFERROR(INDEX(Codes!$B$2:$B$30,MATCH(H38,Codes!$A$2:$A$30,0)),"")) -> Exclude: no computational, learning, or efficiency claim (disease modeling, tools, engineering, theory) | J38: Network physiology; no computational claim in abstract | L38: =IF(K38="","",IF(K38=G38,"Y","N"))
A39: 34 | B39: doi:10.1101/2024.12.23.630065 | C39: Engineered biological neural networks as basic logic operators (bioRxiv) | D39: 2024 | E39: Empirical | F39: Q1 | G39: Exclude | H39: E3 | I39: =IF(H39="","",IFERROR(INDEX(Codes!$B$2:$B$30,MATCH(H39,Codes!$A$2:$A$30,0)),"")) -> Exclude: duplicate or earlier version of an included record (version of record kept) | J39: Preprint of PMC12066566 | L39: =IF(K39="","",IF(K39=G39,"Y","N"))
A40: 35 | B40: doi:10.64898/2026.10.02.756317 | C40: Flexible 3D multimodal organoid interface reveals functional subnetworks in cortical organoids | D40: 2026 | E40: Engineering/tools | F40: Q1; Q2 | G40: Exclude | H40: E1 | I40: =IF(H40="","",IFERROR(INDEX(Codes!$B$2:$B$30,MATCH(H40,Codes!$A$2:$A$30,0)),"")) -> Exclude: no computational, learning, or efficiency claim (disease modeling, tools, engineering, theory) | L40: =IF(K40="","",IF(K40=G40,"Y","N"))
A41: 36 | B41: pmcid:PMC13247413 | C41: BrAIn: AI-based morphology analysis system for brain organoids | D41: 2025 | E41: AI/hardware-only | F41: Q1 | G41: Exclude | H41: E5 | I41: =IF(H41="","",IFERROR(INDEX(Codes!$B$2:$B$30,MATCH(H41,Codes!$A$2:$A$30,0)),"")) -> Exclude: AI, simulation, or hardware only; no living neural substrate | L41: =IF(K41="","",IF(K41=G41,"Y","N"))
A42: 37 | B42: pmid:35776358 | C42: In vitro brain organoids and computational models to study cell death in brain diseases | D42: 2022 | E42: Other | F42: Q1 | G42: Exclude | H42: E1 | I42: =IF(H42="","",IFERROR(INDEX(Codes!$B$2:$B$30,MATCH(H42,Codes!$A$2:$A$30,0)),"")) -> Exclude: no computational, learning, or efficiency claim (disease modeling, tools, engineering, theory) | L42: =IF(K42="","",IF(K42=G42,"Y","N"))
A43: 38 | B43: pmcid:PMC12447339 | C43: The emergence of electrical activity in human brain organoids | D43: 2025 | E43: Review/roadmap | F43: Q1; Q2 | G43: Exclude | H43: E1 | I43: =IF(H43="","",IFERROR(INDEX(Codes!$B$2:$B$30,MATCH(H43,Codes!$A$2:$A$30,0)),"")) -> Exclude: no computational, learning, or efficiency claim (disease modeling, tools, engineering, theory) | L43: =IF(K43="","",IF(K43=G43,"Y","N"))
A44: 39 | B44: pmcid:PMC13621883 | C44: Transforming brain organoids into functional platforms: engineering, imaging, AI, and ethics | D44: 2026 | E44: Review/roadmap | F44: Q1; Q2 | G44: Exclude | H44: E2 | I44: =IF(H44="","",IFERROR(INDEX(Codes!$B$2:$B$30,MATCH(H44,Codes!$A$2:$A$30,0)),"")) -> Exclude: mentions OI only in passing | L44: =IF(K44="","",IF(K44=G44,"Y","N"))
A45: 40 | B45: pmcid:PMC13589029 | C45: Using brain organoids to explore human neurobiology | D45: 2026 | E45: Review/roadmap | F45: Q1 | G45: Exclude | H45: E1 | I45: =IF(H45="","",IFERROR(INDEX(Codes!$B$2:$B$30,MATCH(H45,Codes!$A$2:$A$30,0)),"")) -> Exclude: no computational, learning, or efficiency claim (disease modeling, tools, engineering, theory) | L45: =IF(K45="","",IF(K45=G45,"Y","N"))
A46: 41 | B46: pmcid:PMC12357958 | C46: Human neural organoid microphysiological systems show building blocks for basic learning and memory (Commun Biol) | D46: 2025 | E46: Empirical | F46: Q1; Q2 | G46: Include | H46: I | I46: =IF(H46="","",IFERROR(INDEX(Codes!$B$2:$B$30,MATCH(H46,Codes!$A$2:$A$30,0)),"")) -> Include: empirical paper with a computational, learning, or efficiency claim about living neural tissue as a substrate | L46: =IF(K46="","",IF(K46=G46,"Y","N"))
A47: 42 | B47: pmid:42474232 | C47: Engineering neural organoids: technological advances and translational frontiers | D47: 2026 | E47: Review/roadmap | F47: Q1 | G47: Exclude | H47: E1 | I47: =IF(H47="","",IFERROR(INDEX(Codes!$B$2:$B$30,MATCH(H47,Codes!$A$2:$A$30,0)),"")) -> Exclude: no computational, learning, or efficiency claim (disease modeling, tools, engineering, theory) | L47: =IF(K47="","",IF(K47=G47,"Y","N"))
A48: 43 | B48: pmcid:PMC12066566 | C48: Engineered biological neuronal networks as basic logic operators (Front Comput Neurosci) | D48: 2025 | E48: Empirical | F48: Q1; Q2 | G48: Include | H48: I | I48: =IF(H48="","",IFERROR(INDEX(Codes!$B$2:$B$30,MATCH(H48,Codes!$A$2:$A$30,0)),"")) -> Include: empirical paper with a computational, learning, or efficiency claim about living neural tissue as a substrate | L48: =IF(K48="","",IF(K48=G48,"Y","N"))
A49: 44 | B49: pmcid:PMC11750812 | C49: Editorial: Intersection between the biological and digital: synthetic biological intelligence and organoid intelligence | D49: 2025 | E49: Commentary/news | F49: Q1 | G49: Context | H49: C2 | I49: =IF(H49="","",IFERROR(INDEX(Codes!$B$2:$B$30,MATCH(H49,Codes!$A$2:$A$30,0)),"")) -> Context: commentary, editorial, or press coverage (not scored; used to trace how claims propagate) | J49: Editorial | L49: =IF(K49="","",IF(K49=G49,"Y","N"))
A50: 45 | B50: pmid:37607158 | C50: How brain organoids are revolutionizing neuroscience (IEEE Pulse) | D50: 2023 | E50: Commentary/news | F50: Q1 | G50: Context | H50: C2 | I50: =IF(H50="","",IFERROR(INDEX(Codes!$B$2:$B$30,MATCH(H50,Codes!$A$2:$A$30,0)),"")) -> Context: commentary, editorial, or press coverage (not scored; used to trace how claims propagate) | J50: Popular-press framing | L50: =IF(K50="","",IF(K50=G50,"Y","N"))
A51: 46 | B51: doi:10.64898/2026.08.10.743829 | C51: Handwritten digit classification with neural cultures: architecture, dynamics, decoding | D51: 2026 | E51: Empirical | F51: Q2 | G51: Include | H51: I | I51: =IF(H51="","",IFERROR(INDEX(Codes!$B$2:$B$30,MATCH(H51,Codes!$A$2:$A$30,0)),"")) -> Include: empirical paper with a computational, learning, or efficiency claim about living neural tissue as a substrate | J51: Preprint | L51: =IF(K51="","",IF(K51=G51,"Y","N"))
A52: 47 | B52: arxiv:2602.05737 | C52: Neuro-inspired visual pattern recognition via biological reservoir computing | D52: 2026 | E52: Empirical | F52: Q2 | G52: Include | H52: I | I52: =IF(H52="","",IFERROR(INDEX(Codes!$B$2:$B$30,MATCH(H52,Codes!$A$2:$A$30,0)),"")) -> Include: empirical paper with a computational, learning, or efficiency claim about living neural tissue as a substrate | J52: Preprint | L52: =IF(K52="","",IF(K52=G52,"Y","N"))
A53: 48 | B53: arxiv:2505.03510 | C53: From neurons to computation: biological reservoir computing for pattern recognition | D53: 2025 | E53: Empirical | F53: Q2 | G53: Include | H53: I | I53: =IF(H53="","",IFERROR(INDEX(Codes!$B$2:$B$30,MATCH(H53,Codes!$A$2:$A$30,0)),"")) -> Include: empirical paper with a computational, learning, or efficiency claim about living neural tissue as a substrate | J53: Preprint | L53: =IF(K53="","",IF(K53=G53,"Y","N"))
A54: 49 | B54: pmcid:PMC13596552 | C54: Brain organoid computing for robotic decision-making | D54: 2026 | E54: Empirical | F54: Q2 | G54: Include | H54: I | I54: =IF(H54="","",IFERROR(INDEX(Codes!$B$2:$B$30,MATCH(H54,Codes!$A$2:$A$30,0)),"")) -> Include: empirical paper with a computational, learning, or efficiency claim about living neural tissue as a substrate | J54: Preprint (bioRxiv) | L54: =IF(K54="","",IF(K54=G54,"Y","N"))
A55: 50 | B55: arxiv:2510.05637 | C55: From neural activity to computation: biological reservoirs for digit classification | D55: 2025 | E55: Empirical | F55: Q2 | G55: Include | H55: I | I55: =IF(H55="","",IFERROR(INDEX(Codes!$B$2:$B$30,MATCH(H55,Codes!$A$2:$A$30,0)),"")) -> Include: empirical paper with a computational, learning, or efficiency claim about living neural tissue as a substrate | J55: Preprint | L55: =IF(K55="","",IF(K55=G55,"Y","N"))
A56: 51 | B56: doi:10.64898/2026.09.08.750274 | C56: Harnessing the intrinsic dynamics of biological neural networks for reservoir computing | D56: 2026 | E56: Empirical | F56: Q2 | G56: Include | H56: I | I56: =IF(H56="","",IFERROR(INDEX(Codes!$B$2:$B$30,MATCH(H56,Codes!$A$2:$A$30,0)),"")) -> Include: empirical paper with a computational, learning, or efficiency claim about living neural tissue as a substrate | J56: Preprint | L56: =IF(K56="","",IF(K56=G56,"Y","N"))
A57: 52 | B57: arxiv:2508.20850 | C57: Encoding tactile stimuli for Braille recognition with organoids | D57: 2025 | E57: Empirical | F57: Q2 | G57: Include | H57: I | I57: =IF(H57="","",IFERROR(INDEX(Codes!$B$2:$B$30,MATCH(H57,Codes!$A$2:$A$30,0)),"")) -> Include: empirical paper with a computational, learning, or efficiency claim about living neural tissue as a substrate | J57: Preprint | L57: =IF(K57="","",IF(K57=G57,"Y","N"))
A58: 53 | B58: pmid:42700517 | C58: Brain organoids, high-density MEAs, and deep learning: functional neurobiomarker discovery | D58: 2026 | E58: Review/roadmap | F58: Q2 | G58: Exclude | H58: E5 | I58: =IF(H58="","",IFERROR(INDEX(Codes!$B$2:$B$30,MATCH(H58,Codes!$A$2:$A$30,0)),"")) -> Exclude: AI, simulation, or hardware only; no living neural substrate | J58: AI used for biomarker analysis | L58: =IF(K58="","",IF(K58=G58,"Y","N"))
A59: 54 | B59: pmid:42595103 | C59: Minimal reservoir computing generates hippocampal-inspired stimulation for cortical networks in vitro | D59: 2026 | E59: Empirical | F59: Q2 | G59: Exclude | H59: E1 | I59: =IF(H59="","",IFERROR(INDEX(Codes!$B$2:$B$30,MATCH(H59,Codes!$A$2:$A$30,0)),"")) -> Exclude: no computational, learning, or efficiency claim (disease modeling, tools, engineering, theory) | J59: Seizure neuromodulation; reservoir is a model, not the substrate | L59: =IF(K59="","",IF(K59=G59,"Y","N"))
A60: 55 | B60: doi:10.1101/2025.07.03.663054 | C60: Long-term potentiation and closed-loop learning in paired brain organoids for CNS drug discovery | D60: 2025 | E60: Empirical | F60: Q2; Q3 | G60: Include | H60: I | I60: =IF(H60="","",IFERROR(INDEX(Codes!$B$2:$B$30,MATCH(H60,Codes!$A$2:$A$30,0)),"")) -> Include: empirical paper with a computational, learning, or efficiency claim about living neural tissue as a substrate | J60: Preprint | L60: =IF(K60="","",IF(K60=G60,"Y","N"))
A61: 56 | B61: doi:10.1101/2025.09.12.675888 | C61: High-density recordings from the interior of intact brain organoids enable automated functional assay | D61: 2025 | E61: Engineering/tools | F61: Q2 | G61: Exclude | H61: E1 | I61: =IF(H61="","",IFERROR(INDEX(Codes!$B$2:$B$30,MATCH(H61,Codes!$A$2:$A$30,0)),"")) -> Exclude: no computational, learning, or efficiency claim (disease modeling, tools, engineering, theory) | L61: =IF(K61="","",IF(K61=G61,"Y","N"))
A62: 57 | B62: arxiv:2607.28068 | C62: Stimulus-evoked network dynamics in human cortical organoids: graph-computational framework | D62: 2026 | E62: Empirical | F62: Q2 | G62: Include | H62: I | I62: =IF(H62="","",IFERROR(INDEX(Codes!$B$2:$B$30,MATCH(H62,Codes!$A$2:$A$30,0)),"")) -> Include: empirical paper with a computational, learning, or efficiency claim about living neural tissue as a substrate | J62: Preprint; reports a negative result on structured information processing | L62: =IF(K62="","",IF(K62=G62,"Y","N"))
A63: 58 | B63: doi:10.1101/2025.03.15.641656 | C63: MAIS: in-vitro sandbox for adaptive neuromodulation via scalable neural interfaces | D63: 2025 | E63: Engineering/tools | F63: Q2 | G63: Exclude | H63: E1 | I63: =IF(H63="","",IFERROR(INDEX(Codes!$B$2:$B$30,MATCH(H63,Codes!$A$2:$A$30,0)),"")) -> Exclude: no computational, learning, or efficiency claim (disease modeling, tools, engineering, theory) | L63: =IF(K63="","",IF(K63=G63,"Y","N"))
A64: 59 | B64: arxiv:2309.06297 | C64: Reservoir computing model for multi-electrode electrophysiological data analysis | D64: 2023 | E64: AI/hardware-only | F64: Q2 | G64: Exclude | H64: E5 | I64: =IF(H64="","",IFERROR(INDEX(Codes!$B$2:$B$30,MATCH(H64,Codes!$A$2:$A$30,0)),"")) -> Exclude: AI, simulation, or hardware only; no living neural substrate | J64: Computational model of cultures | L64: =IF(K64="","",IF(K64=G64,"Y","N"))
A65: 60 | B65: pmid:41502138 | C65: 3D neuromodulation in neural organoids with shell MEAs (published version) | E65: Engineering/tools | F65: Q2 | G65: Exclude | H65: E1 | I65: =IF(H65="","",IFERROR(INDEX(Codes!$B$2:$B$30,MATCH(H65,Codes!$A$2:$A$30,0)),"")) -> Exclude: no computational, learning, or efficiency claim (disease modeling, tools, engineering, theory) | L65: =IF(K65="","",IF(K65=G65,"Y","N"))
A66: 61 | B66: pmcid:PMC13194713 | C66: Multilayered microelectrode array for monitoring 3D neural networks in cerebral organoid | D66: 2026 | E66: Engineering/tools | F66: Q2 | G66: Exclude | H66: E1 | I66: =IF(H66="","",IFERROR(INDEX(Codes!$B$2:$B$30,MATCH(H66,Codes!$A$2:$A$30,0)),"")) -> Exclude: no computational, learning, or efficiency claim (disease modeling, tools, engineering, theory) | L66: =IF(K66="","",IF(K66=G66,"Y","N"))
A67: 62 | B67: pmcid:PMC10288593 | C67: Biological neurons act as generalization filters in reservoir computing (PNAS) | D67: 2023 | E67: Empirical | F67: Q2 | G67: Include | H67: I | I67: =IF(H67="","",IFERROR(INDEX(Codes!$B$2:$B$30,MATCH(H67,Codes!$A$2:$A$30,0)),"")) -> Include: empirical paper with a computational, learning, or efficiency claim about living neural tissue as a substrate | L67: =IF(K67="","",IF(K67=G67,"Y","N"))
A68: 63 | B68: pmcid:PMC9474390 | C68: Functional imaging of brain organoids using high-density microelectrode arrays | D68: 2022 | E68: Engineering/tools | F68: Q2 | G68: Exclude | H68: E1 | I68: =IF(H68="","",IFERROR(INDEX(Codes!$B$2:$B$30,MATCH(H68,Codes!$A$2:$A$30,0)),"")) -> Exclude: no computational, learning, or efficiency claim (disease modeling, tools, engineering, theory) | L68: =IF(K68="","",IF(K68=G68,"Y","N"))
A69: 64 | B69: pmcid:PMC9385157 | C69: Shell microelectrode arrays (MEAs) for brain organoids (Sci Adv) | D69: 2022 | E69: Engineering/tools | F69: Q2 | G69: Exclude | H69: E1 | I69: =IF(H69="","",IFERROR(INDEX(Codes!$B$2:$B$30,MATCH(H69,Codes!$A$2:$A$30,0)),"")) -> Exclude: no computational, learning, or efficiency claim (disease modeling, tools, engineering, theory) | L69: =IF(K69="","",IF(K69=G69,"Y","N"))
A70: 65 | B70: arxiv:2210.02913 | C70: Biological neurons act as generalization filters in reservoir computing (arXiv) | D70: 2022 | E70: Empirical | F70: Q2 | G70: Exclude | H70: E3 | I70: =IF(H70="","",IFERROR(INDEX(Codes!$B$2:$B$30,MATCH(H70,Codes!$A$2:$A$30,0)),"")) -> Exclude: duplicate or earlier version of an included record (version of record kept) | J70: Preprint of PMC10288593 | L70: =IF(K70="","",IF(K70=G70,"Y","N"))
A71: 66 | B71: pmcid:PMC11868496 | C71: Magnetically reshapable 3D multi-electrode arrays of liquid metals for brain organoids | E71: Engineering/tools | F71: Q2 | G71: Exclude | H71: E1 | I71: =IF(H71="","",IFERROR(INDEX(Codes!$B$2:$B$30,MATCH(H71,Codes!$A$2:$A$30,0)),"")) -> Exclude: no computational, learning, or efficiency claim (disease modeling, tools, engineering, theory) | L71: =IF(K71="","",IF(K71=G71,"Y","N"))
A72: 67 | B72: pmcid:PMC13394382 | C72: Neuromorphic tissues: soft biomolecular networks for brain-inspired temporal computing | E72: AI/hardware-only | F72: Q2 | G72: Exclude | H72: E5 | I72: =IF(H72="","",IFERROR(INDEX(Codes!$B$2:$B$30,MATCH(H72,Codes!$A$2:$A$30,0)),"")) -> Exclude: AI, simulation, or hardware only; no living neural substrate | J72: No living neurons | L72: =IF(K72="","",IF(K72=G72,"Y","N"))
A73: 68 | B73: pmcid:PMC12321758 | C73: 360-degree size-adjustable MEA system for cerebral organoid monitoring | D73: 2025 | E73: Engineering/tools | F73: Q2 | G73: Exclude | H73: E1 | I73: =IF(H73="","",IFERROR(INDEX(Codes!$B$2:$B$30,MATCH(H73,Codes!$A$2:$A$30,0)),"")) -> Exclude: no computational, learning, or efficiency claim (disease modeling, tools, engineering, theory) | L73: =IF(K73="","",IF(K73=G73,"Y","N"))
A74: 69 | B74: pmid:37469180 | C74: Aerosol jet-printed micro-needle electrode arrays for cerebral organoids and neurospheroids | D74: 2023 | E74: Engineering/tools | F74: Q2 | G74: Exclude | H74: E1 | I74: =IF(H74="","",IFERROR(INDEX(Codes!$B$2:$B$30,MATCH(H74,Codes!$A$2:$A$30,0)),"")) -> Exclude: no computational, learning, or efficiency claim (disease modeling, tools, engineering, theory) | L74: =IF(K74="","",IF(K74=G74,"Y","N"))
A75: 70 | B75: pmcid:PMC12781996 | C75: Feedback-driven brain organoid platform for automated maintenance and activity monitoring | D75: 2025 | E75: Engineering/tools | F75: Q2 | G75: Exclude | H75: E1 | I75: =IF(H75="","",IFERROR(INDEX(Codes!$B$2:$B$30,MATCH(H75,Codes!$A$2:$A$30,0)),"")) -> Exclude: no computational, learning, or efficiency claim (disease modeling, tools, engineering, theory) | L75: =IF(K75="","",IF(K75=G75,"Y","N"))
A76: 71 | B76: pmcid:PMC12392918 | C76: Neural activity mapping in brain organoids via field potential imaging with UHD CMOS microelectrodes | D76: 2025 | E76: Engineering/tools | F76: Q2 | G76: Exclude | H76: E1 | I76: =IF(H76="","",IFERROR(INDEX(Codes!$B$2:$B$30,MATCH(H76,Codes!$A$2:$A$30,0)),"")) -> Exclude: no computational, learning, or efficiency claim (disease modeling, tools, engineering, theory) | L76: =IF(K76="","",IF(K76=G76,"Y","N"))
A77: 72 | B77: pmcid:PMC11094048 | C77: Three-dimensional liquid metal-based neuro-interfaces for human hippocampal organoids | E77: Engineering/tools | F77: Q2 | G77: Exclude | H77: E1 | I77: =IF(H77="","",IFERROR(INDEX(Codes!$B$2:$B$30,MATCH(H77,Codes!$A$2:$A$30,0)),"")) -> Exclude: no computational, learning, or efficiency claim (disease modeling, tools, engineering, theory) | L77: =IF(K77="","",IF(K77=G77,"Y","N"))
A78: 73 | B78: doi:10.1101/2022.11.09.515884 | C78: Large-area electrical imaging at single-neuron resolution using 236,880-electrode CMOS-MEA | D78: 2022 | E78: Engineering/tools | F78: Q2 | G78: Exclude | H78: E1 | I78: =IF(H78="","",IFERROR(INDEX(Codes!$B$2:$B$30,MATCH(H78,Codes!$A$2:$A$30,0)),"")) -> Exclude: no computational, learning, or efficiency claim (disease modeling, tools, engineering, theory) | L78: =IF(K78="","",IF(K78=G78,"Y","N"))
A79: 74 | B79: doi:10.1101/2024.09.25.614992 | C79: Temporal information encoding in isolated cortical networks | D79: 2024 | E79: Empirical | F79: Q2 | G79: Include | H79: I | I79: =IF(H79="","",IFERROR(INDEX(Codes!$B$2:$B$30,MATCH(H79,Codes!$A$2:$A$30,0)),"")) -> Include: empirical paper with a computational, learning, or efficiency claim about living neural tissue as a substrate | J79: Preprint | L79: =IF(K79="","",IF(K79=G79,"Y","N"))
A80: 75 | B80: pmcid:PMC11730284 | C80: Multi-electrode array platform for modeling epilepsy with brain assembloids | E80: Engineering/tools | F80: Q2 | G80: Exclude | H80: E1 | I80: =IF(H80="","",IFERROR(INDEX(Codes!$B$2:$B$30,MATCH(H80,Codes!$A$2:$A$30,0)),"")) -> Exclude: no computational, learning, or efficiency claim (disease modeling, tools, engineering, theory) | L80: =IF(K80="","",IF(K80=G80,"Y","N"))
A81: 76 | B81: arxiv:2405.16946 | C81: Biological neurons compete with deep reinforcement learning in sample efficiency in a simulated gameworld (arXiv v1) | D81: 2024 | E81: Empirical | F81: Q3 | G81: Exclude | H81: E3 | I81: =IF(H81="","",IFERROR(INDEX(Codes!$B$2:$B$30,MATCH(H81,Codes!$A$2:$A$30,0)),"")) -> Exclude: duplicate or earlier version of an included record (version of record kept) | J81: Earlier version of Khajehnejad 2025 seed | L81: =IF(K81="","",IF(K81=G81,"Y","N"))
A82: 77 | B82: pmcid:PMC10469171 | C82: Critical dynamics arise during structured information presentation within embodied in vitro neuronal networks | D82: 2023 | E82: Empirical | F82: Q3 | G82: Include | H82: I | I82: =IF(H82="","",IFERROR(INDEX(Codes!$B$2:$B$30,MATCH(H82,Codes!$A$2:$A$30,0)),"")) -> Include: empirical paper with a computational, learning, or efficiency claim about living neural tissue as a substrate | L82: =IF(K82="","",IF(K82=G82,"Y","N"))
A83: 78 | B83: doi:10.1101/2022.11.03.514955 | C83: Critical dynamics arise during structured information presentation (bioRxiv preprint) | D83: 2022 | E83: Empirical | F83: Q3 | G83: Exclude | H83: E3 | I83: =IF(H83="","",IFERROR(INDEX(Codes!$B$2:$B$30,MATCH(H83,Codes!$A$2:$A$30,0)),"")) -> Exclude: duplicate or earlier version of an included record (version of record kept) | J83: Preprint of PMC10469171 | L83: =IF(K83="","",IF(K83=G83,"Y","N"))
A84: 79 | B84: pmid:36224373 | C84: Neurons in a dish learn to play Pong: what's next? (Nature news) | D84: 2022 | E84: Commentary/news | F84: Q3 | G84: Context | H84: C2 | I84: =IF(H84="","",IFERROR(INDEX(Codes!$B$2:$B$30,MATCH(H84,Codes!$A$2:$A$30,0)),"")) -> Context: commentary, editorial, or press coverage (not scored; used to trace how claims propagate) | J84: News; use for claim-propagation tracing | L84: =IF(K84="","",IF(K84=G84,"Y","N"))
A85: 80 | B85: doi:10.64898/2026.04.14.718383 | C85: Reinforcement learning framework for goal-directed stimulation of engineered neuronal networks | D85: 2026 | E85: Empirical | F85: Q3 | G85: Include | H85: I | I85: =IF(H85="","",IFERROR(INDEX(Codes!$B$2:$B$30,MATCH(H85,Codes!$A$2:$A$30,0)),"")) -> Include: empirical paper with a computational, learning, or efficiency claim about living neural tissue as a substrate | J85: Preprint | L85: =IF(K85="","",IF(K85=G85,"Y","N"))
A86: 81 | B86: doi:10.64898/2026.07.13.738298 | C86: Closed-loop control of in vitro neuronal activity using RL after in silico pre-training | D86: 2026 | E86: Empirical | F86: Q3 | G86: Include | H86: I | I86: =IF(H86="","",IFERROR(INDEX(Codes!$B$2:$B$30,MATCH(H86,Codes!$A$2:$A$30,0)),"")) -> Include: empirical paper with a computational, learning, or efficiency claim about living neural tissue as a substrate | J86: Preprint | L86: =IF(K86="","",IF(K86=G86,"Y","N"))
A87: 82 | B87: arxiv:2405.15616 | C87: Neuromorphic dreaming: a pathway to efficient learning in artificial agents | D87: 2024 | E87: AI/hardware-only | F87: Q3 | G87: Exclude | H87: E5 | I87: =IF(H87="","",IFERROR(INDEX(Codes!$B$2:$B$30,MATCH(H87,Codes!$A$2:$A$30,0)),"")) -> Exclude: AI, simulation, or hardware only; no living neural substrate | L87: =IF(K87="","",IF(K87=G87,"Y","N"))
A88: 83 | B88: arxiv:2508.06980 | C88: Memory-based active inference model of DishBrain-like adaptive behaviour | D88: 2025 | E88: AI/hardware-only | F88: Q3 | G88: Exclude | H88: E5 | I88: =IF(H88="","",IFERROR(INDEX(Codes!$B$2:$B$30,MATCH(H88,Codes!$A$2:$A$30,0)),"")) -> Exclude: AI, simulation, or hardware only; no living neural substrate | J88: In silico model; no living substrate | L88: =IF(K88="","",IF(K88=G88,"Y","N"))
A89: 84 | B89: pmcid:PMC13111196 | C89: Trainable movement control using spikes and muscle-twitch dynamics | D89: 2026 | E89: AI/hardware-only | F89: Q3 | G89: Exclude | H89: E5 | I89: =IF(H89="","",IFERROR(INDEX(Codes!$B$2:$B$30,MATCH(H89,Codes!$A$2:$A$30,0)),"")) -> Exclude: AI, simulation, or hardware only; no living neural substrate | L89: =IF(K89="","",IF(K89=G89,"Y","N"))
A90: 85 | B90: doi:10.64898/2026.10.15.759184 | C90: HAL: goal-directed closed-loop training of network bursts in cortical cultures | D90: 2026 | E90: Empirical | F90: Q3 | G90: Include | H90: I | I90: =IF(H90="","",IFERROR(INDEX(Codes!$B$2:$B$30,MATCH(H90,Codes!$A$2:$A$30,0)),"")) -> Include: empirical paper with a computational, learning, or efficiency claim about living neural tissue as a substrate | J90: Preprint | L90: =IF(K90="","",IF(K90=G90,"Y","N"))
A91: 86 | B91: pmcid:PMC9094569 | C91: Spiking neuronal network model of visual-motor cortex playing a virtual racket-ball game | D91: 2022 | E91: AI/hardware-only | F91: Q3 | G91: Exclude | H91: E5 | I91: =IF(H91="","",IFERROR(INDEX(Codes!$B$2:$B$30,MATCH(H91,Codes!$A$2:$A$30,0)),"")) -> Exclude: AI, simulation, or hardware only; no living neural substrate | L91: =IF(K91="","",IF(K91=G91,"Y","N"))
A92: 87 | B92: pmcid:PMC12080787 | C92: Combining meta reinforcement learning with neural plasticity mechanisms | D92: 2025 | E92: AI/hardware-only | F92: Q3 | G92: Exclude | H92: E5 | I92: =IF(H92="","",IFERROR(INDEX(Codes!$B$2:$B$30,MATCH(H92,Codes!$A$2:$A$30,0)),"")) -> Exclude: AI, simulation, or hardware only; no living neural substrate | L92: =IF(K92="","",IF(K92=G92,"Y","N"))
A93: 88 | B93: pmcid:PMC12994192 | C93: Online supervised learning of temporal patterns in biological neural networks under feedback control (PNAS) | D93: 2026 | E93: Empirical | F93: Q3 | G93: Include | H93: I | I93: =IF(H93="","",IFERROR(INDEX(Codes!$B$2:$B$30,MATCH(H93,Codes!$A$2:$A$30,0)),"")) -> Include: empirical paper with a computational, learning, or efficiency claim about living neural tissue as a substrate | L93: =IF(K93="","",IF(K93=G93,"Y","N"))
A94: 89 | B94: arxiv:2306.10404 | C94: The RL Perceptron: generalisation dynamics of policy learning in high dimensions | D94: 2023 | E94: AI/hardware-only | F94: Q3 | G94: Exclude | H94: E5 | I94: =IF(H94="","",IFERROR(INDEX(Codes!$B$2:$B$30,MATCH(H94,Codes!$A$2:$A$30,0)),"")) -> Exclude: AI, simulation, or hardware only; no living neural substrate | L94: =IF(K94="","",IF(K94=G94,"Y","N"))
A95: 90 | B95: arxiv:2108.01895 | C95: High performance across two Atari paddle games using a perceptual control architecture without training | D95: 2021 | E95: AI/hardware-only | F95: Q3 | G95: Exclude | H95: E5 | I95: =IF(H95="","",IFERROR(INDEX(Codes!$B$2:$B$30,MATCH(H95,Codes!$A$2:$A$30,0)),"")) -> Exclude: AI, simulation, or hardware only; no living neural substrate | L95: =IF(K95="","",IF(K95=G95,"Y","N"))
A96: 91 | B96: arxiv:2605.13315 | C96: Embodied Neurocomputation: interfacing biological neural cultures with scaled task-driven validation | D96: 2026 | E96: Empirical | F96: Q3 | G96: Include | H96: I | I96: =IF(H96="","",IFERROR(INDEX(Codes!$B$2:$B$30,MATCH(H96,Codes!$A$2:$A$30,0)),"")) -> Include: empirical paper with a computational, learning, or efficiency claim about living neural tissue as a substrate | J96: Preprint; compares to DQN agents | L96: =IF(K96="","",IF(K96=G96,"Y","N"))
A97: 92 | B97: arxiv:2004.09043 | C97: Learning as Reinforcement: principles of neuroscience for more general RL agents | D97: 2020 | E97: AI/hardware-only | F97: Q3 | G97: Exclude | H97: E5 | I97: =IF(H97="","",IFERROR(INDEX(Codes!$B$2:$B$30,MATCH(H97,Codes!$A$2:$A$30,0)),"")) -> Exclude: AI, simulation, or hardware only; no living neural substrate | L97: =IF(K97="","",IF(K97=G97,"Y","N"))
A98: 93 | B98: arxiv:2406.14324 | C98: Revealing the learning process in RL agents through attention-oriented metrics | D98: 2024 | E98: AI/hardware-only | F98: Q3 | G98: Exclude | H98: E5 | I98: =IF(H98="","",IFERROR(INDEX(Codes!$B$2:$B$30,MATCH(H98,Codes!$A$2:$A$30,0)),"")) -> Exclude: AI, simulation, or hardware only; no living neural substrate | L98: =IF(K98="","",IF(K98=G98,"Y","N"))
A99: 94 | B99: arxiv:2005.04106 | C99: Brain experiments imply adaptation mechanisms which outperform common AI learning algorithms (arXiv) | D99: 2020 | E99: Empirical | F99: Q3 | G99: Exclude | H99: E3 | I99: =IF(H99="","",IFERROR(INDEX(Codes!$B$2:$B$30,MATCH(H99,Codes!$A$2:$A$30,0)),"")) -> Exclude: duplicate or earlier version of an included record (version of record kept) | J99: Preprint of PMC7181840 | L99: =IF(K99="","",IF(K99=G99,"Y","N"))
A100: 95 | B100: pmcid:PMC7181840 | C100: Brain experiments imply adaptation mechanisms which outperform common AI learning algorithms (Sci Rep) | D100: 2020 | E100: Empirical | F100: Q3 | G100: Include | H100: I | I100: =IF(H100="","",IFERROR(INDEX(Codes!$B$2:$B$30,MATCH(H100,Codes!$A$2:$A$30,0)),"")) -> Include: empirical paper with a computational, learning, or efficiency claim about living neural tissue as a substrate | L100: =IF(K100="","",IF(K100=G100,"Y","N"))
A101: 96 | B101: arxiv:2211.06236 | C101: Efficient deep RL with predictive processing proximal policy optimization | D101: 2022 | E101: AI/hardware-only | F101: Q3 | G101: Exclude | H101: E5 | I101: =IF(H101="","",IFERROR(INDEX(Codes!$B$2:$B$30,MATCH(H101,Codes!$A$2:$A$30,0)),"")) -> Exclude: AI, simulation, or hardware only; no living neural substrate | L101: =IF(K101="","",IF(K101=G101,"Y","N"))
...

Sheet Flow
A1: Selection flow (PRISMA-style counts, auto-calculated from Screening_Log)
A3: Stage | B3: Count | C3: Note
A4: Unique records logged (de-duplicated by identifier) | B4: =COUNTA(Screening_Log!$B$6:$B$405) -> 190 | C4: 8 paper-index queries, 1 web query, 2 manual adds (see Protocol)
A5: Duplicates / earlier versions removed (E3) | B5: =COUNTIF(Screening_Log!$H$6:$H$405,"E3") -> 11 | C5: Preprints and arXiv versions of an included paper
A6: Records screened on title/abstract | B6: =B4-B5 -> 179
A7: Excluded E1: no computational/learning/efficiency claim | B7: =COUNTIF(Screening_Log!$H$6:$H$405,"E1") -> 34 | C7: Disease modeling, tools, engineering
A8: Excluded E2: OI mentioned in passing | B8: =COUNTIF(Screening_Log!$H$6:$H$405,"E2") -> 2
A9: Excluded E4: opinion, news, social, tertiary | B9: =COUNTIF(Screening_Log!$H$6:$H$405,"E4") -> 5
A10: Excluded E5: AI, simulation, or hardware only | B10: =COUNTIF(Screening_Log!$H$6:$H$405,"E5") -> 47 | C10: No living neural substrate
A11: Excluded E6: outside date range | B11: =COUNTIF(Screening_Log!$H$6:$H$405,"E6") -> 1
A12: Excluded E7: full text not accessible | B12: =COUNTIF(Screening_Log!$H$6:$H$405,"E7") -> 0
A13: Excluded E8: ethics not specific to computing/OI | B13: =COUNTIF(Screening_Log!$H$6:$H$405,"E8") -> 24 | C13: Candidates for ethics background if the team wants them
A14: Total excluded (excluding duplicates) | B14: =SUM(B7:B13) -> 113
A15: Context sources kept, not scored | B15: =COUNTIF(Screening_Log!$G$6:$G$405,"Context") -> 20
A16: C1 critique / skeptical | B16: =COUNTIF(Screening_Log!$H$6:$H$405,"C1") -> 2
A17: C2 commentary / press (claim propagation) | B17: =COUNTIF(Screening_Log!$H$6:$H$405,"C2") -> 6
A18: C3 ethics arm (OI-specific) | B18: =COUNTIF(Screening_Log!$H$6:$H$405,"C3") -> 9
A19: C4 comparator literature | B19: =COUNTIF(Screening_Log!$H$6:$H$405,"C4") -> 3
A20: Maybe: needs second screener | B20: =COUNTIF(Screening_Log!$G$6:$G$405,"Maybe") -> 5 | C20: Promote to Include or exclude after full-text check
A21: Included for scoring | B21: =COUNTIF(Screening_Log!$G$6:$G$405,"Include") -> 41 | C21: Rows are pre-filled on the Scoring sheet
A22: Empirical (I) | B22: =COUNTIF(Screening_Log!$H$6:$H$405,"I") -> 28
A23: Review / roadmap (R) | B23: =COUNTIF(Screening_Log!$H$6:$H$405,"R") -> 10
A24: Grey literature (G) | B24: =COUNTIF(Screening_Log!$H$6:$H$405,"G") -> 3
A25: Check: screened - excluded - context - maybe - included | B25: =B6-B14-B15-B20-B21 -> 0 | C25: Should be 0
A26: Check status | B26: =IF(B25=0,"OK","CHECK") -> OK
A27: Second-screener sample size | B27: =COUNTA(Screening_Log!$K$6:$K$405) -> 0 | C27: Aim for ~20% of screened records
A28: Second-screener agreement | B28: =IF(B27=0,"",COUNTIF(Screening_Log!$L$6:$L$405,"Y")/B27) | C28: Share of sampled records where decision matches

Sheet Claims
A1: Claims audit: one row per claim
A2: Rows C01-C11 are copied from the team's OI Notes on the five seed papers (source column says so); they were not re-checked against the PDFs. Add one row per claim as you code each paper. Tags: Demonstrated, Demonstrated under constraints, Projected (extrapolated estimate), Illustrative (authors flag it as illustration), Aspirational (stated as a future goal), Not demonstrated.
A4: Claim ID | B4: Paper ID | C4: Paper | D4: Category | E4: Claim | F4: Claim tag | G4: Evidence basis | H4: Comparator | I4: Unit / n | J4: Source | K4: Notes (where in paper, caveats)
A5: C01 | B5: doi:10.1016/j.neuron.2022.09.001 | C5: Kagan 2022 | D5: Learning/adaptation | E5: Learning in 2D cortical cultures with closed-loop feedback (Pong) | F5: Demonstrated under constraints | G5: Measured | H5: No-cell, rest, in-silico, HEK293T and media-only controls (none showed learning) | I5: Cultures: MCC 9, HCC 11; sessions 101 and 138 (not independent) | J5: Team OI Notes | K5: Not robust across days (cultures appeared to relearn each session); 2D monolayers, not organoids. Resolve n (cultures vs sessions) in Figure 5 legend and Methods.
A6: C02 | B6: doi:10.1016/j.neuron.2022.09.001 | C6: Kagan 2022 | D6: Sentience/intelligence | E6: 'Sentience' (responsive to sensory impressions) | F6: Not demonstrated | J6: Team OI Notes | K6: Team notes: very weak definition, so the title overstates the result. Coder to confirm the tag.
A7: C03 | B7: doi:10.1038/s41928-023-01069-w | C7: Cai 2023 | D7: Computational performance | E7: Henon-map prediction improves with training in organoids (about 0.36 on day 1 to about 0.81 after four epochs) | F7: Demonstrated under constraints | G7: Measured | H7: Linear regression; ANN with/without LSTM (about 50 epochs). Baseline strength unverified; fair check is a software reservoir of similar size | I7: Not recorded; verify | J7: Team OI Notes | K7: Negative control (K252a) about 0.31 to 0.39; blank chip 0. Authors list organoid heterogeneity and variable viability as limits.
A8: C04 | B8: doi:10.1038/s41928-023-01069-w | C8: Cai 2023 | D8: Efficiency (energy/sample/cost) | E8: Energy advantage of brain over AI hardware (about 20 W vs about 8 MW) | F8: Not demonstrated | G8: None | J8: Team OI Notes | K8: Motivation only (Introduction/Discussion); no energy measured for Brainoware.
A9: C05 | B9: doi:10.34133/cbsystems.0336 | C9: Khajehnejad 2025 | D9: Efficiency (energy/sample/cost) | E9: Sample efficiency of cultures versus DQN, A2C and PPO | F9: Demonstrated under constraints | G9: Measured | H9: DQN, A2C, PPO. RL got 40x40 pixels vs cultures' 8-pixel input; 70-episode cap mapped to about 20 minutes | I9: HCC 174 sessions, MCC 110 sessions | J9: Team OI Notes | K9: With 11,000 episodes all three RL algorithms learned. Hypothesis stated up front. Cortical Labs co-authors. Authors call energy comparison 'difficult'.
A10: C06 | B10: doi:10.3389/frai.2024.1376042 | C10: Jordan 2024 | D10: Other | E10: Platform infrastructure: organoids maintained and stimulated remotely; lifespan up to 100 days in best cases | F10: Demonstrated | G10: Measured | I10: Over 1,000 organoids over three years (per team notes) | J10: Team OI Notes | K10: Section labels for lifespan and capacity limits were inferred in the notes; confirm in the PDF.
A11: C07 | B11: doi:10.3389/frai.2024.1376042 | C11: Jordan 2024 | D11: Efficiency (energy/sample/cost) | E11: Energy efficiency of wetware versus silicon | F11: Projected | G11: Projected | H11: GPT-3 training energy vs 20 W brain (motivation) | J11: Team OI Notes | K11: No measured energy or power figures. A fair comparison must count two incubators, a peristaltic pump, a syringe pump and cameras per MEA.
A12: C08 | B12: doi:10.3389/frai.2024.1376042 | C12: Jordan 2024 | D12: Computational performance | E12: Computing performance / classification accuracy | F12: Not demonstrated | G12: None | J12: Team OI Notes | K12: Team notes: work shown is stimulation experiments, not a computing benchmark. Do not cite the 95.5% figure as accuracy; it came from an extraction tool, verify in Section 5.2.
A13: C09 | B13: doi:10.3389/fsci.2023.1017235 | C13: Smirnova 2023 | D13: Efficiency (energy/sample/cost) | E13: Brain-vs-machine efficiency numbers (Frontier 21 MW vs brain 10-20 W; about 10^10x energy; >10^6x data efficiency) | F13: Illustrative | G13: Cited from other work | H13: Frontier supercomputer; AlphaGo | J13: Team OI Notes | K13: Whole-brain figures, not organoid. Authors say comparisons 'serve only as illustrations' and OI power demands are 'very different'.
A14: C10 | B14: doi:10.3389/fsci.2023.1017235 | C14: Smirnova 2023 | D14: Computational performance | E14: Per-organoid capacity (about 800 MB) and OI performance potential | F14: Aspirational | G14: Projected | J14: Team OI Notes | K14: Theoretical, based on under 500 um diameter and under 100,000 cells. Authors say most biocomputing research 'remains in its infancy'.
A15: C11 | B15: doi:10.3389/fsci.2023.1017235 | C15: Smirnova 2023 | D15: Learning/adaptation | E15: Learning in cultures cited as support for OI | F15: Demonstrated | G15: Cited from other work | J15: Team OI Notes | K15: Team notes: demonstrated elsewhere (Kagan), in 2D cultures only; not organoid evidence.

Sheet Scoring
A1: Scoring sheet: one row per included paper
A2: Score each item 0/1/2 or NA (see Rubric_Anchors). Rater 1 and Rater 2 score independently without seeing each other's columns; the Final block shows the agreed score, or DISCUSS where raters differ. After discussion, overwrite DISCUSS cells with the agreed value.
A3: Blue-on-yellow = team input. Columns E and F are pre-filled drafts (from abstracts and identifiers) and need checking; COI for the five seed papers comes from the team's OI Notes. Always verify scores against the PDF, not the abstract.
A4: Paper (pre-filled) | J4: Rater 1 | S4: Rater 2 | AB4: Final (auto: R1/R2 match, else DISCUSS) | AK4: Summary and tier | AP4: Notes
A5: Paper ID | B5: Paper | C5: Year | D5: Type | E5: Claim categories (draft: C=computational, L=learning, E=efficiency) | F5: Peer-review status (auto from identifier) | G5: COI / affiliation | H5: Replication evidence (cite who/where; informs RP score) | I5: Hypothesis stated up front | J5: R1 SM | K5: R1 UA | L5: R1 CT | M5: R1 CF | N5: R1 EA | O5: R1 RB | P5: R1 TR | Q5: R1 CC | R5: R1 RP | S5: R2 SM | T5: R2 UA | U5: R2 CT | V5: R2 CF | W5: R2 EA | X5: R2 RB | Y5: R2 TR | Z5: R2 CC | AA5: R2 RP | AB5: Final SM | AC5: Final UA | AD5: Final CT | AE5: Final CF | AF5: Final EA | AG5: Final RB | AH5: Final TR | AI5: Final CC | AJ5: Final RP | AK5: Final mean | AL5: Items scored | AM5: Items to discuss | AN5: Tier (auto) | AO5: Rank within tier | AP5: Notes
A6: doi:10.1016/j.neuron.2022.09.001 | B6: Kagan et al. In vitro neurons learn and exhibit sentience when embodied in a simulated game-world (DishBrain), Neuron | C6: 2022 | D6: Empirical | E6: L | F6: Peer-reviewed | G6: Mixed academic-industry authors | I6: Unknown | AB6: =IF(J6="","",IF(S6="",J6,IF(J6=S6,J6,"DISCUSS"))) | AC6: =IF(K6="","",IF(T6="",K6,IF(K6=T6,K6,"DISCUSS"))) | AD6: =IF(L6="","",IF(U6="",L6,IF(L6=U6,L6,"DISCUSS"))) | AE6: =IF(M6="","",IF(V6="",M6,IF(M6=V6,M6,"DISCUSS"))) | AF6: =IF(N6="","",IF(W6="",N6,IF(N6=W6,N6,"DISCUSS"))) | AG6: =IF(O6="","",IF(X6="",O6,IF(O6=X6,O6,"DISCUSS"))) | AH6: =IF(P6="","",IF(Y6="",P6,IF(P6=Y6,P6,"DISCUSS"))) | AI6: =IF(Q6="","",IF(Z6="",Q6,IF(Q6=Z6,Q6,"DISCUSS"))) | AJ6: =IF(R6="","",IF(AA6="",R6,IF(R6=AA6,R6,"DISCUSS"))) | AK6: =IFERROR(AVERAGE(AB6:AJ6),"") | AL6: =COUNT(AB6:AJ6) -> 0 | AM6: =COUNTIF(AB6:AJ6,"DISCUSS") -> 0 | AN6: =IF(AL6=0,"",IF(AM6>0,"Resolve DISCUSS",IF(AL6<Tiers!$B$6,"Unrated",IF(AK6>=Tiers!$B$4,"High",IF(AK6>=Tiers!$B$5,"Medium","Low"))))) | AO6: =IF(OR(AN6="",AN6="Unrated",AN6="Resolve DISCUSS"),"",COUNTIFS($AN$6:$AN$105,AN6,$AK$6:$AK$105,">"&AK6)+1)
A7: doi:10.1038/s41928-023-01069-w | B7: Cai et al. Brain organoid reservoir computing for artificial intelligence (Brainoware), Nat Electron | C7: 2023 | D7: Empirical | E7: C,E | F7: Peer-reviewed | G7: Academic, none declared | I7: Unknown | AB7: =IF(J7="","",IF(S7="",J7,IF(J7=S7,J7,"DISCUSS"))) | AC7: =IF(K7="","",IF(T7="",K7,IF(K7=T7,K7,"DISCUSS"))) | AD7: =IF(L7="","",IF(U7="",L7,IF(L7=U7,L7,"DISCUSS"))) | AE7: =IF(M7="","",IF(V7="",M7,IF(M7=V7,M7,"DISCUSS"))) | AF7: =IF(N7="","",IF(W7="",N7,IF(N7=W7,N7,"DISCUSS"))) | AG7: =IF(O7="","",IF(X7="",O7,IF(O7=X7,O7,"DISCUSS"))) | AH7: =IF(P7="","",IF(Y7="",P7,IF(P7=Y7,P7,"DISCUSS"))) | AI7: =IF(Q7="","",IF(Z7="",Q7,IF(Q7=Z7,Q7,"DISCUSS"))) | AJ7: =IF(R7="","",IF(AA7="",R7,IF(R7=AA7,R7,"DISCUSS"))) | AK7: =IFERROR(AVERAGE(AB7:AJ7),"") | AL7: =COUNT(AB7:AJ7) -> 0 | AM7: =COUNTIF(AB7:AJ7,"DISCUSS") -> 0 | AN7: =IF(AL7=0,"",IF(AM7>0,"Resolve DISCUSS",IF(AL7<Tiers!$B$6,"Unrated",IF(AK7>=Tiers!$B$4,"High",IF(AK7>=Tiers!$B$5,"Medium","Low"))))) | AO7: =IF(OR(AN7="",AN7="Unrated",AN7="Resolve DISCUSS"),"",COUNTIFS($AN$6:$AN$105,AN7,$AK$6:$AK$105,">"&AK7)+1)
A8: doi:10.34133/cbsystems.0336 | B8: Khajehnejad et al. Dynamic network plasticity and sample efficiency in biological neural cultures: comparison with deep RL, Cyborg Bionic Syst | C8: 2025 | D8: Empirical | E8: L,E | F8: Peer-reviewed | G8: Mixed academic-industry authors | I8: Unknown | AB8: =IF(J8="","",IF(S8="",J8,IF(J8=S8,J8,"DISCUSS"))) | AC8: =IF(K8="","",IF(T8="",K8,IF(K8=T8,K8,"DISCUSS"))) | AD8: =IF(L8="","",IF(U8="",L8,IF(L8=U8,L8,"DISCUSS"))) | AE8: =IF(M8="","",IF(V8="",M8,IF(M8=V8,M8,"DISCUSS"))) | AF8: =IF(N8="","",IF(W8="",N8,IF(N8=W8,N8,"DISCUSS"))) | AG8: =IF(O8="","",IF(X8="",O8,IF(O8=X8,O8,"DISCUSS"))) | AH8: =IF(P8="","",IF(Y8="",P8,IF(P8=Y8,P8,"DISCUSS"))) | AI8: =IF(Q8="","",IF(Z8="",Q8,IF(Q8=Z8,Q8,"DISCUSS"))) | AJ8: =IF(R8="","",IF(AA8="",R8,IF(R8=AA8,R8,"DISCUSS"))) | AK8: =IFERROR(AVERAGE(AB8:AJ8),"") | AL8: =COUNT(AB8:AJ8) -> 0 | AM8: =COUNTIF(AB8:AJ8,"DISCUSS") -> 0 | AN8: =IF(AL8=0,"",IF(AM8>0,"Resolve DISCUSS",IF(AL8<Tiers!$B$6,"Unrated",IF(AK8>=Tiers!$B$4,"High",IF(AK8>=Tiers!$B$5,"Medium","Low"))))) | AO8: =IF(OR(AN8="",AN8="Unrated",AN8="Resolve DISCUSS"),"",COUNTIFS($AN$6:$AN$105,AN8,$AK$6:$AK$105,">"&AK8)+1)
A9: doi:10.3389/frai.2024.1376042 | B9: Jordan et al. Open and remotely accessible Neuroplatform for research in wetware computing (FinalSpark), Front AI | C9: 2024 | D9: Empirical | E9: C,E | F9: Peer-reviewed | G9: Company / industry source | I9: Unknown | AB9: =IF(J9="","",IF(S9="",J9,IF(J9=S9,J9,"DISCUSS"))) | AC9: =IF(K9="","",IF(T9="",K9,IF(K9=T9,K9,"DISCUSS"))) | AD9: =IF(L9="","",IF(U9="",L9,IF(L9=U9,L9,"DISCUSS"))) | AE9: =IF(M9="","",IF(V9="",M9,IF(M9=V9,M9,"DISCUSS"))) | AF9: =IF(N9="","",IF(W9="",N9,IF(N9=W9,N9,"DISCUSS"))) | AG9: =IF(O9="","",IF(X9="",O9,IF(O9=X9,O9,"DISCUSS"))) | AH9: =IF(P9="","",IF(Y9="",P9,IF(P9=Y9,P9,"DISCUSS"))) | AI9: =IF(Q9="","",IF(Z9="",Q9,IF(Q9=Z9,Q9,"DISCUSS"))) | AJ9: =IF(R9="","",IF(AA9="",R9,IF(R9=AA9,R9,"DISCUSS"))) | AK9: =IFERROR(AVERAGE(AB9:AJ9),"") | AL9: =COUNT(AB9:AJ9) -> 0 | AM9: =COUNTIF(AB9:AJ9,"DISCUSS") -> 0 | AN9: =IF(AL9=0,"",IF(AM9>0,"Resolve DISCUSS",IF(AL9<Tiers!$B$6,"Unrated",IF(AK9>=Tiers!$B$4,"High",IF(AK9>=Tiers!$B$5,"Medium","Low"))))) | AO9: =IF(OR(AN9="",AN9="Unrated",AN9="Resolve DISCUSS"),"",COUNTIFS($AN$6:$AN$105,AN9,$AK$6:$AK$105,">"&AK9)+1)
A10: doi:10.64898/2026.10.11.758231 | B10: PULSE: foundation model for brain organoid network dynamics reporting intrinsic computation | C10: 2026 | D10: Empirical | E10: C | F10: Preprint | G10: Not checked | I10: Unknown | AB10: =IF(J10="","",IF(S10="",J10,IF(J10=S10,J10,"DISCUSS"))) | AC10: =IF(K10="","",IF(T10="",K10,IF(K10=T10,K10,"DISCUSS"))) | AD10: =IF(L10="","",IF(U10="",L10,IF(L10=U10,L10,"DISCUSS"))) | AE10: =IF(M10="","",IF(V10="",M10,IF(M10=V10,M10,"DISCUSS"))) | AF10: =IF(N10="","",IF(W10="",N10,IF(N10=W10,N10,"DISCUSS"))) | AG10: =IF(O10="","",IF(X10="",O10,IF(O10=X10,O10,"DISCUSS"))) | AH10: =IF(P10="","",IF(Y10="",P10,IF(P10=Y10,P10,"DISCUSS"))) | AI10: =IF(Q10="","",IF(Z10="",Q10,IF(Q10=Z10,Q10,"DISCUSS"))) | AJ10: =IF(R10="","",IF(AA10="",R10,IF(R10=AA10,R10,"DISCUSS"))) | AK10: =IFERROR(AVERAGE(AB10:AJ10),"") | AL10: =COUNT(AB10:AJ10) -> 0 | AM10: =COUNTIF(AB10:AJ10,"DISCUSS") -> 0 | AN10: =IF(AL10=0,"",IF(AM10>0,"Resolve DISCUSS",IF(AL10<Tiers!$B$6,"Unrated",IF(AK10>=Tiers!$B$4,"High",IF(AK10>=Tiers!$B$5,"Medium","Low"))))) | AO10: =IF(OR(AN10="",AN10="Unrated",AN10="Resolve DISCUSS"),"",COUNTIFS($AN$6:$AN$105,AN10,$AK$6:$AK$105,">"&AK10)+1)
A11: doi:10.64898/2026.09.09.750433 | B11: Information processing-like phenotype of human brain organoids | C11: 2026 | D11: Empirical | E11: C | F11: Preprint | G11: Not checked | I11: Unknown | AB11: =IF(J11="","",IF(S11="",J11,IF(J11=S11,J11,"DISCUSS"))) | AC11: =IF(K11="","",IF(T11="",K11,IF(K11=T11,K11,"DISCUSS"))) | AD11: =IF(L11="","",IF(U11="",L11,IF(L11=U11,L11,"DISCUSS"))) | AE11: =IF(M11="","",IF(V11="",M11,IF(M11=V11,M11,"DISCUSS"))) | AF11: =IF(N11="","",IF(W11="",N11,IF(N11=W11,N11,"DISCUSS"))) | AG11: =IF(O11="","",IF(X11="",O11,IF(O11=X11,O11,"DISCUSS"))) | AH11: =IF(P11="","",IF(Y11="",P11,IF(P11=Y11,P11,"DISCUSS"))) | AI11: =IF(Q11="","",IF(Z11="",Q11,IF(Q11=Z11,Q11,"DISCUSS"))) | AJ11: =IF(R11="","",IF(AA11="",R11,IF(R11=AA11,R11,"DISCUSS"))) | AK11: =IFERROR(AVERAGE(AB11:AJ11),"") | AL11: =COUNT(AB11:AJ11) -> 0 | AM11: =COUNTIF(AB11:AJ11,"DISCUSS") -> 0 | AN11: =IF(AL11=0,"",IF(AM11>0,"Resolve DISCUSS",IF(AL11<Tiers!$B$6,"Unrated",IF(AK11>=Tiers!$B$4,"High",IF(AK11>=Tiers!$B$5,"Medium","Low"))))) | AO11: =IF(OR(AN11="",AN11="Unrated",AN11="Resolve DISCUSS"),"",COUNTIFS($AN$6:$AN$105,AN11,$AK$6:$AK$105,">"&AK11)+1)
A12: pmcid:PMC11661084 | B12: Goal-directed learning in cortical organoids (Cell Rep) | C12: 2026 | D12: Empirical | E12: L | F12: Peer-reviewed | G12: Not checked | I12: Unknown | AB12: =IF(J12="","",IF(S12="",J12,IF(J12=S12,J12,"DISCUSS"))) | AC12: =IF(K12="","",IF(T12="",K12,IF(K12=T12,K12,"DISCUSS"))) | AD12: =IF(L12="","",IF(U12="",L12,IF(L12=U12,L12,"DISCUSS"))) | AE12: =IF(M12="","",IF(V12="",M12,IF(M12=V12,M12,"DISCUSS"))) | AF12: =IF(N12="","",IF(W12="",N12,IF(N12=W12,N12,"DISCUSS"))) | AG12: =IF(O12="","",IF(X12="",O12,IF(O12=X12,O12,"DISCUSS"))) | AH12: =IF(P12="","",IF(Y12="",P12,IF(P12=Y12,P12,"DISCUSS"))) | AI12: =IF(Q12="","",IF(Z12="",Q12,IF(Q12=Z12,Q12,"DISCUSS"))) | AJ12: =IF(R12="","",IF(AA12="",R12,IF(R12=AA12,R12,"DISCUSS"))) | AK12: =IFERROR(AVERAGE(AB12:AJ12),"") | AL12: =COUNT(AB12:AJ12) -> 0 | AM12: =COUNTIF(AB12:AJ12,"DISCUSS") -> 0 | AN12: =IF(AL12=0,"",IF(AM12>0,"Resolve DISCUSS",IF(AL12<Tiers!$B$6,"Unrated",IF(AK12>=Tiers!$B$4,"High",IF(AK12>=Tiers!$B$5,"Medium","Low"))))) | AO12: =IF(OR(AN12="",AN12="Unrated",AN12="Resolve DISCUSS"),"",COUNTIFS($AN$6:$AN$105,AN12,$AK$6:$AK$105,">"&AK12)+1)
A13: pmcid:PMC12357958 | B13: Human neural organoid microphysiological systems show building blocks for basic learning and memory (Commun Biol) | C13: 2025 | D13: Empirical | E13: L | F13: Peer-reviewed | G13: Not checked | I13: Unknown | AB13: =IF(J13="","",IF(S13="",J13,IF(J13=S13,J13,"DISCUSS"))) | AC13: =IF(K13="","",IF(T13="",K13,IF(K13=T13,K13,"DISCUSS"))) | AD13: =IF(L13="","",IF(U13="",L13,IF(L13=U13,L13,"DISCUSS"))) | AE13: =IF(M13="","",IF(V13="",M13,IF(M13=V13,M13,"DISCUSS"))) | AF13: =IF(N13="","",IF(W13="",N13,IF(N13=W13,N13,"DISCUSS"))) | AG13: =IF(O13="","",IF(X13="",O13,IF(O13=X13,O13,"DISCUSS"))) | AH13: =IF(P13="","",IF(Y13="",P13,IF(P13=Y13,P13,"DISCUSS"))) | AI13: =IF(Q13="","",IF(Z13="",Q13,IF(Q13=Z13,Q13,"DISCUSS"))) | AJ13: =IF(R13="","",IF(AA13="",R13,IF(R13=AA13,R13,"DISCUSS"))) | AK13: =IFERROR(AVERAGE(AB13:AJ13),"") | AL13: =COUNT(AB13:AJ13) -> 0 | AM13: =COUNTIF(AB13:AJ13,"DISCUSS") -> 0 | AN13: =IF(AL13=0,"",IF(AM13>0,"Resolve DISCUSS",IF(AL13<Tiers!$B$6,"Unrated",IF(AK13>=Tiers!$B$4,"High",IF(AK13>=Tiers!$B$5,"Medium","Low"))))) | AO13: =IF(OR(AN13="",AN13="Unrated",AN13="Resolve DISCUSS"),"",COUNTIFS($AN$6:$AN$105,AN13,$AK$6:$AK$105,">"&AK13)+1)
A14: pmcid:PMC12066566 | B14: Engineered biological neuronal networks as basic logic operators (Front Comput Neurosci) | C14: 2025 | D14: Empirical | E14: C | F14: Peer-reviewed | G14: Not checked | I14: Unknown | AB14: =IF(J14="","",IF(S14="",J14,IF(J14=S14,J14,"DISCUSS"))) | AC14: =IF(K14="","",IF(T14="",K14,IF(K14=T14,K14,"DISCUSS"))) | AD14: =IF(L14="","",IF(U14="",L14,IF(L14=U14,L14,"DISCUSS"))) | AE14: =IF(M14="","",IF(V14="",M14,IF(M14=V14,M14,"DISCUSS"))) | AF14: =IF(N14="","",IF(W14="",N14,IF(N14=W14,N14,"DISCUSS"))) | AG14: =IF(O14="","",IF(X14="",O14,IF(O14=X14,O14,"DISCUSS"))) | AH14: =IF(P14="","",IF(Y14="",P14,IF(P14=Y14,P14,"DISCUSS"))) | AI14: =IF(Q14="","",IF(Z14="",Q14,IF(Q14=Z14,Q14,"DISCUSS"))) | AJ14: =IF(R14="","",IF(AA14="",R14,IF(R14=AA14,R14,"DISCUSS"))) | AK14: =IFERROR(AVERAGE(AB14:AJ14),"") | AL14: =COUNT(AB14:AJ14) -> 0 | AM14: =COUNTIF(AB14:AJ14,"DISCUSS") -> 0 | AN14: =IF(AL14=0,"",IF(AM14>0,"Resolve DISCUSS",IF(AL14<Tiers!$B$6,"Unrated",IF(AK14>=Tiers!$B$4,"High",IF(AK14>=Tiers!$B$5,"Medium","Low"))))) | AO14: =IF(OR(AN14="",AN14="Unrated",AN14="Resolve DISCUSS"),"",COUNTIFS($AN$6:$AN$105,AN14,$AK$6:$AK$105,">"&AK14)+1)
A15: doi:10.64898/2026.08.10.743829 | B15: Handwritten digit classification with neural cultures: architecture, dynamics, decoding | C15: 2026 | D15: Empirical | E15: C,E | F15: Preprint | G15: Not checked | I15: Unknown | AB15: =IF(J15="","",IF(S15="",J15,IF(J15=S15,J15,"DISCUSS"))) | AC15: =IF(K15="","",IF(T15="",K15,IF(K15=T15,K15,"DISCUSS"))) | AD15: =IF(L15="","",IF(U15="",L15,IF(L15=U15,L15,"DISCUSS"))) | AE15: =IF(M15="","",IF(V15="",M15,IF(M15=V15,M15,"DISCUSS"))) | AF15: =IF(N15="","",IF(W15="",N15,IF(N15=W15,N15,"DISCUSS"))) | AG15: =IF(O15="","",IF(X15="",O15,IF(O15=X15,O15,"DISCUSS"))) | AH15: =IF(P15="","",IF(Y15="",P15,IF(P15=Y15,P15,"DISCUSS"))) | AI15: =IF(Q15="","",IF(Z15="",Q15,IF(Q15=Z15,Q15,"DISCUSS"))) | AJ15: =IF(R15="","",IF(AA15="",R15,IF(R15=AA15,R15,"DISCUSS"))) | AK15: =IFERROR(AVERAGE(AB15:AJ15),"") | AL15: =COUNT(AB15:AJ15) -> 0 | AM15: =COUNTIF(AB15:AJ15,"DISCUSS") -> 0 | AN15: =IF(AL15=0,"",IF(AM15>0,"Resolve DISCUSS",IF(AL15<Tiers!$B$6,"Unrated",IF(AK15>=Tiers!$B$4,"High",IF(AK15>=Tiers!$B$5,"Medium","Low"))))) | AO15: =IF(OR(AN15="",AN15="Unrated",AN15="Resolve DISCUSS"),"",COUNTIFS($AN$6:$AN$105,AN15,$AK$6:$AK$105,">"&AK15)+1)
A16: arxiv:2602.05737 | B16: Neuro-inspired visual pattern recognition via biological reservoir computing | C16: 2026 | D16: Empirical | E16: C | F16: Preprint | G16: Not checked | I16: Unknown | AB16: =IF(J16="","",IF(S16="",J16,IF(J16=S16,J16,"DISCUSS"))) | AC16: =IF(K16="","",IF(T16="",K16,IF(K16=T16,K16,"DISCUSS"))) | AD16: =IF(L16="","",IF(U16="",L16,IF(L16=U16,L16,"DISCUSS"))) | AE16: =IF(M16="","",IF(V16="",M16,IF(M16=V16,M16,"DISCUSS"))) | AF16: =IF(N16="","",IF(W16="",N16,IF(N16=W16,N16,"DISCUSS"))) | AG16: =IF(O16="","",IF(X16="",O16,IF(O16=X16,O16,"DISCUSS"))) | AH16: =IF(P16="","",IF(Y16="",P16,IF(P16=Y16,P16,"DISCUSS"))) | AI16: =IF(Q16="","",IF(Z16="",Q16,IF(Q16=Z16,Q16,"DISCUSS"))) | AJ16: =IF(R16="","",IF(AA16="",R16,IF(R16=AA16,R16,"DISCUSS"))) | AK16: =IFERROR(AVERAGE(AB16:AJ16),"") | AL16: =COUNT(AB16:AJ16) -> 0 | AM16: =COUNTIF(AB16:AJ16,"DISCUSS") -> 0 | AN16: =IF(AL16=0,"",IF(AM16>0,"Resolve DISCUSS",IF(AL16<Tiers!$B$6,"Unrated",IF(AK16>=Tiers!$B$4,"High",IF(AK16>=Tiers!$B$5,"Medium","Low"))))) | AO16: =IF(OR(AN16="",AN16="Unrated",AN16="Resolve DISCUSS"),"",COUNTIFS($AN$6:$AN$105,AN16,$AK$6:$AK$105,">"&AK16)+1)
A17: arxiv:2505.03510 | B17: From neurons to computation: biological reservoir computing for pattern recognition | C17: 2025 | D17: Empirical | E17: C | F17: Preprint | G17: Not checked | I17: Unknown | AB17: =IF(J17="","",IF(S17="",J17,IF(J17=S17,J17,"DISCUSS"))) | AC17: =IF(K17="","",IF(T17="",K17,IF(K17=T17,K17,"DISCUSS"))) | AD17: =IF(L17="","",IF(U17="",L17,IF(L17=U17,L17,"DISCUSS"))) | AE17: =IF(M17="","",IF(V17="",M17,IF(M17=V17,M17,"DISCUSS"))) | AF17: =IF(N17="","",IF(W17="",N17,IF(N17=W17,N17,"DISCUSS"))) | AG17: =IF(O17="","",IF(X17="",O17,IF(O17=X17,O17,"DISCUSS"))) | AH17: =IF(P17="","",IF(Y17="",P17,IF(P17=Y17,P17,"DISCUSS"))) | AI17: =IF(Q17="","",IF(Z17="",Q17,IF(Q17=Z17,Q17,"DISCUSS"))) | AJ17: =IF(R17="","",IF(AA17="",R17,IF(R17=AA17,R17,"DISCUSS"))) | AK17: =IFERROR(AVERAGE(AB17:AJ17),"") | AL17: =COUNT(AB17:AJ17) -> 0 | AM17: =COUNTIF(AB17:AJ17,"DISCUSS") -> 0 | AN17: =IF(AL17=0,"",IF(AM17>0,"Resolve DISCUSS",IF(AL17<Tiers!$B$6,"Unrated",IF(AK17>=Tiers!$B$4,"High",IF(AK17>=Tiers!$B$5,"Medium","Low"))))) | AO17: =IF(OR(AN17="",AN17="Unrated",AN17="Resolve DISCUSS"),"",COUNTIFS($AN$6:$AN$105,AN17,$AK$6:$AK$105,">"&AK17)+1)
... A33: pmid:41983381 | B33: In vitro biological neuronal networks achieve low power consumption and high-speed communication through predictable stimulation | C33: 2026 | D33: Empirical | E33: E | F33: Peer-reviewed | G33: Not checked | I33: Unknown | AB33: =IF(J33="","",IF(S33="",J33,IF(J33=S33,J33,"DISCUSS"))) | AC33: =IF(K33="","",IF(T33="",K33,IF(K33=T33,K33,"DISCUSS"))) | AD33: =IF(L33="","",IF(U33="",L33,IF(L33=U33,L33,"DISCUSS"))) | AE33: =IF(M33="","",IF(V33="",M33,IF(M33=V33,M33,"DISCUSS"))) | AF33: =IF(N33="","",IF(W33="",N33,IF(N33=W33,N33,"DISCUSS"))) | AG33: =IF(O33="","",IF(X33="",O33,IF(O33=X33,O33,"DISCUSS"))) | AH33: =IF(P33="","",IF(Y33="",P33,IF(P33=Y33,P33,"DISCUSS"))) | AI33: =IF(Q33="","",IF(Z33="",Q33,IF(Q33=Z33,Q33,"DISCUSS"))) | AJ33: =IF(R33="","",IF(AA33="",R33,IF(R33=AA33,R33,"DISCUSS"))) | AK33: =IFERROR(AVERAGE(AB33:AJ33),"") | AL33: =COUNT(AB33:AJ33) -> 0 | AM33: =COUNTIF(AB33:AJ33,"DISCUSS") -> 0 | AN33: =IF(AL33=0,"",IF(AM33>0,"Resolve DISCUSS",IF(AL33<Tiers!$B$6,"Unrated",IF(AK33>=Tiers!$B$4,"High",IF(AK33>=Tiers!$B$5,"Medium","Low"))))) | AO33: =IF(OR(AN33="",AN33="Unrated",AN33="Resolve DISCUSS"),"",COUNTIFS($AN$6:$AN$105,AN33,$AK$6:$AK$105,">"&AK33)+1)
AB34: =IF(J34="","",IF(S34="",J34,IF(J34=S34,J34,"DISCUSS"))) | AC34: =IF(K34="","",IF(T34="",K34,IF(K34=T34,K34,"DISCUSS"))) | AD34: =IF(L34="","",IF(U34="",L34,IF(L34=U34,L34,"DISCUSS"))) | AE34: =IF(M34="","",IF(V34="",M34,IF(M34=V34,M34,"DISCUSS"))) | AF34: =IF(N34="","",IF(W34="",N34,IF(N34=W34,N34,"DISCUSS"))) | AG34: =IF(O34="","",IF(X34="",O34,IF(O34=X34,O34,"DISCUSS"))) | AH34: =IF(P34="","",IF(Y34="",P34,IF(P34=Y34,P34,"DISCUSS"))) | AI34: =IF(Q34="","",IF(Z34="",Q34,IF(Q34=Z34,Q34,"DISCUSS"))) | AJ34: =IF(R34="","",IF(AA34="",R34,IF(R34=AA34,R34,"DISCUSS"))) | AK34: =IFERROR(AVERAGE(AB34:AJ34),"") | AL34: =COUNT(AB34:AJ34) -> 0 | AM34: =COUNTIF(AB34:AJ34,"DISCUSS") -> 0 | AN34: =IF(AL34=0,"",IF(AM34>0,"Resolve DISCUSS",IF(AL34<Tiers!$B$6,"Unrated",IF(AK34>=Tiers!$B$4,"High",IF(AK34>=Tiers!$B$5,"Medium","Low"))))) | AO34: =IF(OR(AN34="",AN34="Unrated",AN34="Resolve DISCUSS"),"",COUNTIFS($AN$6:$AN$105,AN34,$AK$6:$AK$105,">"&AK34)+1)
AB35: =IF(J35="","",IF(S35="",J35,IF(J35=S35,J35,"DISCUSS"))) | AC35: =IF(K35="","",IF(T35="",K35,IF(K35=T35,K35,"DISCUSS"))) | AD35: =IF(L35="","",IF(U35="",L35,IF(L35=U35,L35,"DISCUSS"))) | AE35: =IF(M35="","",IF(V35="",M35,IF(M35=V35,M35,"DISCUSS"))) | AF35: =IF(N35="","",IF(W35="",N35,IF(N35=W35,N35,"DISCUSS"))) | AG35: =IF(O35="","",IF(X35="",O35,IF(O35=X35,O35,"DISCUSS"))) | AH35: =IF(P35="","",IF(Y35="",P35,IF(P35=Y35,P35,"DISCUSS"))) | AI35: =IF(Q35="","",IF(Z35="",Q35,IF(Q35=Z35,Q35,"DISCUSS"))) | AJ35: =IF(R35="","",IF(AA35="",R35,IF(R35=AA35,R35,"DISCUSS"))) | AK35: =IFERROR(AVERAGE(AB35:AJ35),"") | AL35: =COUNT(AB35:AJ35) -> 0 | AM35: =COUNTIF(AB35:AJ35,"DISCUSS") -> 0 | AN35: =IF(AL35=0,"",IF(AM35>0,"Resolve DISCUSS",IF(AL35<Tiers!$B$6,"Unrated",IF(AK35>=Tiers!$B$4,"High",IF(AK35>=Tiers!$B$5,"Medium","Low"))))) | AO35: =IF(OR(AN35="",AN35="Unrated",AN35="Resolve DISCUSS"),"",COUNTIFS($AN$6:$AN$105,AN35,$AK$6:$AK$105,">"&AK35)+1)
AB36: =IF(J36="","",IF(S36="",J36,IF(J36=S36,J36,"DISCUSS"))) | AC36: =IF(K36="","",IF(T36="",K36,IF(K36=T36,K36,"DISCUSS"))) | AD36: =IF(L36="","",IF(U36="",L36,IF(L36=U36,L36,"DISCUSS"))) | AE36: =IF(M36="","",IF(V36="",M36,IF(M36=V36,M36,"DISCUSS"))) | AF36: =IF(N36="","",IF(W36="",N36,IF(N36=W36,N36,"DISCUSS"))) | AG36: =IF(O36="","",IF(X36="",O36,IF(O36=X36,O36,"DISCUSS"))) | AH36: =IF(P36="","",IF(Y36="",P36,IF(P36=Y36,P36,"DISCUSS"))) | AI36: =IF(Q36="","",IF(Z36="",Q36,IF(Q36=Z36,Q36,"DISCUSS"))) | AJ36: =IF(R36="","",IF(AA36="",R36,IF(R36=AA36,R36,"DISCUSS"))) | AK36: =IFERROR(AVERAGE(AB36:AJ36),"") | AL36: =COUNT(AB36:AJ36) -> 0 | AM36: =COUNTIF(AB36:AJ36,"DISCUSS") -> 0 | AN36: =IF(AL36=0,"",IF(AM36>0,"Resolve DISCUSS",IF(AL36<Tiers!$B$6,"Unrated",IF(AK36>=Tiers!$B$4,"High",IF(AK36>=Tiers!$B$5,"Medium","Low"))))) | AO36: =IF(OR(AN36="",AN36="Unrated",AN36="Resolve DISCUSS"),"",COUNTIFS($AN$6:$AN$105,AN36,$AK$6:$AK$105,">"&AK36)+1)
AB37: =IF(J37="","",IF(S37="",J37,IF(J37=S37,J37,"DISCUSS"))) | AC37: =IF(K37="","",IF(T37="",K37,IF(K37=T37,K37,"DISCUSS"))) | AD37: =IF(L37="","",IF(U37="",L37,IF(L37=U37,L37,"DISCUSS"))) | AE37: =IF(M37="","",IF(V37="",M37,IF(M37=V37,M37,"DISCUSS"))) | AF37: =IF(N37="","",IF(W37="",N37,IF(N37=W37,N37,"DISCUSS"))) | AG37: =IF(O37="","",IF(X37="",O37,IF(O37=X37,O37,"DISCUSS"))) | AH37: =IF(P37="","",IF(Y37="",P37,IF(P37=Y37,P37,"DISCUSS"))) | AI37: =IF(Q37="","",IF(Z37="",Q37,IF(Q37=Z37,Q37,"DISCUSS"))) | AJ37: =IF(R37="","",IF(AA37="",R37,IF(R37=AA37,R37,"DISCUSS"))) | AK37: =IFERROR(AVERAGE(AB37:AJ37),"") | AL37: =COUNT(AB37:AJ37) -> 0 | AM37: =COUNTIF(AB37:AJ37,"DISCUSS") -> 0 | AN37: =IF(AL37=0,"",IF(AM37>0,"Resolve DISCUSS",IF(AL37<Tiers!$B$6,"Unrated",IF(AK37>=Tiers!$B$4,"High",IF(AK37>=Tiers!$B$5,"Medium","Low"))))) | AO37: =IF(OR(AN37="",AN37="Unrated",AN37="Resolve DISCUSS"),"",COUNTIFS($AN$6:$AN$105,AN37,$AK$6:$AK$105,">"&AK37)+1)
AB38: =IF(J38="","",IF(S38="",J38,IF(J38=S38,J38,"DISCUSS"))) | AC38: =IF(K38="","",IF(T38="",K38,IF(K38=T38,K38,"DISCUSS"))) | AD38: =IF(L38="","",IF(U38="",L38,IF(L38=U38,L38,"DISCUSS"))) | AE38: =IF(M38="","",IF(V38="",M38,IF(M38=V38,M38,"DISCUSS"))) | AF38: =IF(N38="","",IF(W38="",N38,IF(N38=W38,N38,"DISCUSS"))) | AG38: =IF(O38="","",IF(X38="",O38,IF(O38=X38,O38,"DISCUSS"))) | AH38: =IF(P38="","",IF(Y38="",P38,IF(P38=Y38,P38,"DISCUSS"))) | AI38: =IF(Q38="","",IF(Z38="",Q38,IF(Q38=Z38,Q38,"DISCUSS"))) | AJ38: =IF(R38="","",IF(AA38="",R38,IF(R38=AA38,R38,"DISCUSS"))) | AK38: =IFERROR(AVERAGE(AB38:AJ38),"") | AL38: =COUNT(AB38:AJ38) -> 0 | AM38: =COUNTIF(AB38:AJ38,"DISCUSS") -> 0 | AN38: =IF(AL38=0,"",IF(AM38>0,"Resolve DISCUSS",IF(AL38<Tiers!$B$6,"Unrated",IF(AK38>=Tiers!$B$4,"High",IF(AK38>=Tiers!$B$5,"Medium","Low"))))) | AO38: =IF(OR(AN38="",AN38="Unrated",AN38="Resolve DISCUSS"),"",COUNTIFS($AN$6:$AN$105,AN38,$AK$6:$AK$105,">"&AK38)+1)
AB39: =IF(J39="","",IF(S39="",J39,IF(J39=S39,J39,"DISCUSS"))) | AC39: =IF(K39="","",IF(T39="",K39,IF(K39=T39,K39,"DISCUSS"))) | AD39: =IF(L39="","",IF(U39="",L39,IF(L39=U39,L39,"DISCUSS"))) | AE39: =IF(M39="","",IF(V39="",M39,IF(M39=V39,M39,"DISCUSS"))) | AF39: =IF(N39="","",IF(W39="",N39,IF(N39=W39,N39,"DISCUSS"))) | AG39: =IF(O39="","",IF(X39="",O39,IF(O39=X39,O39,"DISCUSS"))) | AH39: =IF(P39="","",IF(Y39="",P39,IF(P39=Y39,P39,"DISCUSS"))) | AI39: =IF(Q39="","",IF(Z39="",Q39,IF(Q39=Z39,Q39,"DISCUSS"))) | AJ39: =IF(R39="","",IF(AA39="",R39,IF(R39=AA39,R39,"DISCUSS"))) | AK39: =IFERROR(AVERAGE(AB39:AJ39),"") | AL39: =COUNT(AB39:AJ39) -> 0 | AM39: =COUNTIF(AB39:AJ39,"DISCUSS") -> 0 | AN39: =IF(AL39=0,"",IF(AM39>0,"Resolve DISCUSS",IF(AL39<Tiers!$B$6,"Unrated",IF(AK39>=Tiers!$B$4,"High",IF(AK39>=Tiers!$B$5,"Medium","Low"))))) | AO39: =IF(OR(AN39="",AN39="Unrated",AN39="Resolve DISCUSS"),"",COUNTIFS($AN$6:$AN$105,AN39,$AK$6:$AK$105,">"&AK39)+1)
AB40: =IF(J40="","",IF(S40="",J40,IF(J40=S40,J40,"DISCUSS"))) | AC40: =IF(K40="","",IF(T40="",K40,IF(K40=T40,K40,"DISCUSS"))) | AD40: =IF(L40="","",IF(U40="",L40,IF(L40=U40,L40,"DISCUSS"))) | AE40: =IF(M40="","",IF(V40="",M40,IF(M40=V40,M40,"DISCUSS"))) | AF40: =IF(N40="","",IF(W40="",N40,IF(N40=W40,N40,"DISCUSS"))) | AG40: =IF(O40="","",IF(X40="",O40,IF(O40=X40,O40,"DISCUSS"))) | AH40: =IF(P40="","",IF(Y40="",P40,IF(P40=Y40,P40,"DISCUSS"))) | AI40: =IF(Q40="","",IF(Z40="",Q40,IF(Q40=Z40,Q40,"DISCUSS"))) | AJ40: =IF(R40="","",IF(AA40="",R40,IF(R40=AA40,R40,"DISCUSS"))) | AK40: =IFERROR(AVERAGE(AB40:AJ40),"") | AL40: =COUNT(AB40:AJ40) -> 0 | AM40: =COUNTIF(AB40:AJ40,"DISCUSS") -> 0 | AN40: =IF(AL40=0,"",IF(AM40>0,"Resolve DISCUSS",IF(AL40<Tiers!$B$6,"Unrated",IF(AK40>=Tiers!$B$4,"High",IF(AK40>=Tiers!$B$5,"Medium","Low"))))) | AO40: =IF(OR(AN40="",AN40="Unrated",AN40="Resolve DISCUSS"),"",COUNTIFS($AN$6:$AN$105,AN40,$AK$6:$AK$105,">"&AK40)+1)
AB41: =IF(J41="","",IF(S41="",J41,IF(J41=S41,J41,"DISCUSS"))) | AC41: =IF(K41="","",IF(T41="",K41,IF(K41=T41,K41,"DISCUSS"))) | AD41: =IF(L41="","",IF(U41="",L41,IF(L41=U41,L41,"DISCUSS"))) | AE41: =IF(M41="","",IF(V41="",M41,IF(M41=V41,M41,"DISCUSS"))) | AF41: =IF(N41="","",IF(W41="",N41,IF(N41=W41,N41,"DISCUSS"))) | AG41: =IF(O41="","",IF(X41="",O41,IF(O41=X41,O41,"DISCUSS"))) | AH41: =IF(P41="","",IF(Y41="",P41,IF(P41=Y41,P41,"DISCUSS"))) | AI41: =IF(Q41="","",IF(Z41="",Q41,IF(Q41=Z41,Q41,"DISCUSS"))) | AJ41: =IF(R41="","",IF(AA41="",R41,IF(R41=AA41,R41,"DISCUSS"))) | AK41: =IFERROR(AVERAGE(AB41:AJ41),"") | AL41: =COUNT(AB41:AJ41) -> 0 | AM41: =COUNTIF(AB41:AJ41,"DISCUSS") -> 0 | AN41: =IF(AL41=0,"",IF(AM41>0,"Resolve DISCUSS",IF(AL41<Tiers!$B$6,"Unrated",IF(AK41>=Tiers!$B$4,"High",IF(AK41>=Tiers!$B$5,"Medium","Low"))))) | AO41: =IF(OR(AN41="",AN41="Unrated",AN41="Resolve DISCUSS"),"",COUNTIFS($AN$6:$AN$105,AN41,$AK$6:$AK$105,">"&AK41)+1)
AB42: =IF(J42="","",IF(S42="",J42,IF(J42=S42,J42,"DISCUSS"))) | AC42: =IF(K42="","",IF(T42="",K42,IF(K42=T42,K42,"DISCUSS"))) | AD42: =IF(L42="","",IF(U42="",L42,IF(L42=U42,L42,"DISCUSS"))) | AE42: =IF(M42="","",IF(V42="",M42,IF(M42=V42,M42,"DISCUSS"))) | AF42: =IF(N42="","",IF(W42="",N42,IF(N42=W42,N42,"DISCUSS"))) | AG42: =IF(O42="","",IF(X42="",O42,IF(O42=X42,O42,"DISCUSS"))) | AH42: =IF(P42="","",IF(Y42="",P42,IF(P42=Y42,P42,"DISCUSS"))) | AI42: =IF(Q42="","",IF(Z42="",Q42,IF(Q42=Z42,Q42,"DISCUSS"))) | AJ42: =IF(R42="","",IF(AA42="",R42,IF(R42=AA42,R42,"DISCUSS"))) | AK42: =IFERROR(AVERAGE(AB42:AJ42),"") | AL42: =COUNT(AB42:AJ42) -> 0 | AM42: =COUNTIF(AB42:AJ42,"DISCUSS") -> 0 | AN42: =IF(AL42=0,"",IF(AM42>0,"Resolve DISCUSS",IF(AL42<Tiers!$B$6,"Unrated",IF(AK42>=Tiers!$B$4,"High",IF(AK42>=Tiers!$B$5,"Medium","Low"))))) | AO42: =IF(OR(AN42="",AN42="Unrated",AN42="Resolve DISCUSS"),"",COUNTIFS($AN$6:$AN$105,AN42,$AK$6:$AK$105,">"&AK42)+1)
AB43: =IF(J43="","",IF(S43="",J43,IF(J43=S43,J43,"DISCUSS"))) | AC43: =IF(K43="","",IF(T43="",K43,IF(K43=T43,K43,"DISCUSS"))) | AD43: =IF(L43="","",IF(U43="",L43,IF(L43=U43,L43,"DISCUSS"))) | AE43: =IF(M43="","",IF(V43="",M43,IF(M43=V43,M43,"DISCUSS"))) | AF43: =IF(N43="","",IF(W43="",N43,IF(N43=W43,N43,"DISCUSS"))) | AG43: =IF(O43="","",IF(X43="",O43,IF(O43=X43,O43,"DISCUSS"))) | AH43: =IF(P43="","",IF(Y43="",P43,IF(P43=Y43,P43,"DISCUSS"))) | AI43: =IF(Q43="","",IF(Z43="",Q43,IF(Q43=Z43,Q43,"DISCUSS"))) | AJ43: =IF(R43="","",IF(AA43="",R43,IF(R43=AA43,R43,"DISCUSS"))) | AK43: =IFERROR(AVERAGE(AB43:AJ43),"") | AL43: =COUNT(AB43:AJ43) -> 0 | AM43: =COUNTIF(AB43:AJ43,"DISCUSS") -> 0 | AN43: =IF(AL43=0,"",IF(AM43>0,"Resolve DISCUSS",IF(AL43<Tiers!$B$6,"Unrated",IF(AK43>=Tiers!$B$4,"High",IF(AK43>=Tiers!$B$5,"Medium","Low"))))) | AO43: =IF(OR(AN43="",AN43="Unrated",AN43="Resolve DISCUSS"),"",COUNTIFS($AN$6:$AN$105,AN43,$AK$6:$AK$105,">"&AK43)+1)
AB44: =IF(J44="","",IF(S44="",J44,IF(J44=S44,J44,"DISCUSS"))) | AC44: =IF(K44="","",IF(T44="",K44,IF(K44=T44,K44,"DISCUSS"))) | AD44: =IF(L44="","",IF(U44="",L44,IF(L44=U44,L44,"DISCUSS"))) | AE44: =IF(M44="","",IF(V44="",M44,IF(M44=V44,M44,"DISCUSS"))) | AF44: =IF(N44="","",IF(W44="",N44,IF(N44=W44,N44,"DISCUSS"))) | AG44: =IF(O44="","",IF(X44="",O44,IF(O44=X44,O44,"DISCUSS"))) | AH44: =IF(P44="","",IF(Y44="",P44,IF(P44=Y44,P44,"DISCUSS"))) | AI44: =IF(Q44="","",IF(Z44="",Q44,IF(Q44=Z44,Q44,"DISCUSS"))) | AJ44: =IF(R44="","",IF(AA44="",R44,IF(R44=AA44,R44,"DISCUSS"))) | AK44: =IFERROR(AVERAGE(AB44:AJ44),"") | AL44: =COUNT(AB44:AJ44) -> 0 | AM44: =COUNTIF(AB44:AJ44,"DISCUSS") -> 0 | AN44: =IF(AL44=0,"",IF(AM44>0,"Resolve DISCUSS",IF(AL44<Tiers!$B$6,"Unrated",IF(AK44>=Tiers!$B$4,"High",IF(AK44>=Tiers!$B$5,"Medium","Low"))))) | AO44: =IF(OR(AN44="",AN44="Unrated",AN44="Resolve DISCUSS"),"",COUNTIFS($AN$6:$AN$105,AN44,$AK$6:$AK$105,">"&AK44)+1)
AB45: =IF(J45="","",IF(S45="",J45,IF(J45=S45,J45,"DISCUSS"))) | AC45: =IF(K45="","",IF(T45="",K45,IF(K45=T45,K45,"DISCUSS"))) | AD45: =IF(L45="","",IF(U45="",L45,IF(L45=U45,L45,"DISCUSS"))) | AE45: =IF(M45="","",IF(V45="",M45,IF(M45=V45,M45,"DISCUSS"))) | AF45: =IF(N45="","",IF(W45="",N45,IF(N45=W45,N45,"DISCUSS"))) | AG45: =IF(O45="","",IF(X45="",O45,IF(O45=X45,O45,"DISCUSS"))) | AH45: =IF(P45="","",IF(Y45="",P45,IF(P45=Y45,P45,"DISCUSS"))) | AI45: =IF(Q45="","",IF(Z45="",Q45,IF(Q45=Z45,Q45,"DISCUSS"))) | AJ45: =IF(R45="","",IF(AA45="",R45,IF(R45=AA45,R45,"DISCUSS"))) | AK45: =IFERROR(AVERAGE(AB45:AJ45),"") | AL45: =COUNT(AB45:AJ45) -> 0 | AM45: =COUNTIF(AB45:AJ45,"DISCUSS") -> 0 | AN45: =IF(AL45=0,"",IF(AM45>0,"Resolve DISCUSS",IF(AL45<Tiers!$B$6,"Unrated",IF(AK45>=Tiers!$B$4,"High",IF(AK45>=Tiers!$B$5,"Medium","Low"))))) | AO45: =IF(OR(AN45="",AN45="Unrated",AN45="Resolve DISCUSS"),"",COUNTIFS($AN$6:$AN$105,AN45,$AK$6:$AK$105,">"&AK45)+1)
... AB105: =IF(J105="","",IF(S105="",J105,IF(J105=S105,J105,"DISCUSS"))) | AC105: =IF(K105="","",IF(T105="",K105,IF(K105=T105,K105,"DISCUSS"))) | AD105: =IF(L105="","",IF(U105="",L105,IF(L105=U105,L105,"DISCUSS"))) | AE105: =IF(M105="","",IF(V105="",M105,IF(M105=V105,M105,"DISCUSS"))) | AF105: =IF(N105="","",IF(W105="",N105,IF(N105=W105,N105,"DISCUSS"))) | AG105: =IF(O105="","",IF(X105="",O105,IF(O105=X105,O105,"DISCUSS"))) | AH105: =IF(P105="","",IF(Y105="",P105,IF(P105=Y105,P105,"DISCUSS"))) | AI105: =IF(Q105="","",IF(Z105="",Q105,IF(Q105=Z105,Q105,"DISCUSS"))) | AJ105: =IF(R105="","",IF(AA105="",R105,IF(R105=AA105,R105,"DISCUSS"))) | AK105: =IFERROR(AVERAGE(AB105:AJ105),"") | AL105: =COUNT(AB105:AJ105) -> 0 | AM105: =COUNTIF(AB105:AJ105,"DISCUSS") -> 0 | AN105: =IF(AL105=0,"",IF(AM105>0,"Resolve DISCUSS",IF(AL105<Tiers!$B$6,"Unrated",IF(AK105>=Tiers!$B$4,"High",IF(AK105>=Tiers!$B$5,"Medium","Low"))))) | AO105: =IF(OR(AN105="",AN105="Unrated",AN105="Resolve DISCUSS"),"",COUNTIFS($AN$6:$AN$105,AN105,$AK$6:$AK$105,">"&AK105)+1)

Sheet Scoring_Reviews
A1: Scoring sheet for reviews, roadmaps and company/market pages (separate rubric: Rubric_Anchors rows 22+)
A2: These records make claims by citing other work, so empirical items (controls, unit of analysis, robustness) don't apply. Same 0/1/2/NA scale, two raters, same tier cut-offs (Tiers sheet). Their tier is reported separately from the empirical tiers.
A4: Paper (pre-filled) | H4: Rater 1 | L4: Rater 2 | P4: Final (auto) | T4: Summary and tier | X4: Notes
A5: Paper ID | B5: Paper | C5: Year | D5: Type | E5: Claim categories | F5: Peer-review status | G5: COI / affiliation | H5: R1 PS | I5: R1 HR | J5: R1 MP | K5: R1 CC | L5: R2 PS | M5: R2 HR | N5: R2 MP | O5: R2 CC | P5: Final PS | Q5: Final HR | R5: Final MP | S5: Final CC | T5: Final mean | U5: Items scored | V5: Items to discuss | W5: Tier (auto) | X5: Notes
A6: doi:10.3389/fsci.2023.1017235 | B6: Smirnova et al. Organoid intelligence (OI): the new frontier in biocomputing and intelligence-in-a-dish, Front Sci | C6: 2023 | D6: Review/roadmap | E6: C,L,E | F6: Peer-reviewed | G6: Academic, declared industry COI | P6: =IF(H6="","",IF(L6="",H6,IF(H6=L6,H6,"DISCUSS"))) | Q6: =IF(I6="","",IF(M6="",I6,IF(I6=M6,I6,"DISCUSS"))) | R6: =IF(J6="","",IF(N6="",J6,IF(J6=N6,J6,"DISCUSS"))) | S6: =IF(K6="","",IF(O6="",K6,IF(K6=O6,K6,"DISCUSS"))) | T6: =IFERROR(AVERAGE(P6:S6),"") | U6: =COUNT(P6:S6) -> 0 | V6: =COUNTIF(P6:S6,"DISCUSS") -> 0 | W6: =IF(U6=0,"",IF(V6>0,"Resolve DISCUSS",IF(U6<Tiers!$B$7,"Unrated",IF(T6>=Tiers!$B$4,"High",IF(T6>=Tiers!$B$5,"Medium","Low")))))
A7: pmid:42399712 | B7: Computing inspired by the brain: a journey from algorithms to organoids (Nat Comput Sci) | C7: 2026 | D7: Review/roadmap | F7: Peer-reviewed | G7: Not checked | P7: =IF(H7="","",IF(L7="",H7,IF(H7=L7,H7,"DISCUSS"))) | Q7: =IF(I7="","",IF(M7="",I7,IF(I7=M7,I7,"DISCUSS"))) | R7: =IF(J7="","",IF(N7="",J7,IF(J7=N7,J7,"DISCUSS"))) | S7: =IF(K7="","",IF(O7="",K7,IF(K7=O7,K7,"DISCUSS"))) | T7: =IFERROR(AVERAGE(P7:S7),"") | U7: =COUNT(P7:S7) -> 0 | V7: =COUNTIF(P7:S7,"DISCUSS") -> 0 | W7: =IF(U7=0,"",IF(V7>0,"Resolve DISCUSS",IF(U7<Tiers!$B$7,"Unrated",IF(T7>=Tiers!$B$4,"High",IF(T7>=Tiers!$B$5,"Medium","Low")))))
A8: arxiv:2503.19770 | B8: Brain Organoid Computing: an Overview | C8: 2025 | D8: Review/roadmap | F8: Preprint | G8: Not checked | P8: =IF(H8="","",IF(L8="",H8,IF(H8=L8,H8,"DISCUSS"))) | Q8: =IF(I8="","",IF(M8="",I8,IF(I8=M8,I8,"DISCUSS"))) | R8: =IF(J8="","",IF(N8="",J8,IF(J8=N8,J8,"DISCUSS"))) | S8: =IF(K8="","",IF(O8="",K8,IF(K8=O8,K8,"DISCUSS"))) | T8: =IFERROR(AVERAGE(P8:S8),"") | U8: =COUNT(P8:S8) -> 0 | V8: =COUNTIF(P8:S8,"DISCUSS") -> 0 | W8: =IF(U8=0,"",IF(V8>0,"Resolve DISCUSS",IF(U8<Tiers!$B$7,"Unrated",IF(T8>=Tiers!$B$4,"High",IF(T8>=Tiers!$B$5,"Medium","Low")))))
A9: pmcid:PMC10013972 | B9: First Organoid Intelligence (OI) workshop to form an OI community | C9: 2023 | D9: Review/roadmap | F9: Peer-reviewed | G9: Not checked | P9: =IF(H9="","",IF(L9="",H9,IF(H9=L9,H9,"DISCUSS"))) | Q9: =IF(I9="","",IF(M9="",I9,IF(I9=M9,I9,"DISCUSS"))) | R9: =IF(J9="","",IF(N9="",J9,IF(J9=N9,J9,"DISCUSS"))) | S9: =IF(K9="","",IF(O9="",K9,IF(K9=O9,K9,"DISCUSS"))) | T9: =IFERROR(AVERAGE(P9:S9),"") | U9: =COUNT(P9:S9) -> 0 | V9: =COUNTIF(P9:S9,"DISCUSS") -> 0 | W9: =IF(U9=0,"",IF(V9>0,"Resolve DISCUSS",IF(U9<Tiers!$B$7,"Unrated",IF(T9>=Tiers!$B$4,"High",IF(T9>=Tiers!$B$5,"Medium","Low")))))
A10: pmid:37009773 | B10: Organoid intelligence (OI): the ultimate functionality of a brain microphysiological system (ALTEX) | C10: 2023 | D10: Review/roadmap | F10: Peer-reviewed | G10: Not checked | P10: =IF(H10="","",IF(L10="",H10,IF(H10=L10,H10,"DISCUSS"))) | Q10: =IF(I10="","",IF(M10="",I10,IF(I10=M10,I10,"DISCUSS"))) | R10: =IF(J10="","",IF(N10="",J10,IF(J10=N10,J10,"DISCUSS"))) | S10: =IF(K10="","",IF(O10="",K10,IF(K10=O10,K10,"DISCUSS"))) | T10: =IFERROR(AVERAGE(P10:S10),"") | U10: =COUNT(P10:S10) -> 0 | V10: =COUNTIF(P10:S10,"DISCUSS") -> 0 | W10: =IF(U10=0,"",IF(V10>0,"Resolve DISCUSS",IF(U10<Tiers!$B$7,"Unrated",IF(T10>=Tiers!$B$4,"High",IF(T10>=Tiers!$B$5,"Medium","Low")))))
A11: pmcid:PMC11027187 | B11: Organoid intelligence: integration of organoid technology and AI in the new era of in vitro models | C11: 2024 | D11: Review/roadmap | F11: Peer-reviewed | G11: Not checked | P11: =IF(H11="","",IF(L11="",H11,IF(H11=L11,H11,"DISCUSS"))) | Q11: =IF(I11="","",IF(M11="",I11,IF(I11=M11,I11,"DISCUSS"))) | R11: =IF(J11="","",IF(N11="",J11,IF(J11=N11,J11,"DISCUSS"))) | S11: =IF(K11="","",IF(O11="",K11,IF(K11=O11,K11,"DISCUSS"))) | T11: =IFERROR(AVERAGE(P11:S11),"") | U11: =COUNT(P11:S11) -> 0 | V11: =COUNTIF(P11:S11,"DISCUSS") -> 0 | W11: =IF(U11=0,"",IF(V11>0,"Resolve DISCUSS",IF(U11<Tiers!$B$7,"Unrated",IF(T11>=Tiers!$B$4,"High",IF(T11>=Tiers!$B$5,"Medium","Low")))))
A12: arxiv:2501.18772 | B12: Dissociated neuronal cultures as model systems for self-organized prediction | C12: 2025 | D12: Review/roadmap | F12: Preprint | G12: Not checked | P12: =IF(H12="","",IF(L12="",H12,IF(H12=L12,H12,"DISCUSS"))) | Q12: =IF(I12="","",IF(M12="",I12,IF(I12=M12,I12,"DISCUSS"))) | R12: =IF(J12="","",IF(N12="",J12,IF(J12=N12,J12,"DISCUSS"))) | S12: =IF(K12="","",IF(O12="",K12,IF(K12=O12,K12,"DISCUSS"))) | T12: =IFERROR(AVERAGE(P12:S12),"") | U12: =COUNT(P12:S12) -> 0 | V12: =COUNTIF(P12:S12,"DISCUSS") -> 0 | W12: =IF(U12=0,"",IF(V12>0,"Resolve DISCUSS",IF(U12<Tiers!$B$7,"Unrated",IF(T12>=Tiers!$B$4,"High",IF(T12>=Tiers!$B$5,"Medium","Low")))))
A13: pmcid:PMC12632695 | B13: A computational perspective on NeuroAI and synthetic biological intelligence | C13: 2025 | D13: Review/roadmap | F13: Peer-reviewed | G13: Not checked | P13: =IF(H13="","",IF(L13="",H13,IF(H13=L13,H13,"DISCUSS"))) | Q13: =IF(I13="","",IF(M13="",I13,IF(I13=M13,I13,"DISCUSS"))) | R13: =IF(J13="","",IF(N13="",J13,IF(J13=N13,J13,"DISCUSS"))) | S13: =IF(K13="","",IF(O13="",K13,IF(K13=O13,K13,"DISCUSS"))) | T13: =IFERROR(AVERAGE(P13:S13),"") | U13: =COUNT(P13:S13) -> 0 | V13: =COUNTIF(P13:S13,"DISCUSS") -> 0 | W13: =IF(U13=0,"",IF(V13>0,"Resolve DISCUSS",IF(U13<Tiers!$B$7,"Unrated",IF(T13>=Tiers!$B$4,"High",IF(T13>=Tiers!$B$5,"Medium","Low")))))
A14: arxiv:2604.27933 | B14: Synthetic biological intelligence: system-level abstractions and adaptive bio-digital interaction | C14: 2026 | D14: Review/roadmap | F14: Preprint | G14: Not checked | P14: =IF(H14="","",IF(L14="",H14,IF(H14=L14,H14,"DISCUSS"))) | Q14: =IF(I14="","",IF(M14="",I14,IF(I14=M14,I14,"DISCUSS"))) | R14: =IF(J14="","",IF(N14="",J14,IF(J14=N14,J14,"DISCUSS"))) | S14: =IF(K14="","",IF(O14="",K14,IF(K14=O14,K14,"DISCUSS"))) | T14: =IFERROR(AVERAGE(P14:S14),"") | U14: =COUNT(P14:S14) -> 0 | V14: =COUNTIF(P14:S14,"DISCUSS") -> 0 | W14: =IF(U14=0,"",IF(V14>0,"Resolve DISCUSS",IF(U14<Tiers!$B$7,"Unrated",IF(T14>=Tiers!$B$4,"High",IF(T14>=Tiers!$B$5,"Medium","Low")))))
A15: pmcid:PMC7615149 | B15: The technology, opportunities, and challenges of synthetic biological intelligence (Biotechnol Adv) | C15: 2023 | D15: Review/roadmap | F15: Peer-reviewed | G15: Not checked | P15: =IF(H15="","",IF(L15="",H15,IF(H15=L15,H15,"DISCUSS"))) | Q15: =IF(I15="","",IF(M15="",I15,IF(I15=M15,I15,"DISCUSS"))) | R15: =IF(J15="","",IF(N15="",J15,IF(J15=N15,J15,"DISCUSS"))) | S15: =IF(K15="","",IF(O15="",K15,IF(K15=O15,K15,"DISCUSS"))) | T15: =IFERROR(AVERAGE(P15:S15),"") | U15: =COUNT(P15:S15) -> 0 | V15: =COUNTIF(P15:S15,"DISCUSS") -> 0 | W15: =IF(U15=0,"",IF(V15>0,"Resolve DISCUSS",IF(U15<Tiers!$B$7,"Unrated",IF(T15>=Tiers!$B$4,"High",IF(T15>=Tiers!$B$5,"Medium","Low")))))
A16: https://corticallabs.com/cl1.html | B16: Cortical Labs: CL1 biological computer product page | D16: Grey literature | E16: E | F16: Company/market page | G16: Company / industry source | P16: =IF(H16="","",IF(L16="",H16,IF(H16=L16,H16,"DISCUSS"))) | Q16: =IF(I16="","",IF(M16="",I16,IF(I16=M16,I16,"DISCUSS"))) | R16: =IF(J16="","",IF(N16="",J16,IF(J16=N16,J16,"DISCUSS"))) | S16: =IF(K16="","",IF(O16="",K16,IF(K16=O16,K16,"DISCUSS"))) | T16: =IFERROR(AVERAGE(P16:S16),"") | U16: =COUNT(P16:S16) -> 0 | V16: =COUNTIF(P16:S16,"DISCUSS") -> 0 | W16: =IF(U16=0,"",IF(V16>0,"Resolve DISCUSS",IF(U16<Tiers!$B$7,"Unrated",IF(T16>=Tiers!$B$4,"High",IF(T16>=Tiers!$B$5,"Medium","Low")))))
A17: https://finalspark.com/ | B17: FinalSpark homepage (bioprocessor, energy claims) | D17: Grey literature | E17: E | F17: Company/market page | G17: Company / industry source | P17: =IF(H17="","",IF(L17="",H17,IF(H17=L17,H17,"DISCUSS"))) | Q17: =IF(I17="","",IF(M17="",I17,IF(I17=M17,I17,"DISCUSS"))) | R17: =IF(J17="","",IF(N17="",J17,IF(J17=N17,J17,"DISCUSS"))) | S17: =IF(K17="","",IF(O17="",K17,IF(K17=O17,K17,"DISCUSS"))) | T17: =IFERROR(AVERAGE(P17:S17),"") | U17: =COUNT(P17:S17) -> 0 | V17: =COUNTIF(P17:S17,"DISCUSS") -> 0 | W17: =IF(U17=0,"",IF(V17>0,"Resolve DISCUSS",IF(U17<Tiers!$B$7,"Unrated",IF(T17>=Tiers!$B$4,"High",IF(T17>=Tiers!$B$5,"Medium","Low")))))
A18: manual:insightace-organoid-biocomputer-market | B18: InsightAce Analytic: Biocomputer Based on Organoids Market Size and Scope Analysis (market report) | D18: Grey literature | E18: E | F18: Company/market page | G18: Company / industry source | P18: =IF(H18="","",IF(L18="",H18,IF(H18=L18,H18,"DISCUSS"))) | Q18: =IF(I18="","",IF(M18="",I18,IF(I18=M18,I18,"DISCUSS"))) | R18: =IF(J18="","",IF(N18="",J18,IF(J18=N18,J18,"DISCUSS"))) | S18: =IF(K18="","",IF(O18="",K18,IF(K18=O18,K18,"DISCUSS"))) | T18: =IFERROR(AVERAGE(P18:S18),"") | U18: =COUNT(P18:S18) -> 0 | V18: =COUNTIF(P18:S18,"DISCUSS") -> 0 | W18: =IF(U18=0,"",IF(V18>0,"Resolve DISCUSS",IF(U18<Tiers!$B$7,"Unrated",IF(T18>=Tiers!$B$4,"High",IF(T18>=Tiers!$B$5,"Medium","Low")))))
P19: =IF(H19="","",IF(L19="",H19,IF(H19=L19,H19,"DISCUSS"))) | Q19: =IF(I19="","",IF(M19="",I19,IF(I19=M19,I19,"DISCUSS"))) | R19: =IF(J19="","",IF(N19="",J19,IF(J19=N19,J19,"DISCUSS"))) | S19: =IF(K19="","",IF(O19="",K19,IF(K19=O19,K19,"DISCUSS"))) | T19: =IFERROR(AVERAGE(P19:S19),"") | U19: =COUNT(P19:S19) -> 0 | V19: =COUNTIF(P19:S19,"DISCUSS") -> 0 | W19: =IF(U19=0,"",IF(V19>0,"Resolve DISCUSS",IF(U19<Tiers!$B$7,"Unrated",IF(T19>=Tiers!$B$4,"High",IF(T19>=Tiers!$B$5,"Medium","Low")))))
P20: =IF(H20="","",IF(L20="",H20,IF(H20=L20,H20,"DISCUSS"))) | Q20: =IF(I20="","",IF(M20="",I20,IF(I20=M20,I20,"DISCUSS"))) | R20: =IF(J20="","",IF(N20="",J20,IF(J20=N20,J20,"DISCUSS"))) | S20: =IF(K20="","",IF(O20="",K20,IF(K20=O20,K20,"DISCUSS"))) | T20: =IFERROR(AVERAGE(P20:S20),"") | U20: =COUNT(P20:S20) -> 0 | V20: =COUNTIF(P20:S20,"DISCUSS") -> 0 | W20: =IF(U20=0,"",IF(V20>0,"Resolve DISCUSS",IF(U20<Tiers!$B$7,"Unrated",IF(T20>=Tiers!$B$4,"High",IF(T20>=Tiers!$B$5,"Medium","Low")))))
P21: =IF(H21="","",IF(L21="",H21,IF(H21=L21,H21,"DISCUSS"))) | Q21: =IF(I21="","",IF(M21="",I21,IF(I21=M21,I21,"DISCUSS"))) | R21: =IF(J21="","",IF(N21="",J21,IF(J21=N21,J21,"DISCUSS"))) | S21: =IF(K21="","",IF(O21="",K21,IF(K21=O21,K21,"DISCUSS"))) | T21: =IFERROR(AVERAGE(P21:S21),"") | U21: =COUNT(P21:S21) -> 0 | V21: =COUNTIF(P21:S21,"DISCUSS") -> 0 | W21: =IF(U21=0,"",IF(V21>0,"Resolve DISCUSS",IF(U21<Tiers!$B$7,"Unrated",IF(T21>=Tiers!$B$4,"High",IF(T21>=Tiers!$B$5,"Medium","Low")))))
P22: =IF(H22="","",IF(L22="",H22,IF(H22=L22,H22,"DISCUSS"))) | Q22: =IF(I22="","",IF(M22="",I22,IF(I22=M22,I22,"DISCUSS"))) | R22: =IF(J22="","",IF(N22="",J22,IF(J22=N22,J22,"DISCUSS"))) | S22: =IF(K22="","",IF(O22="",K22,IF(K22=O22,K22,"DISCUSS"))) | T22: =IFERROR(AVERAGE(P22:S22),"") | U22: =COUNT(P22:S22) -> 0 | V22: =COUNTIF(P22:S22,"DISCUSS") -> 0 | W22: =IF(U22=0,"",IF(V22>0,"Resolve DISCUSS",IF(U22<Tiers!$B$7,"Unrated",IF(T22>=Tiers!$B$4,"High",IF(T22>=Tiers!$B$5,"Medium","Low")))))
P23: =IF(H23="","",IF(L23="",H23,IF(H23=L23,H23,"DISCUSS"))) | Q23: =IF(I23="","",IF(M23="",I23,IF(I23=M23,I23,"DISCUSS"))) | R23: =IF(J23="","",IF(N23="",J23,IF(J23=N23,J23,"DISCUSS"))) | S23: =IF(K23="","",IF(O23="",K23,IF(K23=O23,K23,"DISCUSS"))) | T23: =IFERROR(AVERAGE(P23:S23),"") | U23: =COUNT(P23:S23) -> 0 | V23: =COUNTIF(P23:S23,"DISCUSS") -> 0 | W23: =IF(U23=0,"",IF(V23>0,"Resolve DISCUSS",IF(U23<Tiers!$B$7,"Unrated",IF(T23>=Tiers!$B$4,"High",IF(T23>=Tiers!$B$5,"Medium","Low")))))
P24: =IF(H24="","",IF(L24="",H24,IF(H24=L24,H24,"DISCUSS"))) | Q24: =IF(I24="","",IF(M24="",I24,IF(I24=M24,I24,"DISCUSS"))) | R24: =IF(J24="","",IF(N24="",J24,IF(J24=N24,J24,"DISCUSS"))) | S24: =IF(K24="","",IF(O24="",K24,IF(K24=O24,K24,"DISCUSS"))) | T24: =IFERROR(AVERAGE(P24:S24),"") | U24: =COUNT(P24:S24) -> 0 | V24: =COUNTIF(P24:S24,"DISCUSS") -> 0 | W24: =IF(U24=0,"",IF(V24>0,"Resolve DISCUSS",IF(U24<Tiers!$B$7,"Unrated",IF(T24>=Tiers!$B$4,"High",IF(T24>=Tiers!$B$5,"Medium","Low")))))
P25: =IF(H25="","",IF(L25="",H25,IF(H25=L25,H25,"DISCUSS"))) | Q25: =IF(I25="","",IF(M25="",I25,IF(I25=M25,I25,"DISCUSS"))) | R25: =IF(J25="","",IF(N25="",J25,IF(J25=N25,J25,"DISCUSS"))) | S25: =IF(K25="","",IF(O25="",K25,IF(K25=O25,K25,"DISCUSS"))) | T25: =IFERROR(AVERAGE(P25:S25),"") | U25: =COUNT(P25:S25) -> 0 | V25: =COUNTIF(P25:S25,"DISCUSS") -> 0 | W25: =IF(U25=0,"",IF(V25>0,"Resolve DISCUSS",IF(U25<Tiers!$B$7,"Unrated",IF(T25>=Tiers!$B$4,"High",IF(T25>=Tiers!$B$5,"Medium","Low")))))
P26: =IF(H26="","",IF(L26="",H26,IF(H26=L26,H26,"DISCUSS"))) | Q26: =IF(I26="","",IF(M26="",I26,IF(I26=M26,I26,"DISCUSS"))) | R26: =IF(J26="","",IF(N26="",J26,IF(J26=N26,J26,"DISCUSS"))) | S26: =IF(K26="","",IF(O26="",K26,IF(K26=O26,K26,"DISCUSS"))) | T26: =IFERROR(AVERAGE(P26:S26),"") | U26: =COUNT(P26:S26) -> 0 | V26: =COUNTIF(P26:S26,"DISCUSS") -> 0 | W26: =IF(U26=0,"",IF(V26>0,"Resolve DISCUSS",IF(U26<Tiers!$B$7,"Unrated",IF(T26>=Tiers!$B$4,"High",IF(T26>=Tiers!$B$5,"Medium","Low")))))
P27: =IF(H27="","",IF(L27="",H27,IF(H27=L27,H27,"DISCUSS"))) | Q27: =IF(I27="","",IF(M27="",I27,IF(I27=M27,I27,"DISCUSS"))) | R27: =IF(J27="","",IF(N27="",J27,IF(J27=N27,J27,"DISCUSS"))) | S27: =IF(K27="","",IF(O27="",K27,IF(K27=O27,K27,"DISCUSS"))) | T27: =IFERROR(AVERAGE(P27:S27),"") | U27: =COUNT(P27:S27) -> 0 | V27: =COUNTIF(P27:S27,"DISCUSS") -> 0 | W27: =IF(U27=0,"",IF(V27>0,"Resolve DISCUSS",IF(U27<Tiers!$B$7,"Unrated",IF(T27>=Tiers!$B$4,"High",IF(T27>=Tiers!$B$5,"Medium","Low")))))
P28: =IF(H28="","",IF(L28="",H28,IF(H28=L28,H28,"DISCUSS"))) | Q28: =IF(I28="","",IF(M28="",I28,IF(I28=M28,I28,"DISCUSS"))) | R28: =IF(J28="","",IF(N28="",J28,IF(J28=N28,J28,"DISCUSS"))) | S28: =IF(K28="","",IF(O28="",K28,IF(K28=O28,K28,"DISCUSS"))) | T28: =IFERROR(AVERAGE(P28:S28),"") | U28: =COUNT(P28:S28) -> 0 | V28: =COUNTIF(P28:S28,"DISCUSS") -> 0 | W28: =IF(U28=0,"",IF(V28>0,"Resolve DISCUSS",IF(U28<Tiers!$B$7,"Unrated",IF(T28>=Tiers!$B$4,"High",IF(T28>=Tiers!$B$5,"Medium","Low")))))
P29: =IF(H29="","",IF(L29="",H29,IF(H29=L29,H29,"DISCUSS"))) | Q29: =IF(I29="","",IF(M29="",I29,IF(I29=M29,I29,"DISCUSS"))) | R29: =IF(J29="","",IF(N29="",J29,IF(J29=N29,J29,"DISCUSS"))) | S29: =IF(K29="","",IF(O29="",K29,IF(K29=O29,K29,"DISCUSS"))) | T29: =IFERROR(AVERAGE(P29:S29),"") | U29: =COUNT(P29:S29) -> 0 | V29: =COUNTIF(P29:S29,"DISCUSS") -> 0 | W29: =IF(U29=0,"",IF(V29>0,"Resolve DISCUSS",IF(U29<Tiers!$B$7,"Unrated",IF(T29>=Tiers!$B$4,"High",IF(T29>=Tiers!$B$5,"Medium","Low")))))
P30: =IF(H30="","",IF(L30="",H30,IF(H30=L30,H30,"DISCUSS"))) | Q30: =IF(I30="","",IF(M30="",I30,IF(I30=M30,I30,"DISCUSS"))) | R30: =IF(J30="","",IF(N30="",J30,IF(J30=N30,J30,"DISCUSS"))) | S30: =IF(K30="","",IF(O30="",K30,IF(K30=O30,K30,"DISCUSS"))) | T30: =IFERROR(AVERAGE(P30:S30),"") | U30: =COUNT(P30:S30) -> 0 | V30: =COUNTIF(P30:S30,"DISCUSS") -> 0 | W30: =IF(U30=0,"",IF(V30>0,"Resolve DISCUSS",IF(U30<Tiers!$B$7,"Unrated",IF(T30>=Tiers!$B$4,"High",IF(T30>=Tiers!$B$5,"Medium","Low")))))
... P55: =IF(H55="","",IF(L55="",H55,IF(H55=L55,H55,"DISCUSS"))) | Q55: =IF(I55="","",IF(M55="",I55,IF(I55=M55,I55,"DISCUSS"))) | R55: =IF(J55="","",IF(N55="",J55,IF(J55=N55,J55,"DISCUSS"))) | S55: =IF(K55="","",IF(O55="",K55,IF(K55=O55,K55,"DISCUSS"))) | T55: =IFERROR(AVERAGE(P55:S55),"") | U55: =COUNT(P55:S55) -> 0 | V55: =COUNTIF(P55:S55,"DISCUSS") -> 0 | W55: =IF(U55=0,"",IF(V55>0,"Resolve DISCUSS",IF(U55<Tiers!$B$7,"Unrated",IF(T55>=Tiers!$B$4,"High",IF(T55>=Tiers!$B$5,"Medium","Low")))))

Sheet Rubric_Anchors
A1: Rubric v1 (draft for team review): scoring anchors
A2: Report each paper as a profile across items, not as one total. Use NA when an item does not apply; NA is excluded from averages. This table is for empirical papers; reviews, roadmaps and company pages use the Review rubric below.
A4: Code | B4: Item | C4: What it asks | D4: 2 | E4: 1 | F4: 0 | G4: Use NA when | H4: Where to look
A5: SM | B5: System match | C5: Does the claim concern the system that was actually tested? | D5: Claim is about the substrate tested (organoid claims from organoid data) | E5: Mixed or 2D/organoid gap exists and the paper acknowledges it | F5: Claim extrapolated beyond the system tested with no acknowledgment (e.g., 2D culture result presented as organoid or brain evidence) | G5: Never for empirical papers. For reviews, score the evidence they cite for their headline claims | H5: Abstract vs Methods; cell source and culture type
A6: UA | B6: Unit of analysis | C6: Are statistics done at the level of independent biological units? | D6: Stats at culture/organoid level, or a model that accounts for repeated sessions | E6: n reported but independence unclear | F6: n missing, or repeated sessions/recordings treated as independent samples | G6: No quantitative result or statistics reported (reviews, grey literature) | H6: Figure legends, Methods statistics, supplementary tables
A7: CT | B7: Controls | C7: Could the result arise from artifact rather than neural activity or learning? | D7: Two or more appropriate negative controls (e.g., no-cell, inactive cells, no stimulation, no feedback) | E7: One control | F7: No controls | G7: Reviews and grey literature | H7: Results, control figures, supplementary figures
A8: CF | B8: Comparator fairness | C8: If compared with AI/silicon, is the comparison like-for-like? | D8: Same task and metric, matched inputs and budget, baseline tuned or tuning documented, no cap that favors one side | E8: Partial matching, limitations stated | F8: Comparator unmatched, untuned, or unspecified | G8: No comparison to AI or silicon is made | H8: Methods (baselines, input encoding, hyperparameters), comparison figures
A9: EA | B9: Energy accounting | C9: If an energy-efficiency claim is made, was energy measured for the full system? | D9: Measured full-system energy including life support (incubation, pumps, cooling), against a stated comparator | E9: Partial measurement (e.g., electrode or neuron level only) | F9: Energy appears only as motivation or as brain-level figures | G9: No energy claim. Sample- or data-efficiency claims are scored under CF, not here | H9: Introduction, Discussion, any power or energy table
A10: RB | B10: Robustness | C10: Does the result hold across days, batches, lines, or labs? | D10: Shown across days/batches/lines (or replicated within the paper) | E10: Single condition, limitation honestly stated | F10: Not examined, or contradicted by the paper's own data | G10: Reviews and grey literature | H10: Results across sessions, supplementary replicates, Limitations
A11: TR | B11: Transparency | C11: Could another lab reproduce the work? | D11: Methods sufficient (organoid/culture protocol, stimulation and recording parameters) and data or code available | E11: Methods sufficient but no data/code, or data on request only | F11: Insufficient methods and no data/code | G11: Grey literature (score as 0 if no methods given) | H11: Methods, data availability statement, repositories
A12: CC | B12: Claim calibration | C12: Do title, abstract, and headline claims match the evidence and the paper's own limitations? | D12: Headline claims match results and limitations | E12: Mild overreach (stronger wording in title/abstract than in results) | F12: Headline contradicted by the paper's own hedges or limitations | G12: Never | H12: Title, abstract vs Results and Limitations
A13: RP | B13: Replication | C13: Has the result been reproduced by anyone other than the original team? | D13: Independently reproduced by a lab with no author overlap (or an independent reanalysis of shared data reaches the same result) | E13: Repeated only by the same group or company, or in a follow-up by overlapping authors | F13: No replication attempt known | G13: Never. Expect mostly 0 in this field; the point is to see where the exceptions are | H13: Citing papers (Google Scholar 'cited by'), follow-up preprints, replication notes
A15: Descriptors (recorded, not scored)
A16: COI / affiliation | C16: Company / industry source; Mixed academic-industry authors; Academic, declared industry COI; Academic, none declared; Not checked. Record from the affiliations and competing-interest statement. A COI is not a rigor flaw by itself; the Analysis sheet tests whether it tracks the scores.
A17: Peer-review status | C17: Pre-filled from the identifier (preprint servers vs journals). Some preprints have since been published, so verify.
A18: Hypothesis stated up front | C18: Yes if the paper states the predicted result before the methods/results (e.g., Khajehnejad anticipates greater sample efficiency).
A22: Review rubric: reviews, roadmaps and company/market pages (scored on Scoring_Reviews)
A23: Code | B23: Item | C23: What it asks | D23: 2 | E23: 1 | F23: 0 | G23: Use NA when | H23: Where to look
A24: PS | B24: Primary sourcing | C24: Do the headline numbers trace to primary measurements? | D24: Each headline number is cited to the primary study that measured it | E24: Some traced, some cited second-hand or to other reviews | F24: Key numbers uncited, or only cited to reviews or press | G24: Never | H24: Reference list vs the numbers in the abstract and text
A25: HR | B25: Hedge retention | C25: Does it carry forward the original authors' caveats? | D25: Caveats preserved (e.g., 2D not organoid, whole-brain not organoid, capped comparison) | E25: Some caveats dropped | F25: Caveated results stated as established | G25: Never | H25: Compare each cited claim with its source paper's Limitations
A26: MP | B26: Measured vs projected | C26: Does it separate what was measured from what is projected or hoped for? | D26: Labels measured, projected and aspirational claims clearly | E26: Partly separated | F26: Blends them (e.g., brain-level efficiency presented as organoid-level) | G26: Never | H26: Efficiency, capacity and 'potential' statements
A27: CC | B27: Claim calibration | C27: Do title, abstract and headline match the evidence it presents? | D27: Headline matches the evidence and the stated limits | E27: Mild overreach | F27: Headline contradicted by its own hedges or by the evidence it cites | G27: Never | H27: Title and abstract vs body

Sheet Tiers
A1: Tiers: sort papers into High / Medium / Low, compare within tiers, extract findings, find the determining factor
A2: Step 1 sorts each paper by its mean Final score. Step 2 ranks papers against each other inside a tier (Scoring column 'Rank within tier'). Step 3 summarizes what each tier shows. Step 4 asks which rubric item separates the tiers.
A3: 1. Tier cut-offs (team input; fix them BEFORE scoring and record the date in Protocol)
A4: High tier: mean Final score at least | B4: 1.5 | C4: Out of 2. Papers at or above this are High.
A5: Medium tier: mean Final score at least | B5: 1 | C5: Below this is Low.
A6: Minimum items scored (empirical papers) | B6: 6 | C6: Out of 9. Fewer scored items = Unrated, so NA-heavy papers aren't tiered on thin evidence.
A7: Minimum items scored (reviews / company pages) | B7: 3 | C7: Out of 4.
A8: A paper shows 'Resolve DISCUSS' instead of a tier until every rater disagreement is settled.
A10: 2. Papers per tier
A11: Tier | B11: Empirical papers | C11: Reviews / company pages
A12: High | B12: =COUNTIF(Scoring!$AN$6:$AN$105,$A12) -> 0 | C12: =COUNTIF(Scoring_Reviews!$W$6:$W$55,$A12) -> 0
A13: Medium | B13: =COUNTIF(Scoring!$AN$6:$AN$105,$A13) -> 0 | C13: =COUNTIF(Scoring_Reviews!$W$6:$W$55,$A13) -> 0
A14: Low | B14: =COUNTIF(Scoring!$AN$6:$AN$105,$A14) -> 0 | C14: =COUNTIF(Scoring_Reviews!$W$6:$W$55,$A14) -> 0
A15: Unrated | B15: =COUNTIF(Scoring!$AN$6:$AN$105,$A15) -> 0 | C15: =COUNTIF(Scoring_Reviews!$W$6:$W$55,$A15) -> 0
A16: Resolve DISCUSS | B16: =COUNTIF(Scoring!$AN$6:$AN$105,$A16) -> 0 | C16: =COUNTIF(Scoring_Reviews!$W$6:$W$55,$A16) -> 0
A19: 3. Mean Final score per item within each tier (empirical papers)
A20: Tier | B20: Papers | C20: SM | D20: UA | E20: CT | F20: CF | G20: EA | H20: RB | I20: TR | J20: CC | K20: RP
A21: High | B21: =COUNTIF(Scoring!$AN$6:$AN$105,$A21) -> 0 | C21: =IFERROR(AVERAGEIFS(Scoring!$AB$6:$AB$105,Scoring!$AN$6:$AN$105,$A21),"") | D21: =IFERROR(AVERAGEIFS(Scoring!$AC$6:$AC$105,Scoring!$AN$6:$AN$105,$A21),"") | E21: =IFERROR(AVERAGEIFS(Scoring!$AD$6:$AD$105,Scoring!$AN$6:$AN$105,$A21),"") | F21: =IFERROR(AVERAGEIFS(Scoring!$AE$6:$AE$105,Scoring!$AN$6:$AN$105,$A21),"") | G21: =IFERROR(AVERAGEIFS(Scoring!$AF$6:$AF$105,Scoring!$AN$6:$AN$105,$A21),"") | H21: =IFERROR(AVERAGEIFS(Scoring!$AG$6:$AG$105,Scoring!$AN$6:$AN$105,$A21),"") | I21: =IFERROR(AVERAGEIFS(Scoring!$AH$6:$AH$105,Scoring!$AN$6:$AN$105,$A21),"") | J21: =IFERROR(AVERAGEIFS(Scoring!$AI$6:$AI$105,Scoring!$AN$6:$AN$105,$A21),"") | K21: =IFERROR(AVERAGEIFS(Scoring!$AJ$6:$AJ$105,Scoring!$AN$6:$AN$105,$A21),"")
A22: Medium | B22: =COUNTIF(Scoring!$AN$6:$AN$105,$A22) -> 0 | C22: =IFERROR(AVERAGEIFS(Scoring!$AB$6:$AB$105,Scoring!$AN$6:$AN$105,$A22),"") | D22: =IFERROR(AVERAGEIFS(Scoring!$AC$6:$AC$105,Scoring!$AN$6:$AN$105,$A22),"") | E22: =IFERROR(AVERAGEIFS(Scoring!$AD$6:$AD$105,Scoring!$AN$6:$AN$105,$A22),"") | F22: =IFERROR(AVERAGEIFS(Scoring!$AE$6:$AE$105,Scoring!$AN$6:$AN$105,$A22),"") | G22: =IFERROR(AVERAGEIFS(Scoring!$AF$6:$AF$105,Scoring!$AN$6:$AN$105,$A22),"") | H22: =IFERROR(AVERAGEIFS(Scoring!$AG$6:$AG$105,Scoring!$AN$6:$AN$105,$A22),"") | I22: =IFERROR(AVERAGEIFS(Scoring!$AH$6:$AH$105,Scoring!$AN$6:$AN$105,$A22),"") | J22: =IFERROR(AVERAGEIFS(Scoring!$AI$6:$AI$105,Scoring!$AN$6:$AN$105,$A22),"") | K22: =IFERROR(AVERAGEIFS(Scoring!$AJ$6:$AJ$105,Scoring!$AN$6:$AN$105,$A22),"")
A23: Low | B23: =COUNTIF(Scoring!$AN$6:$AN$105,$A23) -> 0 | C23: =IFERROR(AVERAGEIFS(Scoring!$AB$6:$AB$105,Scoring!$AN$6:$AN$105,$A23),"") | D23: =IFERROR(AVERAGEIFS(Scoring!$AC$6:$AC$105,Scoring!$AN$6:$AN$105,$A23),"") | E23: =IFERROR(AVERAGEIFS(Scoring!$AD$6:$AD$105,Scoring!$AN$6:$AN$105,$A23),"") | F23: =IFERROR(AVERAGEIFS(Scoring!$AE$6:$AE$105,Scoring!$AN$6:$AN$105,$A23),"") | G23: =IFERROR(AVERAGEIFS(Scoring!$AF$6:$AF$105,Scoring!$AN$6:$AN$105,$A23),"") | H23: =IFERROR(AVERAGEIFS(Scoring!$AG$6:$AG$105,Scoring!$AN$6:$AN$105,$A23),"") | I23: =IFERROR(AVERAGEIFS(Scoring!$AH$6:$AH$105,Scoring!$AN$6:$AN$105,$A23),"") | J23: =IFERROR(AVERAGEIFS(Scoring!$AI$6:$AI$105,Scoring!$AN$6:$AN$105,$A23),"") | K23: =IFERROR(AVERAGEIFS(Scoring!$AJ$6:$AJ$105,Scoring!$AN$6:$AN$105,$A23),"")
A24: Gap: High minus Low | C24: =IFERROR(C21-C23,"") | D24: =IFERROR(D21-D23,"") | E24: =IFERROR(E21-E23,"") | F24: =IFERROR(F21-F23,"") | G24: =IFERROR(G21-G23,"") | H24: =IFERROR(H21-H23,"") | I24: =IFERROR(I21-I23,"") | J24: =IFERROR(J21-J23,"") | K24: =IFERROR(K21-K23,"")
A25: Gap rank (1 = biggest gap) | C25: =IF(C24="","",RANK(C24,$C$24:$K$24)) | D25: =IF(D24="","",RANK(D24,$C$24:$K$24)) | E25: =IF(E24="","",RANK(E24,$C$24:$K$24)) | F25: =IF(F24="","",RANK(F24,$C$24:$K$24)) | G25: =IF(G24="","",RANK(G24,$C$24:$K$24)) | H25: =IF(H24="","",RANK(H24,$C$24:$K$24)) | I25: =IF(I24="","",RANK(I24,$C$24:$K$24)) | J25: =IF(J24="","",RANK(J24,$C$24:$K$24)) | K25: =IF(K24="","",RANK(K24,$C$24:$K$24))
A26: Candidate determining factor (auto): item with the largest High-Low gap | F26: =IFERROR(INDEX($C$20:$K$20,MATCH(MAX($C$24:$K$24),$C$24:$K$24,0)),"")
A27: Read this carefully: tiers are built from the same item scores, so a gap is partly built in and says which items drive the tiers, not what causes rigor. Treat the auto factor as a lead, then check it two ways: (a) re-tier with that item left out and count how many papers change tier; (b) read the papers that sit in a different tier from what the item alone predicts. Replication will probably score 0 for nearly everyone, so its gap will be small even if it matters; look at who has any replication at all.
A29: 4. Who is in each tier (empirical papers)
A30: Group | B30: High | C30: Medium | D30: Low
A31: COI: Company / industry source | B31: =COUNTIFS(Scoring!$AN$6:$AN$105,"High",Scoring!$G$6:$G$105,"Company / industry source") -> 0 | C31: =COUNTIFS(Scoring!$AN$6:$AN$105,"Medium",Scoring!$G$6:$G$105,"Company / industry source") -> 0 | D31: =COUNTIFS(Scoring!$AN$6:$AN$105,"Low",Scoring!$G$6:$G$105,"Company / industry source") -> 0
A32: COI: Mixed academic-industry authors | B32: =COUNTIFS(Scoring!$AN$6:$AN$105,"High",Scoring!$G$6:$G$105,"Mixed academic-industry authors") -> 0 | C32: =COUNTIFS(Scoring!$AN$6:$AN$105,"Medium",Scoring!$G$6:$G$105,"Mixed academic-industry authors") -> 0 | D32: =COUNTIFS(Scoring!$AN$6:$AN$105,"Low",Scoring!$G$6:$G$105,"Mixed academic-industry authors") -> 0
A33: COI: Academic, declared industry COI | B33: =COUNTIFS(Scoring!$AN$6:$AN$105,"High",Scoring!$G$6:$G$105,"Academic, declared industry COI") -> 0 | C33: =COUNTIFS(Scoring!$AN$6:$AN$105,"Medium",Scoring!$G$6:$G$105,"Academic, declared industry COI") -> 0 | D33: =COUNTIFS(Scoring!$AN$6:$AN$105,"Low",Scoring!$G$6:$G$105,"Academic, declared industry COI") -> 0
A34: COI: Academic, none declared | B34: =COUNTIFS(Scoring!$AN$6:$AN$105,"High",Scoring!$G$6:$G$105,"Academic, none declared") -> 0 | C34: =COUNTIFS(Scoring!$AN$6:$AN$105,"Medium",Scoring!$G$6:$G$105,"Academic, none declared") -> 0 | D34: =COUNTIFS(Scoring!$AN$6:$AN$105,"Low",Scoring!$G$6:$G$105,"Academic, none declared") -> 0
A35: Peer-reviewed | B35: =COUNTIFS(Scoring!$AN$6:$AN$105,"High",Scoring!$F$6:$F$105,"Peer-reviewed") -> 0 | C35: =COUNTIFS(Scoring!$AN$6:$AN$105,"Medium",Scoring!$F$6:$F$105,"Peer-reviewed") -> 0 | D35: =COUNTIFS(Scoring!$AN$6:$AN$105,"Low",Scoring!$F$6:$F$105,"Peer-reviewed") -> 0
A36: Preprint | B36: =COUNTIFS(Scoring!$AN$6:$AN$105,"High",Scoring!$F$6:$F$105,"Preprint") -> 0 | C36: =COUNTIFS(Scoring!$AN$6:$AN$105,"Medium",Scoring!$F$6:$F$105,"Preprint") -> 0 | D36: =COUNTIFS(Scoring!$AN$6:$AN$105,"Low",Scoring!$F$6:$F$105,"Preprint") -> 0
A37: Makes a computational claim | B37: =COUNTIFS(Scoring!$AN$6:$AN$105,"High",Scoring!$E$6:$E$105,"*C*") -> 0 | C37: =COUNTIFS(Scoring!$AN$6:$AN$105,"Medium",Scoring!$E$6:$E$105,"*C*") -> 0 | D37: =COUNTIFS(Scoring!$AN$6:$AN$105,"Low",Scoring!$E$6:$E$105,"*C*") -> 0
A38: Makes a learning claim | B38: =COUNTIFS(Scoring!$AN$6:$AN$105,"High",Scoring!$E$6:$E$105,"*L*") -> 0 | C38: =COUNTIFS(Scoring!$AN$6:$AN$105,"Medium",Scoring!$E$6:$E$105,"*L*") -> 0 | D38: =COUNTIFS(Scoring!$AN$6:$AN$105,"Low",Scoring!$E$6:$E$105,"*L*") -> 0
A39: Makes an efficiency claim | B39: =COUNTIFS(Scoring!$AN$6:$AN$105,"High",Scoring!$E$6:$E$105,"*E*") -> 0 | C39: =COUNTIFS(Scoring!$AN$6:$AN$105,"Medium",Scoring!$E$6:$E$105,"*E*") -> 0 | D39: =COUNTIFS(Scoring!$AN$6:$AN$105,"Low",Scoring!$E$6:$E$105,"*E*") -> 0
A41: 5. Essential findings from each tier (team writes these after scoring; one row per tier)
A42: Tier | B42: What these papers actually show (essential findings) | C42: Shared strengths | D42: Shared weaknesses | E42: Claims that hold up | F42: Claims that do not | G42: Papers to cite as examples
A43: High
A44: Medium
A45: Low
A47: 6. Determining factor (team conclusion)
A48: Factor the team settles on
A49: Evidence (tier gaps, leave-one-out check, papers read)
A50: What would change this conclusion

Sheet Analysis
A1: Analysis (all cells are formulas on the Scoring and Claims sheets; they fill in as scores are entered)
A3: 1. Item means (Final scores)
A4: Code | B4: Item | C4: Papers scored | D4: NA | E4: Mean (0-2) | F4: % scored 2 | G4: % scored 0
A5: SM | B5: System match | C5: =COUNT(Scoring!AB$6:AB$105) -> 0 | D5: =COUNTIF(Scoring!AB$6:AB$105,"NA") -> 0 | E5: =IFERROR(AVERAGE(Scoring!AB$6:AB$105),"") | F5: =IF(C5=0,"",COUNTIF(Scoring!AB$6:AB$105,2)/C5) | G5: =IF(C5=0,"",COUNTIF(Scoring!AB$6:AB$105,0)/C5)
A6: UA | B6: Unit of analysis | C6: =COUNT(Scoring!AC$6:AC$105) -> 0 | D6: =COUNTIF(Scoring!AC$6:AC$105,"NA") -> 0 | E6: =IFERROR(AVERAGE(Scoring!AC$6:AC$105),"") | F6: =IF(C6=0,"",COUNTIF(Scoring!AC$6:AC$105,2)/C6) | G6: =IF(C6=0,"",COUNTIF(Scoring!AC$6:AC$105,0)/C6)
A7: CT | B7: Controls | C7: =COUNT(Scoring!AD$6:AD$105) -> 0 | D7: =COUNTIF(Scoring!AD$6:AD$105,"NA") -> 0 | E7: =IFERROR(AVERAGE(Scoring!AD$6:AD$105),"") | F7: =IF(C7=0,"",COUNTIF(Scoring!AD$6:AD$105,2)/C7) | G7: =IF(C7=0,"",COUNTIF(Scoring!AD$6:AD$105,0)/C7)
A8: CF | B8: Comparator fairness | C8: =COUNT(Scoring!AE$6:AE$105) -> 0 | D8: =COUNTIF(Scoring!AE$6:AE$105,"NA") -> 0 | E8: =IFERROR(AVERAGE(Scoring!AE$6:AE$105),"") | F8: =IF(C8=0,"",COUNTIF(Scoring!AE$6:AE$105,2)/C8) | G8: =IF(C8=0,"",COUNTIF(Scoring!AE$6:AE$105,0)/C8)
A9: EA | B9: Energy accounting | C9: =COUNT(Scoring!AF$6:AF$105) -> 0 | D9: =COUNTIF(Scoring!AF$6:AF$105,"NA") -> 0 | E9: =IFERROR(AVERAGE(Scoring!AF$6:AF$105),"") | F9: =IF(C9=0,"",COUNTIF(Scoring!AF$6:AF$105,2)/C9) | G9: =IF(C9=0,"",COUNTIF(Scoring!AF$6:AF$105,0)/C9)
A10: RB | B10: Robustness | C10: =COUNT(Scoring!AG$6:AG$105) -> 0 | D10: =COUNTIF(Scoring!AG$6:AG$105,"NA") -> 0 | E10: =IFERROR(AVERAGE(Scoring!AG$6:AG$105),"") | F10: =IF(C10=0,"",COUNTIF(Scoring!AG$6:AG$105,2)/C10) | G10: =IF(C10=0,"",COUNTIF(Scoring!AG$6:AG$105,0)/C10)
A11: TR | B11: Transparency | C11: =COUNT(Scoring!AH$6:AH$105) -> 0 | D11: =COUNTIF(Scoring!AH$6:AH$105,"NA") -> 0 | E11: =IFERROR(AVERAGE(Scoring!AH$6:AH$105),"") | F11: =IF(C11=0,"",COUNTIF(Scoring!AH$6:AH$105,2)/C11) | G11: =IF(C11=0,"",COUNTIF(Scoring!AH$6:AH$105,0)/C11)
A12: CC | B12: Claim calibration | C12: =COUNT(Scoring!AI$6:AI$105) -> 0 | D12: =COUNTIF(Scoring!AI$6:AI$105,"NA") -> 0 | E12: =IFERROR(AVERAGE(Scoring!AI$6:AI$105),"") | F12: =IF(C12=0,"",COUNTIF(Scoring!AI$6:AI$105,2)/C12) | G12: =IF(C12=0,"",COUNTIF(Scoring!AI$6:AI$105,0)/C12)
A13: RP | B13: Replication | C13: =COUNT(Scoring!AJ$6:AJ$105) -> 0 | D13: =COUNTIF(Scoring!AJ$6:AJ$105,"NA") -> 0 | E13: =IFERROR(AVERAGE(Scoring!AJ$6:AJ$105),"") | F13: =IF(C13=0,"",COUNTIF(Scoring!AJ$6:AJ$105,2)/C13) | G13: =IF(C13=0,"",COUNTIF(Scoring!AJ$6:AJ$105,0)/C13)
A15: 2. Inter-rater agreement, Rater 1 vs Rater 2 (unweighted Cohen's kappa; only pairs where both raters gave a number)
A16: Code | B16: Item | C16: Pairs | D16: Exact agree | E16: % agree | F16: 0-vs-2 splits | G16: R1=0 | H16: R1=1 | I16: R1=2 | J16: R2=0 | K16: R2=1 | L16: R2=2 | M16: Expected agree (pE) | N16: Cohen's kappa
A17: SM | B17: System match | C17: =SUMPRODUCT(ISNUMBER(Scoring!$J$6:$J$105)*ISNUMBER(Scoring!$S$6:$S$105)) -> 0 | D17: =SUMPRODUCT(ISNUMBER(Scoring!$J$6:$J$105)*ISNUMBER(Scoring!$S$6:$S$105)*(Scoring!$J$6:$J$105=Scoring!$S$6:$S$105)) -> 0 | E17: =IF(C17=0,"",D17/C17) | F17: =SUMPRODUCT(ISNUMBER(Scoring!$J$6:$J$105)*ISNUMBER(Scoring!$S$6:$S$105)*(Scoring!$J$6:$J$105=0)*(Scoring!$S$6:$S$105=2))+SUMPRODUCT(ISNUMBER(Scoring!$J$6:$J$105)*ISNUMBER(Scoring!$S$6:$S$105)*(Scoring!$J$6:$J$105=2)*(Scoring!$S$6:$S$105=0)) -> 0 | G17: =SUMPRODUCT(ISNUMBER(Scoring!$J$6:$J$105)*ISNUMBER(Scoring!$S$6:$S$105)*(Scoring!$J$6:$J$105=0)) -> 0 | H17: =SUMPRODUCT(ISNUMBER(Scoring!$J$6:$J$105)*ISNUMBER(Scoring!$S$6:$S$105)*(Scoring!$J$6:$J$105=1)) -> 0 | I17: =SUMPRODUCT(ISNUMBER(Scoring!$J$6:$J$105)*ISNUMBER(Scoring!$S$6:$S$105)*(Scoring!$J$6:$J$105=2)) -> 0 | J17: =SUMPRODUCT(ISNUMBER(Scoring!$J$6:$J$105)*ISNUMBER(Scoring!$S$6:$S$105)*(Scoring!$S$6:$S$105=0)) -> 0 | K17: =SUMPRODUCT(ISNUMBER(Scoring!$J$6:$J$105)*ISNUMBER(Scoring!$S$6:$S$105)*(Scoring!$S$6:$S$105=1)) -> 0 | L17: =SUMPRODUCT(ISNUMBER(Scoring!$J$6:$J$105)*ISNUMBER(Scoring!$S$6:$S$105)*(Scoring!$S$6:$S$105=2)) -> 0 | M17: =IF(C17=0,"",(G17*J17+H17*K17+I17*L17)/C17^2) | N17: =IF(C17=0,"",IF(M17=1,"",(E17-M17)/(1-M17)))
A18: UA | B18: Unit of analysis | C18: =SUMPRODUCT(ISNUMBER(Scoring!$K$6:$K$105)*ISNUMBER(Scoring!$T$6:$T$105)) -> 0 | D18: =SUMPRODUCT(ISNUMBER(Scoring!$K$6:$K$105)*ISNUMBER(Scoring!$T$6:$T$105)*(Scoring!$K$6:$K$105=Scoring!$T$6:$T$105)) -> 0 | E18: =IF(C18=0,"",D18/C18) | F18: =SUMPRODUCT(ISNUMBER(Scoring!$K$6:$K$105)*ISNUMBER(Scoring!$T$6:$T$105)*(Scoring!$K$6:$K$105=0)*(Scoring!$T$6:$T$105=2))+SUMPRODUCT(ISNUMBER(Scoring!$K$6:$K$105)*ISNUMBER(Scoring!$T$6:$T$105)*(Scoring!$K$6:$K$105=2)*(Scoring!$T$6:$T$105=0)) -> 0 | G18: =SUMPRODUCT(ISNUMBER(Scoring!$K$6:$K$105)*ISNUMBER(Scoring!$T$6:$T$105)*(Scoring!$K$6:$K$105=0)) -> 0 | H18: =SUMPRODUCT(ISNUMBER(Scoring!$K$6:$K$105)*ISNUMBER(Scoring!$T$6:$T$105)*(Scoring!$K$6:$K$105=1)) -> 0 | I18: =SUMPRODUCT(ISNUMBER(Scoring!$K$6:$K$105)*ISNUMBER(Scoring!$T$6:$T$105)*(Scoring!$K$6:$K$105=2)) -> 0 | J18: =SUMPRODUCT(ISNUMBER(Scoring!$K$6:$K$105)*ISNUMBER(Scoring!$T$6:$T$105)*(Scoring!$T$6:$T$105=0)) -> 0 | K18: =SUMPRODUCT(ISNUMBER(Scoring!$K$6:$K$105)*ISNUMBER(Scoring!$T$6:$T$105)*(Scoring!$T$6:$T$105=1)) -> 0 | L18: =SUMPRODUCT(ISNUMBER(Scoring!$K$6:$K$105)*ISNUMBER(Scoring!$T$6:$T$105)*(Scoring!$T$6:$T$105=2)) -> 0 | M18: =IF(C18=0,"",(G18*J18+H18*K18+I18*L18)/C18^2) | N18: =IF(C18=0,"",IF(M18=1,"",(E18-M18)/(1-M18)))
A19: CT | B19: Controls | C19: =SUMPRODUCT(ISNUMBER(Scoring!$L$6:$L$105)*ISNUMBER(Scoring!$U$6:$U$105)) -> 0 | D19: =SUMPRODUCT(ISNUMBER(Scoring!$L$6:$L$105)*ISNUMBER(Scoring!$U$6:$U$105)*(Scoring!$L$6:$L$105=Scoring!$U$6:$U$105)) -> 0 | E19: =IF(C19=0,"",D19/C19) | F19: =SUMPRODUCT(ISNUMBER(Scoring!$L$6:$L$105)*ISNUMBER(Scoring!$U$6:$U$105)*(Scoring!$L$6:$L$105=0)*(Scoring!$U$6:$U$105=2))+SUMPRODUCT(ISNUMBER(Scoring!$L$6:$L$105)*ISNUMBER(Scoring!$U$6:$U$105)*(Scoring!$L$6:$L$105=2)*(Scoring!$U$6:$U$105=0)) -> 0 | G19: =SUMPRODUCT(ISNUMBER(Scoring!$L$6:$L$105)*ISNUMBER(Scoring!$U$6:$U$105)*(Scoring!$L$6:$L$105=0)) -> 0 | H19: =SUMPRODUCT(ISNUMBER(Scoring!$L$6:$L$105)*ISNUMBER(Scoring!$U$6:$U$105)*(Scoring!$L$6:$L$105=1)) -> 0 | I19: =SUMPRODUCT(ISNUMBER(Scoring!$L$6:$L$105)*ISNUMBER(Scoring!$U$6:$U$105)*(Scoring!$L$6:$L$105=2)) -> 0 | J19: =SUMPRODUCT(ISNUMBER(Scoring!$L$6:$L$105)*ISNUMBER(Scoring!$U$6:$U$105)*(Scoring!$U$6:$U$105=0)) -> 0 | K19: =SUMPRODUCT(ISNUMBER(Scoring!$L$6:$L$105)*ISNUMBER(Scoring!$U$6:$U$105)*(Scoring!$U$6:$U$105=1)) -> 0 | L19: =SUMPRODUCT(ISNUMBER(Scoring!$L$6:$L$105)*ISNUMBER(Scoring!$U$6:$U$105)*(Scoring!$U$6:$U$105=2)) -> 0 | M19: =IF(C19=0,"",(G19*J19+H19*K19+I19*L19)/C19^2) | N19: =IF(C19=0,"",IF(M19=1,"",(E19-M19)/(1-M19)))
A20: CF | B20: Comparator fairness | C20: =SUMPRODUCT(ISNUMBER(Scoring!$M$6:$M$105)*ISNUMBER(Scoring!$V$6:$V$105)) -> 0 | D20: =SUMPRODUCT(ISNUMBER(Scoring!$M$6:$M$105)*ISNUMBER(Scoring!$V$6:$V$105)*(Scoring!$M$6:$M$105=Scoring!$V$6:$V$105)) -> 0 | E20: =IF(C20=0,"",D20/C20) | F20: =SUMPRODUCT(ISNUMBER(Scoring!$M$6:$M$105)*ISNUMBER(Scoring!$V$6:$V$105)*(Scoring!$M$6:$M$105=0)*(Scoring!$V$6:$V$105=2))+SUMPRODUCT(ISNUMBER(Scoring!$M$6:$M$105)*ISNUMBER(Scoring!$V$6:$V$105)*(Scoring!$M$6:$M$105=2)*(Scoring!$V$6:$V$105=0)) -> 0 | G20: =SUMPRODUCT(ISNUMBER(Scoring!$M$6:$M$105)*ISNUMBER(Scoring!$V$6:$V$105)*(Scoring!$M$6:$M$105=0)) -> 0 | H20: =SUMPRODUCT(ISNUMBER(Scoring!$M$6:$M$105)*ISNUMBER(Scoring!$V$6:$V$105)*(Scoring!$M$6:$M$105=1)) -> 0 | I20: =SUMPRODUCT(ISNUMBER(Scoring!$M$6:$M$105)*ISNUMBER(Scoring!$V$6:$V$105)*(Scoring!$M$6:$M$105=2)) -> 0 | J20: =SUMPRODUCT(ISNUMBER(Scoring!$M$6:$M$105)*ISNUMBER(Scoring!$V$6:$V$105)*(Scoring!$V$6:$V$105=0)) -> 0 | K20: =SUMPRODUCT(ISNUMBER(Scoring!$M$6:$M$105)*ISNUMBER(Scoring!$V$6:$V$105)*(Scoring!$V$6:$V$105=1)) -> 0 | L20: =SUMPRODUCT(ISNUMBER(Scoring!$M$6:$M$105)*ISNUMBER(Scoring!$V$6:$V$105)*(Scoring!$V$6:$V$105=2)) -> 0 | M20: =IF(C20=0,"",(G20*J20+H20*K20+I20*L20)/C20^2) | N20: =IF(C20=0,"",IF(M20=1,"",(E20-M20)/(1-M20)))
A21: EA | B21: Energy accounting | C21: =SUMPRODUCT(ISNUMBER(Scoring!$N$6:$N$105)*ISNUMBER(Scoring!$W$6:$W$105)) -> 0 | D21: =SUMPRODUCT(ISNUMBER(Scoring!$N$6:$N$105)*ISNUMBER(Scoring!$W$6:$W$105)*(Scoring!$N$6:$N$105=Scoring!$W$6:$W$105)) -> 0 | E21: =IF(C21=0,"",D21/C21) | F21: =SUMPRODUCT(ISNUMBER(Scoring!$N$6:$N$105)*ISNUMBER(Scoring!$W$6:$W$105)*(Scoring!$N$6:$N$105=0)*(Scoring!$W$6:$W$105=2))+SUMPRODUCT(ISNUMBER(Scoring!$N$6:$N$105)*ISNUMBER(Scoring!$W$6:$W$105)*(Scoring!$N$6:$N$105=2)*(Scoring!$W$6:$W$105=0)) -> 0 | G21: =SUMPRODUCT(ISNUMBER(Scoring!$N$6:$N$105)*ISNUMBER(Scoring!$W$6:$W$105)*(Scoring!$N$6:$N$105=0)) -> 0 | H21: =SUMPRODUCT(ISNUMBER(Scoring!$N$6:$N$105)*ISNUMBER(Scoring!$W$6:$W$105)*(Scoring!$N$6:$N$105=1)) -> 0 | I21: =SUMPRODUCT(ISNUMBER(Scoring!$N$6:$N$105)*ISNUMBER(Scoring!$W$6:$W$105)*(Scoring!$N$6:$N$105=2)) -> 0 | J21: =SUMPRODUCT(ISNUMBER(Scoring!$N$6:$N$105)*ISNUMBER(Scoring!$W$6:$W$105)*(Scoring!$W$6:$W$105=0)) -> 0 | K21: =SUMPRODUCT(ISNUMBER(Scoring!$N$6:$N$105)*ISNUMBER(Scoring!$W$6:$W$105)*(Scoring!$W$6:$W$105=1)) -> 0 | L21: =SUMPRODUCT(ISNUMBER(Scoring!$N$6:$N$105)*ISNUMBER(Scoring!$W$6:$W$105)*(Scoring!$W$6:$W$105=2)) -> 0 | M21: =IF(C21=0,"",(G21*J21+H21*K21+I21*L21)/C21^2) | N21: =IF(C21=0,"",IF(M21=1,"",(E21-M21)/(1-M21)))
A22: RB | B22: Robustness | C22: =SUMPRODUCT(ISNUMBER(Scoring!$O$6:$O$105)*ISNUMBER(Scoring!$X$6:$X$105)) -> 0 | D22: =SUMPRODUCT(ISNUMBER(Scoring!$O$6:$O$105)*ISNUMBER(Scoring!$X$6:$X$105)*(Scoring!$O$6:$O$105=Scoring!$X$6:$X$105)) -> 0 | E22: =IF(C22=0,"",D22/C22) | F22: =SUMPRODUCT(ISNUMBER(Scoring!$O$6:$O$105)*ISNUMBER(Scoring!$X$6:$X$105)*(Scoring!$O$6:$O$105=0)*(Scoring!$X$6:$X$105=2))+SUMPRODUCT(ISNUMBER(Scoring!$O$6:$O$105)*ISNUMBER(Scoring!$X$6:$X$105)*(Scoring!$O$6:$O$105=2)*(Scoring!$X$6:$X$105=0)) -> 0 | G22: =SUMPRODUCT(ISNUMBER(Scoring!$O$6:$O$105)*ISNUMBER(Scoring!$X$6:$X$105)*(Scoring!$O$6:$O$105=0)) -> 0 | H22: =SUMPRODUCT(ISNUMBER(Scoring!$O$6:$O$105)*ISNUMBER(Scoring!$X$6:$X$105)*(Scoring!$O$6:$O$105=1)) -> 0 | I22: =SUMPRODUCT(ISNUMBER(Scoring!$O$6:$O$105)*ISNUMBER(Scoring!$X$6:$X$105)*(Scoring!$O$6:$O$105=2)) -> 0 | J22: =SUMPRODUCT(ISNUMBER(Scoring!$O$6:$O$105)*ISNUMBER(Scoring!$X$6:$X$105)*(Scoring!$X$6:$X$105=0)) -> 0 | K22: =SUMPRODUCT(ISNUMBER(Scoring!$O$6:$O$105)*ISNUMBER(Scoring!$X$6:$X$105)*(Scoring!$X$6:$X$105=1)) -> 0 | L22: =SUMPRODUCT(ISNUMBER(Scoring!$O$6:$O$105)*ISNUMBER(Scoring!$X$6:$X$105)*(Scoring!$X$6:$X$105=2)) -> 0 | M22: =IF(C22=0,"",(G22*J22+H22*K22+I22*L22)/C22^2) | N22: =IF(C22=0,"",IF(M22=1,"",(E22-M22)/(1-M22)))
A23: TR | B23: Transparency | C23: =SUMPRODUCT(ISNUMBER(Scoring!$P$6:$P$105)*ISNUMBER(Scoring!$Y$6:$Y$105)) -> 0 | D23: =SUMPRODUCT(ISNUMBER(Scoring!$P$6:$P$105)*ISNUMBER(Scoring!$Y$6:$Y$105)*(Scoring!$P$6:$P$105=Scoring!$Y$6:$Y$105)) -> 0 | E23: =IF(C23=0,"",D23/C23) | F23: =SUMPRODUCT(ISNUMBER(Scoring!$P$6:$P$105)*ISNUMBER(Scoring!$Y$6:$Y$105)*(Scoring!$P$6:$P$105=0)*(Scoring!$Y$6:$Y$105=2))+SUMPRODUCT(ISNUMBER(Scoring!$P$6:$P$105)*ISNUMBER(Scoring!$Y$6:$Y$105)*(Scoring!$P$6:$P$105=2)*(Scoring!$Y$6:$Y$105=0)) -> 0 | G23: =SUMPRODUCT(ISNUMBER(Scoring!$P$6:$P$105)*ISNUMBER(Scoring!$Y$6:$Y$105)*(Scoring!$P$6:$P$105=0)) -> 0 | H23: =SUMPRODUCT(ISNUMBER(Scoring!$P$6:$P$105)*ISNUMBER(Scoring!$Y$6:$Y$105)*(Scoring!$P$6:$P$105=1)) -> 0 | I23: =SUMPRODUCT(ISNUMBER(Scoring!$P$6:$P$105)*ISNUMBER(Scoring!$Y$6:$Y$105)*(Scoring!$P$6:$P$105=2)) -> 0 | J23: =SUMPRODUCT(ISNUMBER(Scoring!$P$6:$P$105)*ISNUMBER(Scoring!$Y$6:$Y$105)*(Scoring!$Y$6:$Y$105=0)) -> 0 | K23: =SUMPRODUCT(ISNUMBER(Scoring!$P$6:$P$105)*ISNUMBER(Scoring!$Y$6:$Y$105)*(Scoring!$Y$6:$Y$105=1)) -> 0 | L23: =SUMPRODUCT(ISNUMBER(Scoring!$P$6:$P$105)*ISNUMBER(Scoring!$Y$6:$Y$105)*(Scoring!$Y$6:$Y$105=2)) -> 0 | M23: =IF(C23=0,"",(G23*J23+H23*K23+I23*L23)/C23^2) | N23: =IF(C23=0,"",IF(M23=1,"",(E23-M23)/(1-M23)))
A24: CC | B24: Claim calibration | C24: =SUMPRODUCT(ISNUMBER(Scoring!$Q$6:$Q$105)*ISNUMBER(Scoring!$Z$6:$Z$105)) -> 0 | D24: =SUMPRODUCT(ISNUMBER(Scoring!$Q$6:$Q$105)*ISNUMBER(Scoring!$Z$6:$Z$105)*(Scoring!$Q$6:$Q$105=Scoring!$Z$6:$Z$105)) -> 0 | E24: =IF(C24=0,"",D24/C24) | F24: =SUMPRODUCT(ISNUMBER(Scoring!$Q$6:$Q$105)*ISNUMBER(Scoring!$Z$6:$Z$105)*(Scoring!$Q$6:$Q$105=0)*(Scoring!$Z$6:$Z$105=2))+SUMPRODUCT(ISNUMBER(Scoring!$Q$6:$Q$105)*ISNUMBER(Scoring!$Z$6:$Z$105)*(Scoring!$Q$6:$Q$105=2)*(Scoring!$Z$6:$Z$105=0)) -> 0 | G24: =SUMPRODUCT(ISNUMBER(Scoring!$Q$6:$Q$105)*ISNUMBER(Scoring!$Z$6:$Z$105)*(Scoring!$Q$6:$Q$105=0)) -> 0 | H24: =SUMPRODUCT(ISNUMBER(Scoring!$Q$6:$Q$105)*ISNUMBER(Scoring!$Z$6:$Z$105)*(Scoring!$Q$6:$Q$105=1)) -> 0 | I24: =SUMPRODUCT(ISNUMBER(Scoring!$Q$6:$Q$105)*ISNUMBER(Scoring!$Z$6:$Z$105)*(Scoring!$Q$6:$Q$105=2)) -> 0 | J24: =SUMPRODUCT(ISNUMBER(Scoring!$Q$6:$Q$105)*ISNUMBER(Scoring!$Z$6:$Z$105)*(Scoring!$Z$6:$Z$105=0)) -> 0 | K24: =SUMPRODUCT(ISNUMBER(Scoring!$Q$6:$Q$105)*ISNUMBER(Scoring!$Z$6:$Z$105)*(Scoring!$Z$6:$Z$105=1)) -> 0 | L24: =SUMPRODUCT(ISNUMBER(Scoring!$Q$6:$Q$105)*ISNUMBER(Scoring!$Z$6:$Z$105)*(Scoring!$Z$6:$Z$105=2)) -> 0 | M24: =IF(C24=0,"",(G24*J24+H24*K24+I24*L24)/C24^2) | N24: =IF(C24=0,"",IF(M24=1,"",(E24-M24)/(1-M24)))
A25: RP | B25: Replication | C25: =SUMPRODUCT(ISNUMBER(Scoring!$R$6:$R$105)*ISNUMBER(Scoring!$AA$6:$AA$105)) -> 0 | D25: =SUMPRODUCT(ISNUMBER(Scoring!$R$6:$R$105)*ISNUMBER(Scoring!$AA$6:$AA$105)*(Scoring!$R$6:$R$105=Scoring!$AA$6:$AA$105)) -> 0 | E25: =IF(C25=0,"",D25/C25) | F25: =SUMPRODUCT(ISNUMBER(Scoring!$R$6:$R$105)*ISNUMBER(Scoring!$AA$6:$AA$105)*(Scoring!$R$6:$R$105=0)*(Scoring!$AA$6:$AA$105=2))+SUMPRODUCT(ISNUMBER(Scoring!$R$6:$R$105)*ISNUMBER(Scoring!$AA$6:$AA$105)*(Scoring!$R$6:$R$105=2)*(Scoring!$AA$6:$AA$105=0)) -> 0 | G25: =SUMPRODUCT(ISNUMBER(Scoring!$R$6:$R$105)*ISNUMBER(Scoring!$AA$6:$AA$105)*(Scoring!$R$6:$R$105=0)) -> 0 | H25: =SUMPRODUCT(ISNUMBER(Scoring!$R$6:$R$105)*ISNUMBER(Scoring!$AA$6:$AA$105)*(Scoring!$R$6:$R$105=1)) -> 0 | I25: =SUMPRODUCT(ISNUMBER(Scoring!$R$6:$R$105)*ISNUMBER(Scoring!$AA$6:$AA$105)*(Scoring!$R$6:$R$105=2)) -> 0 | J25: =SUMPRODUCT(ISNUMBER(Scoring!$R$6:$R$105)*ISNUMBER(Scoring!$AA$6:$AA$105)*(Scoring!$AA$6:$AA$105=0)) -> 0 | K25: =SUMPRODUCT(ISNUMBER(Scoring!$R$6:$R$105)*ISNUMBER(Scoring!$AA$6:$AA$105)*(Scoring!$AA$6:$AA$105=1)) -> 0 | L25: =SUMPRODUCT(ISNUMBER(Scoring!$R$6:$R$105)*ISNUMBER(Scoring!$AA$6:$AA$105)*(Scoring!$AA$6:$AA$105=2)) -> 0 | M25: =IF(C25=0,"",(G25*J25+H25*K25+I25*L25)/C25^2) | N25: =IF(C25=0,"",IF(M25=1,"",(E25-M25)/(1-M25)))
A26: All | B26: Pooled across items | C26: =SUM(C17:C25) -> 0 | D26: =SUM(D17:D25) -> 0 | E26: =IF(C26=0,"",D26/C26) | F26: =SUM(F17:F25) -> 0 | G26: =SUM(G17:G25) -> 0 | H26: =SUM(H17:H25) -> 0 | I26: =SUM(I17:I25) -> 0 | J26: =SUM(J17:J25) -> 0 | K26: =SUM(K17:K25) -> 0 | L26: =SUM(L17:L25) -> 0 | M26: =IF(C26=0,"",(G26*J26+H26*K26+I26*L26)/C26^2) | N26: =IF(C26=0,"",IF(M26=1,"",(E26-M26)/(1-M26)))
A27: Notes: unweighted kappa treats 0-vs-1 and 0-vs-2 as equally bad, which is harsh for an ordinal scale; a linear-weighted kappa can be computed once scores exist. With about 10-15 doubly scored papers, per-item kappas are unstable, so lean on the pooled figure and the 0-vs-2 splits. Kappa can be low even with high % agreement when one score dominates (e.g., most EA items are NA or 0).
A29: 3. Scores by COI / affiliation group (descriptive; does affiliation track rigor?)
A30: Group | B30: Papers with a score | C30: Mean of paper means | D30: SM | E30: UA | F30: CT | G30: CF | H30: EA | I30: RB | J30: TR | K30: CC | L30: RP
A31: =Lists!D2 -> Company / industry source | B31: =COUNTIFS(Scoring!$G$6:$G$105,$A31,Scoring!$AK$6:$AK$105,">=0") -> 0 | C31: =IFERROR(AVERAGEIFS(Scoring!$AK$6:$AK$105,Scoring!$G$6:$G$105,$A31),"") | D31: =IFERROR(AVERAGEIFS(Scoring!$AB$6:$AB$105,Scoring!$G$6:$G$105,$A31),"") | E31: =IFERROR(AVERAGEIFS(Scoring!$AC$6:$AC$105,Scoring!$G$6:$G$105,$A31),"") | F31: =IFERROR(AVERAGEIFS(Scoring!$AD$6:$AD$105,Scoring!$G$6:$G$105,$A31),"") | G31: =IFERROR(AVERAGEIFS(Scoring!$AE$6:$AE$105,Scoring!$G$6:$G$105,$A31),"") | H31: =IFERROR(AVERAGEIFS(Scoring!$AF$6:$AF$105,Scoring!$G$6:$G$105,$A31),"") | I31: =IFERROR(AVERAGEIFS(Scoring!$AG$6:$AG$105,Scoring!$G$6:$G$105,$A31),"") | J31: =IFERROR(AVERAGEIFS(Scoring!$AH$6:$AH$105,Scoring!$G$6:$G$105,$A31),"") | K31: =IFERROR(AVERAGEIFS(Scoring!$AI$6:$AI$105,Scoring!$G$6:$G$105,$A31),"") | L31: =IFERROR(AVERAGEIFS(Scoring!$AJ$6:$AJ$105,Scoring!$G$6:$G$105,$A31),"")
A32: =Lists!D3 -> Mixed academic-industry authors | B32: =COUNTIFS(Scoring!$G$6:$G$105,$A32,Scoring!$AK$6:$AK$105,">=0") -> 0 | C32: =IFERROR(AVERAGEIFS(Scoring!$AK$6:$AK$105,Scoring!$G$6:$G$105,$A32),"") | D32: =IFERROR(AVERAGEIFS(Scoring!$AB$6:$AB$105,Scoring!$G$6:$G$105,$A32),"") | E32: =IFERROR(AVERAGEIFS(Scoring!$AC$6:$AC$105,Scoring!$G$6:$G$105,$A32),"") | F32: =IFERROR(AVERAGEIFS(Scoring!$AD$6:$AD$105,Scoring!$G$6:$G$105,$A32),"") | G32: =IFERROR(AVERAGEIFS(Scoring!$AE$6:$AE$105,Scoring!$G$6:$G$105,$A32),"") | H32: =IFERROR(AVERAGEIFS(Scoring!$AF$6:$AF$105,Scoring!$G$6:$G$105,$A32),"") | I32: =IFERROR(AVERAGEIFS(Scoring!$AG$6:$AG$105,Scoring!$G$6:$G$105,$A32),"") | J32: =IFERROR(AVERAGEIFS(Scoring!$AH$6:$AH$105,Scoring!$G$6:$G$105,$A32),"") | K32: =IFERROR(AVERAGEIFS(Scoring!$AI$6:$AI$105,Scoring!$G$6:$G$105,$A32),"") | L32: =IFERROR(AVERAGEIFS(Scoring!$AJ$6:$AJ$105,Scoring!$G$6:$G$105,$A32),"")
A33: =Lists!D4 -> Academic, declared industry COI | B33: =COUNTIFS(Scoring!$G$6:$G$105,$A33,Scoring!$AK$6:$AK$105,">=0") -> 0 | C33: =IFERROR(AVERAGEIFS(Scoring!$AK$6:$AK$105,Scoring!$G$6:$G$105,$A33),"") | D33: =IFERROR(AVERAGEIFS(Scoring!$AB$6:$AB$105,Scoring!$G$6:$G$105,$A33),"") | E33: =IFERROR(AVERAGEIFS(Scoring!$AC$6:$AC$105,Scoring!$G$6:$G$105,$A33),"") | F33: =IFERROR(AVERAGEIFS(Scoring!$AD$6:$AD$105,Scoring!$G$6:$G$105,$A33),"") | G33: =IFERROR(AVERAGEIFS(Scoring!$AE$6:$AE$105,Scoring!$G$6:$G$105,$A33),"") | H33: =IFERROR(AVERAGEIFS(Scoring!$AF$6:$AF$105,Scoring!$G$6:$G$105,$A33),"") | I33: =IFERROR(AVERAGEIFS(Scoring!$AG$6:$AG$105,Scoring!$G$6:$G$105,$A33),"") | J33: =IFERROR(AVERAGEIFS(Scoring!$AH$6:$AH$105,Scoring!$G$6:$G$105,$A33),"") | K33: =IFERROR(AVERAGEIFS(Scoring!$AI$6:$AI$105,Scoring!$G$6:$G$105,$A33),"") | L33: =IFERROR(AVERAGEIFS(Scoring!$AJ$6:$AJ$105,Scoring!$G$6:$G$105,$A33),"")
A34: =Lists!D5 -> Academic, none declared | B34: =COUNTIFS(Scoring!$G$6:$G$105,$A34,Scoring!$AK$6:$AK$105,">=0") -> 0 | C34: =IFERROR(AVERAGEIFS(Scoring!$AK$6:$AK$105,Scoring!$G$6:$G$105,$A34),"") | D34: =IFERROR(AVERAGEIFS(Scoring!$AB$6:$AB$105,Scoring!$G$6:$G$105,$A34),"") | E34: =IFERROR(AVERAGEIFS(Scoring!$AC$6:$AC$105,Scoring!$G$6:$G$105,$A34),"") | F34: =IFERROR(AVERAGEIFS(Scoring!$AD$6:$AD$105,Scoring!$G$6:$G$105,$A34),"") | G34: =IFERROR(AVERAGEIFS(Scoring!$AE$6:$AE$105,Scoring!$G$6:$G$105,$A34),"") | H34: =IFERROR(AVERAGEIFS(Scoring!$AF$6:$AF$105,Scoring!$G$6:$G$105,$A34),"") | I34: =IFERROR(AVERAGEIFS(Scoring!$AG$6:$AG$105,Scoring!$G$6:$G$105,$A34),"") | J34: =IFERROR(AVERAGEIFS(Scoring!$AH$6:$AH$105,Scoring!$G$6:$G$105,$A34),"") | K34: =IFERROR(AVERAGEIFS(Scoring!$AI$6:$AI$105,Scoring!$G$6:$G$105,$A34),"") | L34: =IFERROR(AVERAGEIFS(Scoring!$AJ$6:$AJ$105,Scoring!$G$6:$G$105,$A34),"")
A35: =Lists!D6 -> Not checked | B35: =COUNTIFS(Scoring!$G$6:$G$105,$A35,Scoring!$AK$6:$AK$105,">=0") -> 0 | C35: =IFERROR(AVERAGEIFS(Scoring!$AK$6:$AK$105,Scoring!$G$6:$G$105,$A35),"") | D35: =IFERROR(AVERAGEIFS(Scoring!$AB$6:$AB$105,Scoring!$G$6:$G$105,$A35),"") | E35: =IFERROR(AVERAGEIFS(Scoring!$AC$6:$AC$105,Scoring!$G$6:$G$105,$A35),"") | F35: =IFERROR(AVERAGEIFS(Scoring!$AD$6:$AD$105,Scoring!$G$6:$G$105,$A35),"") | G35: =IFERROR(AVERAGEIFS(Scoring!$AE$6:$AE$105,Scoring!$G$6:$G$105,$A35),"") | H35: =IFERROR(AVERAGEIFS(Scoring!$AF$6:$AF$105,Scoring!$G$6:$G$105,$A35),"") | I35: =IFERROR(AVERAGEIFS(Scoring!$AG$6:$AG$105,Scoring!$G$6:$G$105,$A35),"") | J35: =IFERROR(AVERAGEIFS(Scoring!$AH$6:$AH$105,Scoring!$G$6:$G$105,$A35),"") | K35: =IFERROR(AVERAGEIFS(Scoring!$AI$6:$AI$105,Scoring!$G$6:$G$105,$A35),"") | L35: =IFERROR(AVERAGEIFS(Scoring!$AJ$6:$AJ$105,Scoring!$G$6:$G$105,$A35),"")
A36: Caution: groups will be small and confounded (industry sources also make most of the efficiency claims, so EA and CF are scored on different papers). Report counts alongside means, and use an exact test (e.g., Mann-Whitney) rather than reading small gaps as findings.
A38: 4. Scores by peer-review status
A39: Group | B39: Papers with a score | C39: Mean of paper means | D39: SM | E39: UA | F39: CT | G39: CF | H39: EA | I39: RB | J39: TR | K39: CC | L39: RP
A40: =Lists!E2 -> Peer-reviewed | B40: =COUNTIFS(Scoring!$F$6:$F$105,$A40,Scoring!$AK$6:$AK$105,">=0") -> 0 | C40: =IFERROR(AVERAGEIFS(Scoring!$AK$6:$AK$105,Scoring!$F$6:$F$105,$A40),"") | D40: =IFERROR(AVERAGEIFS(Scoring!$AB$6:$AB$105,Scoring!$F$6:$F$105,$A40),"") | E40: =IFERROR(AVERAGEIFS(Scoring!$AC$6:$AC$105,Scoring!$F$6:$F$105,$A40),"") | F40: =IFERROR(AVERAGEIFS(Scoring!$AD$6:$AD$105,Scoring!$F$6:$F$105,$A40),"") | G40: =IFERROR(AVERAGEIFS(Scoring!$AE$6:$AE$105,Scoring!$F$6:$F$105,$A40),"") | H40: =IFERROR(AVERAGEIFS(Scoring!$AF$6:$AF$105,Scoring!$F$6:$F$105,$A40),"") | I40: =IFERROR(AVERAGEIFS(Scoring!$AG$6:$AG$105,Scoring!$F$6:$F$105,$A40),"") | J40: =IFERROR(AVERAGEIFS(Scoring!$AH$6:$AH$105,Scoring!$F$6:$F$105,$A40),"") | K40: =IFERROR(AVERAGEIFS(Scoring!$AI$6:$AI$105,Scoring!$F$6:$F$105,$A40),"") | L40: =IFERROR(AVERAGEIFS(Scoring!$AJ$6:$AJ$105,Scoring!$F$6:$F$105,$A40),"")
A41: =Lists!E3 -> Preprint | B41: =COUNTIFS(Scoring!$F$6:$F$105,$A41,Scoring!$AK$6:$AK$105,">=0") -> 0 | C41: =IFERROR(AVERAGEIFS(Scoring!$AK$6:$AK$105,Scoring!$F$6:$F$105,$A41),"") | D41: =IFERROR(AVERAGEIFS(Scoring!$AB$6:$AB$105,Scoring!$F$6:$F$105,$A41),"") | E41: =IFERROR(AVERAGEIFS(Scoring!$AC$6:$AC$105,Scoring!$F$6:$F$105,$A41),"") | F41: =IFERROR(AVERAGEIFS(Scoring!$AD$6:$AD$105,Scoring!$F$6:$F$105,$A41),"") | G41: =IFERROR(AVERAGEIFS(Scoring!$AE$6:$AE$105,Scoring!$F$6:$F$105,$A41),"") | H41: =IFERROR(AVERAGEIFS(Scoring!$AF$6:$AF$105,Scoring!$F$6:$F$105,$A41),"") | I41: =IFERROR(AVERAGEIFS(Scoring!$AG$6:$AG$105,Scoring!$F$6:$F$105,$A41),"") | J41: =IFERROR(AVERAGEIFS(Scoring!$AH$6:$AH$105,Scoring!$F$6:$F$105,$A41),"") | K41: =IFERROR(AVERAGEIFS(Scoring!$AI$6:$AI$105,Scoring!$F$6:$F$105,$A41),"") | L41: =IFERROR(AVERAGEIFS(Scoring!$AJ$6:$AJ$105,Scoring!$F$6:$F$105,$A41),"")
A42: =Lists!E4 -> Company/market page | B42: =COUNTIFS(Scoring!$F$6:$F$105,$A42,Scoring!$AK$6:$AK$105,">=0") -> 0 | C42: =IFERROR(AVERAGEIFS(Scoring!$AK$6:$AK$105,Scoring!$F$6:$F$105,$A42),"") | D42: =IFERROR(AVERAGEIFS(Scoring!$AB$6:$AB$105,Scoring!$F$6:$F$105,$A42),"") | E42: =IFERROR(AVERAGEIFS(Scoring!$AC$6:$AC$105,Scoring!$F$6:$F$105,$A42),"") | F42: =IFERROR(AVERAGEIFS(Scoring!$AD$6:$AD$105,Scoring!$F$6:$F$105,$A42),"") | G42: =IFERROR(AVERAGEIFS(Scoring!$AE$6:$AE$105,Scoring!$F$6:$F$105,$A42),"") | H42: =IFERROR(AVERAGEIFS(Scoring!$AF$6:$AF$105,Scoring!$F$6:$F$105,$A42),"") | I42: =IFERROR(AVERAGEIFS(Scoring!$AG$6:$AG$105,Scoring!$F$6:$F$105,$A42),"") | J42: =IFERROR(AVERAGEIFS(Scoring!$AH$6:$AH$105,Scoring!$F$6:$F$105,$A42),"") | K42: =IFERROR(AVERAGEIFS(Scoring!$AI$6:$AI$105,Scoring!$F$6:$F$105,$A42),"") | L42: =IFERROR(AVERAGEIFS(Scoring!$AJ$6:$AJ$105,Scoring!$F$6:$F$105,$A42),"")
A44: 5. Claims audit: how each claim category is tagged
A45: Category | B45: Total claims | C45: Demonstrated | D45: Demonstrated under constraints | E45: Projected | F45: Illustrative | G45: Aspirational | H45: Not demonstrated | I45: % without direct measurement
A46: =Lists!C2 -> Computational performance | B46: =COUNTIF(Claims!$D$5:$D$204,$A46) -> 3 | C46: =COUNTIFS(Claims!$D$5:$D$204,$A46,Claims!$F$5:$F$204,Lists!$B$2) -> 0 | D46: =COUNTIFS(Claims!$D$5:$D$204,$A46,Claims!$F$5:$F$204,Lists!$B$3) -> 1 | E46: =COUNTIFS(Claims!$D$5:$D$204,$A46,Claims!$F$5:$F$204,Lists!$B$4) -> 0 | F46: =COUNTIFS(Claims!$D$5:$D$204,$A46,Claims!$F$5:$F$204,Lists!$B$5) -> 0 | G46: =COUNTIFS(Claims!$D$5:$D$204,$A46,Claims!$F$5:$F$204,Lists!$B$6) -> 1 | H46: =COUNTIFS(Claims!$D$5:$D$204,$A46,Claims!$F$5:$F$204,Lists!$B$7) -> 1 | I46: =IF(B46=0,"",(E46+F46+G46+H46)/B46) -> 0.66666667
A47: =Lists!C3 -> Learning/adaptation | B47: =COUNTIF(Claims!$D$5:$D$204,$A47) -> 2 | C47: =COUNTIFS(Claims!$D$5:$D$204,$A47,Claims!$F$5:$F$204,Lists!$B$2) -> 1 | D47: =COUNTIFS(Claims!$D$5:$D$204,$A47,Claims!$F$5:$F$204,Lists!$B$3) -> 1 | E47: =COUNTIFS(Claims!$D$5:$D$204,$A47,Claims!$F$5:$F$204,Lists!$B$4) -> 0 | F47: =COUNTIFS(Claims!$D$5:$D$204,$A47,Claims!$F$5:$F$204,Lists!$B$5) -> 0 | G47: =COUNTIFS(Claims!$D$5:$D$204,$A47,Claims!$F$5:$F$204,Lists!$B$6) -> 0 | H47: =COUNTIFS(Claims!$D$5:$D$204,$A47,Claims!$F$5:$F$204,Lists!$B$7) -> 0 | I47: =IF(B47=0,"",(E47+F47+G47+H47)/B47) -> 0
A48: =Lists!C4 -> Efficiency (energy/sample/cost) | B48: =COUNTIF(Claims!$D$5:$D$204,$A48) -> 4 | C48: =COUNTIFS(Claims!$D$5:$D$204,$A48,Claims!$F$5:$F$204,Lists!$B$2) -> 0 | D48: =COUNTIFS(Claims!$D$5:$D$204,$A48,Claims!$F$5:$F$204,Lists!$B$3) -> 1 | E48: =COUNTIFS(Claims!$D$5:$D$204,$A48,Claims!$F$5:$F$204,Lists!$B$4) -> 1 | F48: =COUNTIFS(Claims!$D$5:$D$204,$A48,Claims!$F$5:$F$204,Lists!$B$5) -> 1 | G48: =COUNTIFS(Claims!$D$5:$D$204,$A48,Claims!$F$5:$F$204,Lists!$B$6) -> 0 | H48: =COUNTIFS(Claims!$D$5:$D$204,$A48,Claims!$F$5:$F$204,Lists!$B$7) -> 1 | I48: =IF(B48=0,"",(E48+F48+G48+H48)/B48) -> 0.75
A49: =Lists!C5 -> Sentience/intelligence | B49: =COUNTIF(Claims!$D$5:$D$204,$A49) -> 1 | C49: =COUNTIFS(Claims!$D$5:$D$204,$A49,Claims!$F$5:$F$204,Lists!$B$2) -> 0 | D49: =COUNTIFS(Claims!$D$5:$D$204,$A49,Claims!$F$5:$F$204,Lists!$B$3) -> 0 | E49: =COUNTIFS(Claims!$D$5:$D$204,$A49,Claims!$F$5:$F$204,Lists!$B$4) -> 0 | F49: =COUNTIFS(Claims!$D$5:$D$204,$A49,Claims!$F$5:$F$204,Lists!$B$5) -> 0 | G49: =COUNTIFS(Claims!$D$5:$D$204,$A49,Claims!$F$5:$F$204,Lists!$B$6) -> 0 | H49: =COUNTIFS(Claims!$D$5:$D$204,$A49,Claims!$F$5:$F$204,Lists!$B$7) -> 1 | I49: =IF(B49=0,"",(E49+F49+G49+H49)/B49) -> 1
A50: =Lists!C6 -> Other | B50: =COUNTIF(Claims!$D$5:$D$204,$A50) -> 1 | C50: =COUNTIFS(Claims!$D$5:$D$204,$A50,Claims!$F$5:$F$204,Lists!$B$2) -> 1 | D50: =COUNTIFS(Claims!$D$5:$D$204,$A50,Claims!$F$5:$F$204,Lists!$B$3) -> 0 | E50: =COUNTIFS(Claims!$D$5:$D$204,$A50,Claims!$F$5:$F$204,Lists!$B$4) -> 0 | F50: =COUNTIFS(Claims!$D$5:$D$204,$A50,Claims!$F$5:$F$204,Lists!$B$5) -> 0 | G50: =COUNTIFS(Claims!$D$5:$D$204,$A50,Claims!$F$5:$F$204,Lists!$B$6) -> 0 | H50: =COUNTIFS(Claims!$D$5:$D$204,$A50,Claims!$F$5:$F$204,Lists!$B$7) -> 0 | I50: =IF(B50=0,"",(E50+F50+G50+H50)/B50) -> 0
A51: All categories | B51: =SUM(B46:B50) -> 11 | C51: =SUM(C46:C50) -> 2 | D51: =SUM(D46:D50) -> 3 | E51: =SUM(E46:E50) -> 1 | F51: =SUM(F46:F50) -> 1 | G51: =SUM(G46:G50) -> 1 | H51: =SUM(H46:H50) -> 3 | I51: =IF(B51=0,"",(E51+F51+G51+H51)/B51) -> 0.54545455
A52: '% without direct measurement' = (Projected + Illustrative + Aspirational + Not demonstrated) / total claims. It depends entirely on which claims you choose to log, so log every explicit efficiency, learning and computation claim, not only the weak ones.

Sheet Codes
A1: Code | B1: Meaning | C1: Decision class
A2: I | B2: Include: empirical paper with a computational, learning, or efficiency claim about living neural tissue as a substrate | C2: Include
A3: R | B3: Include: review or roadmap that makes explicit claims about such systems | C3: Include
A4: G | B4: Include: grey literature (company page or market report) making explicit claims | C4: Include
A5: M | B5: Maybe: borderline, needs second screener or full-text check | C5: Maybe
A6: C1 | B6: Context: critique or skeptical source (not scored; used for calibration and claim-propagation arguments) | C6: Context
A7: C2 | B7: Context: commentary, editorial, or press coverage (not scored; used to trace how claims propagate) | C7: Context
A8: C3 | B8: Context: ethics or governance paper specific to organoid computing / OI (ethics arm, not scored on the main rubric) | C8: Context
A9: C4 | B9: Context: comparator literature (e.g., AI/neuromorphic energy and sample-efficiency baselines) | C9: Context
A10: E1 | B10: Exclude: no computational, learning, or efficiency claim (disease modeling, tools, engineering, theory) | C10: Exclude
A11: E2 | B11: Exclude: mentions OI only in passing | C11: Exclude
A12: E3 | B12: Exclude: duplicate or earlier version of an included record (version of record kept) | C12: Exclude
... A17: E8 | B17: Exclude: brain-organoid ethics not specific to computing / OI | C17: Exclude

Sheet Lists
A1: Score | B1: Claim tag | C1: Claim category | D1: COI / affiliation | E1: Peer-review status | F1: Yes/No | G1: Evidence basis | H1: Decision
A2: 0 | B2: Demonstrated | C2: Computational performance | D2: Company / industry source | E2: Peer-reviewed | F2: Yes | G2: Measured | H2: Include
A3: 1 | B3: Demonstrated under constraints | C3: Learning/adaptation | D3: Mixed academic-industry authors | E3: Preprint | F3: No | G3: Partially measured | H3: Maybe
A4: 2 | B4: Projected | C4: Efficiency (energy/sample/cost) | D4: Academic, declared industry COI | E4: Company/market page | F4: Unknown | G4: Projected | H4: Context
A5: NA | B5: Illustrative | C5: Sentience/intelligence | D5: Academic, none declared | G5: Cited from other work | H5: Exclude
B6: Aspirational | C6: Other | D6: Not checked | G6: None
B7: Not demonstrated
A8: Edit these lists to change dropdown options. Do not rename a value after scoring starts.
